Workbook

Sheet Staff
A1: Steve Arnott
A2: Humphrey Goodman
A3: Ted Hastings
A4: Neville Parker
A5: Christopher Foyle
A6: Robbie Lewis
A7: Richard Poole
A8: Kate Fleming
A9: Ellie Miller
A10: Jackson Brodie
A11: Cormoran Strike
A12: Marcella Backland
... A34: Adam Dalgliesh

Sheet SFIA Level
A1: Competence Level | B1: Numeric
A2: No Knowledge | B2: 0
A3: Awareness | B3: 1
A4: Working | B4: 2
A5: Practitioner | B5: 3
A6: Expert | B6: 4

Sheet Baseline
D1: Service Delivery | Q1: Service Operations | AG1: Service Resilience | AP1: Service Improvement | AU1: Future Roles
C2: Competency | D2: Service Desk | H2: Fulfilment | M2: Governance | P2: Service Delivery | Q2: Infrastructure | W2: Research Computing | AA2: Applications & Data | AG2: Resilience | AJ2: Governance | AL2: DevOps | AP2: Principal Engineers
D3: Assistant Systems Analyst | E3: Systems Analyst | F3: Senior Systems Analyst SD | G3: Service Desk Lead | H3: Senior Systems Analyst Ful | I3: Problem Analyst | J3: Fulfilment Lead | K3: Junior Systems Administrator | L3: Systems Administrator | M3: Senior Systems Administrator | N3: Service Fulfilment Lead | O3: Major incident manager | P3: Service Delivery Manager | Q3: Assistant Systems Administrator | R3: Systems Administrator | S3: Senior Systems Administrator | T3: Senior Network Adminsitrator | U3: Infrastructure Specialist | V3: Infrastructure Lead | W3: Assistant Systems Engineer | X3: Systems Engineer | Y3: Senior Systems Engineer | Z3: Research Computing Lead | AA3: Assistant Developer | AB3: Assistant Software Engineer | AC3: Software Engineer | AD3: Senior Software Engineer | AE3: Software Engineering Lead | AF3: Service Operations Manager | AG3: Service Resilience Analyst | AH3: Senior Systems Administrator (Vulnerabilities) | AI3: Junior IT Governance Administrator | AJ3: Systems Administrator (Governance) | AK3: Senior Systems Administrator (Governance) | AL3: Assistant Software Engineer DO | AM3: Software Engineer (DevOps) | AN3: Senior Software Engineer (DevOps) | AO3: Service Resilience Manager | AP3: Technical Relationship Lead | AQ3: Principal Engineer (Research Computing) | AR3: Principal Engineer (Infrastructure) | AS3: Principal Engineer (Linux) | AT3: Principal Engineer EdTech | AU3: Web Service Designer | AV3: Senior Web Service Designer | AW3: Database Administrator | AX3: Senior Database Administrator | AY3: Change and Release manager | AZ3: Solutions Architect
A4: CoSECore1 | B4: Asset Management | C4: Managing the full life cycle of assets from acquisition, operation, maintenance to disposal. | D4: Working | E4: Working | F4: Working | G4: Practitioner | H4: Practitioner | I4: Practitioner | J4: Practitioner | K4: Working | L4: Working | M4: Practitioner | N4: Practitioner | O4: Practitioner | P4: Practitioner | Q4: Working | R4: Working | S4: Working | T4: Working | U4: Working | V4: Working | W4: Working | X4: Working | Y4: Working | Z4: Working | AA4: Working | AB4: Working | AC4: Working | AD4: Working | AE4: Working | AF4: Practitioner | AG4: Working | AH4: Working | AI4: Working | AJ4: Practitioner | AK4: Expert | AL4: Working | AM4: Working | AN4: Working | AO4: Working | AP4: Practitioner | AQ4: Practitioner | AR4: Practitioner | AS4: Practitioner | AT4: Practitioner | AU4: Practitioner | AV4: Working | AW4: Working | AX4: Working | AY4: Expert | AZ4: Expert
A5: CoSECore2 | B5: Change Control | C5: Assessing risks associated with proposed changes and ensuring changes to products, services or systems are controlled and coordinated. | D5: Working | E5: Working | F5: Practitioner | G5: Expert | H5: Practitioner | I5: Practitioner | J5: Expert | K5: Working | L5: Working | M5: Practitioner | N5: Practitioner | O5: Practitioner | P5: Expert | Q5: Working | R5: Practitioner | S5: Practitioner | T5: Practitioner | U5: Practitioner | V5: Practitioner | W5: Working | X5: Working | Y5: Working | Z5: Practitioner | AA5: Working | AB5: Practitioner | AC5: Practitioner | AD5: Practitioner | AE5: Practitioner | AF5: Practitioner | AG5: Working | AH5: Practitioner | AI5: Awareness | AJ5: Working | AK5: Working | AL5: Working | AM5: Working | AN5: Working | AO5: Practitioner | AP5: Practitioner | AQ5: Practitioner | AR5: Practitioner | AS5: Practitioner | AT5: Practitioner | AU5: Practitioner | AV5: Practitioner | AW5: Practitioner | AX5: Practitioner
A6: CoSECore3 | B6: Customer Service Support | C6: Managing and operating customer service or service desk functions. | D6: Working | E6: Practitioner | F6: Practitioner | G6: Expert | H6: Practitioner | I6: Practitioner | J6: Expert | K6: Working | L6: Practitioner | M6: Practitioner | N6: Practitioner | O6: Practitioner | P6: Expert | Q6: Working | R6: Practitioner | S6: Practitioner | T6: Practitioner | U6: Practitioner | V6: Practitioner | W6: Working | X6: Practitioner | Y6: Practitioner | Z6: Practitioner | AA6: Working | AB6: Practitioner | AC6: Practitioner | AD6: Practitioner | AE6: Practitioner | AF6: Practitioner | AG6: Practitioner | AH6: Practitioner | AI6: Working | AJ6: Practitioner | AK6: Practitioner | AL6: Practitioner | AM6: Practitioner | AN6: Practitioner | AO6: Practitioner | AP6: Practitioner | AQ6: Practitioner | AR6: Practitioner | AS6: Practitioner | AT6: Practitioner | AU6: Working | AV6: Working | AW6: Working | AX6: Working | AY6: Working | AZ6: Working
A7: CoSECore5 | B7: Incident management | C7: Coordinating responses to incident reports, minimising negative impacts and restoring service as quickly as possible. | D7: Working | E7: Working | F7: Practitioner | G7: Expert | H7: Practitioner | I7: Practitioner | J7: Expert | K7: Working | L7: Practitioner | M7: Practitioner | N7: Practitioner | O7: Practitioner | P7: Practitioner | Q7: Working | R7: Working | S7: Working | T7: Working | U7: Working | V7: Working | W7: Working | X7: Working | Y7: Working | Z7: Working | AA7: Working | AB7: Working | AC7: Working | AD7: Practitioner | AE7: Practitioner | AF7: Practitioner | AG7: Working | AH7: Working | AI7: Working | AJ7: Practitioner | AK7: Practitioner | AL7: Working | AM7: Working | AN7: Working | AO7: Practitioner | AP7: Practitioner | AQ7: Practitioner | AR7: Practitioner | AS7: Practitioner | AT7: Practitioner | AU7: Practitioner | AV7: Practitioner | AW7: Practitioner | AX7: Practitioner
A8: CoSECore6 | B8: Information security | C8: Defining and operating a framework of security controls and security management strategies. | D8: Working | E8: Working | F8: Practitioner | G8: Practitioner | H8: Practitioner | I8: Practitioner | J8: Practitioner | K8: Working | L8: Working | M8: Practitioner | N8: Practitioner | O8: Practitioner | P8: Practitioner | Q8: Working | R8: Practitioner | S8: Practitioner | T8: Practitioner | U8: Practitioner | V8: Practitioner | W8: Working | X8: Practitioner | Y8: Practitioner | Z8: Practitioner | AA8: Working | AB8: Working | AC8: Practitioner | AD8: Practitioner | AE8: Practitioner | AF8: Practitioner | AG8: Practitioner | AH8: Practitioner | AI8: Working | AJ8: Working | AK8: Practitioner | AL8: Practitioner | AM8: Practitioner | AN8: Practitioner | AO8: Expert | AP8: Practitioner | AQ8: Practitioner | AR8: Practitioner | AS8: Practitioner | AT8: Practitioner | AU8: Practitioner | AV8: Practitioner | AW8: Practitioner | AX8: Practitioner | AY8: Practitioner | AZ8: Practitioner
A9: CoSECore7 | B9: Personal data protection | C9: Implementing and operating a framework of controls and management strategies to promote compliance with personal data legislation. | D9: Working | E9: Practitioner | F9: Practitioner | G9: Practitioner | H9: Practitioner | I9: Practitioner | J9: Practitioner | K9: Working | L9: Practitioner | M9: Practitioner | N9: Practitioner | O9: Practitioner | P9: Practitioner | Q9: Practitioner | R9: Practitioner | S9: Practitioner | T9: Practitioner | U9: Practitioner | V9: Practitioner | W9: Practitioner | X9: Practitioner | Y9: Practitioner | Z9: Practitioner | AA9: Working | AB9: Working | AC9: Practitioner | AD9: Practitioner | AE9: Practitioner | AF9: Practitioner | AG9: Practitioner | AH9: Practitioner | AI9: Working | AJ9: Practitioner | AK9: Practitioner | AL9: Practitioner | AM9: Practitioner | AN9: Practitioner | AO9: Expert | AP9: Practitioner | AQ9: Practitioner | AR9: Practitioner | AS9: Practitioner | AT9: Practitioner | AU9: Working | AV9: Working | AW9: Working | AX9: Working | AY9: Working | AZ9: Working
A10: CoSESvc07 | B10: Problem management | C10: Managing the life cycle of all problems that have occurred or could occur in delivering a service. | D10: Working | E10: Working | F10: Practitioner | G10: Expert | H10: Practitioner | I10: Expert | J10: Expert | K10: Working | L10: Working | M10: Working | N10: Working | O10: Practitioner | P10: Expert | Q10: Working | R10: Working | S10: Practitioner | T10: Practitioner | U10: Expert | V10: Expert | W10: Working | X10: Working | Y10: Practitioner | Z10: Working | AA10: Awareness | AB10: Working | AC10: Working | AD10: Working | AE10: Working | AF10: Working | AG10: Working | AH10: Practitioner | AI10: Working | AJ10: Working | AK10: Working | AL10: Working | AM10: Working | AN10: Working | AO10: Working | AP10: Working | AQ10: Working | AR10: Working | AS10: Working | AT10: Working | AU10: Working | AV10: Working | AW10: Working | AX10: Working | AY10: Working | AZ10: Working
A11: CoSESvc10 | B11: Service catalogue management | C11: Providing a source of consistent information about available services and products to customers and users. | D11: Working | E11: Working | F11: Practitioner | G11: Expert | H11: Practitioner | I11: Practitioner | J11: Expert | K11: Working | L11: Working | M11: Working | N11: Working | O11: Practitioner | P11: Expert | Q11: Working | R11: Working | S11: Practitioner | T11: Practitioner | U11: Expert | V11: Expert | W11: Working | X11: Working | Y11: Practitioner | Z11: Working | AA11: Awareness | AB11: Working | AC11: Working | AD11: Working | AE11: Working | AF11: Working | AG11: Working | AH11: Practitioner | AI11: Working | AJ11: Working | AK11: Working | AL11: Working | AM11: Working | AN11: Working | AO11: Working | AP11: Working | AQ11: Working | AR11: Working | AS11: Working | AT11: Working | AU11: Working | AV11: Working | AW11: Working | AX11: Working | AY11: Working | AZ11: Working
A12: CoSESvc11 | B12: Service level management | C12: Agreeing targets for service levels and assessing, monitoring, and managing the delivery of services against the targets. | D12: Working | E12: Working | F12: Practitioner | G12: Expert | H12: Working | I12: Working | J12: Expert | K12: Working | L12: Working | M12: Practitioner | N12: Practitioner | O12: Practitioner | P12: Expert | Q12: Working | R12: Working | S12: Practitioner | T12: Practitioner | U12: Expert | V12: Expert | W12: Working | X12: Working | Y12: Practitioner | Z12: Working | AA12: Awareness | AB12: Working | AC12: Working | AD12: Working | AE12: Working | AF12: Working | AG12: Working | AH12: Practitioner | AI12: No Knowledge | AJ12: Working | AK12: Working | AL12: Working | AM12: Working | AN12: Working | AO12: Working | AP12: Working | AQ12: Working | AR12: Working | AS12: Working | AT12: Working | AU12: Working | AV12: Working | AW12: Working | AX12: Working | AY12: Working | AZ12: Working
A13: CoSESvc01 | B13: Availability Management | C13: Ensuring that services deliver agreed levels of availability to meet the current and future needs of the business. | D13: Awareness | E13: Awareness | F13: Working | G13: Working | H13: Working | I13: Working | J13: Working | K13: Awareness | L13: Awareness | M13: Awareness | N13: Awareness | O13: Expert | P13: Expert | Q13: Working | R13: Working | S13: Practitioner | T13: Practitioner | U13: Expert | V13: Expert | W13: Working | X13: Working | Y13: Practitioner | Z13: Working | AA13: Awareness | AB13: Working | AC13: Working | AD13: Working | AE13: Working | AF13: Practitioner | AG13: Practitioner | AH13: Practitioner | AI13: Awareness | AJ13: Awareness | AK13: Awareness | AL13: Working | AM13: Working | AN13: Working | AO13: Expert | AP13: Practitioner | AQ13: Practitioner | AR13: Practitioner | AS13: Practitioner | AT13: Practitioner | AY13: Practitioner | AZ13: Practitioner
A14: CoSESvc02 | B14: Capacity management | C14: Ensuring that service components have the capacity and performance to meet current and planned business needs. | D14: No Knowledge | E14: No Knowledge | F14: No Knowledge | G14: No Knowledge | H14: No Knowledge | I14: No Knowledge | J14: No Knowledge | K14: Awareness | L14: No Knowledge | M14: No Knowledge | N14: No Knowledge | O14: Working | P14: Working | Q14: Working | R14: Working | S14: Practitioner | T14: Practitioner | U14: Expert | V14: Expert | W14: Working | X14: Working | Y14: Practitioner | Z14: No Knowledge | AA14: Awareness | AB14: Working | AC14: Working | AD14: Working | AE14: Working | AF14: Practitioner | AG14: No Knowledge | AH14: Practitioner | AI14: Awareness | AJ14: No Knowledge | AK14: No Knowledge | AL14: No Knowledge | AM14: No Knowledge | AN14: No Knowledge | AO14: No Knowledge | AP14: Practitioner | AQ14: Practitioner | AR14: Practitioner | AS14: Practitioner | AT14: Practitioner
A15: CoSESvc03 | B15: Configuration Management | C15: Planning, identifying, controlling, accounting for and auditing of configuration items (CIs) and their interrelationships. | D15: Awareness | E15: Awareness | F15: Awareness | G15: Awareness | H15: Awareness | I15: Awareness | J15: Awareness | K15: Awareness | L15: Awareness | M15: Working | N15: Working | O15: Working | P15: Working | Q15: Working | R15: Working | S15: Practitioner | T15: Practitioner | U15: Expert | V15: Expert | W15: Working | X15: Working | Y15: Practitioner | Z15: Working | AA15: Awareness | AB15: Working | AC15: Working | AD15: Working | AE15: Working | AF15: Practitioner | AG15: No Knowledge | AH15: Practitioner | AI15: Awareness | AJ15: No Knowledge | AK15: No Knowledge | AL15: Working | AM15: Working | AN15: Working | AO15: No Knowledge | AP15: Practitioner | AQ15: Practitioner | AR15: Practitioner | AS15: Practitioner | AT15: Practitioner
A16: CoSESvc04 | B16: Continuity Management | C16: Developing, implementing and testing a business continuity framework. | D16: Awareness | E16: Awareness | F16: Awareness | G16: Awareness | H16: Awareness | I16: Awareness | J16: Awareness | K16: Awareness | L16: Awareness | M16: Awareness | N16: Awareness | O16: Practitioner | P16: Practitioner | Q16: Working | R16: Working | S16: Practitioner | T16: Practitioner | U16: Expert | V16: Expert | W16: Working | X16: Working | Y16: Practitioner | Z16: Working | AA16: Awareness | AB16: Working | AC16: Working | AD16: Working | AE16: Working | AF16: Practitioner | AG16: Practitioner | AH16: Practitioner | AI16: Awareness | AJ16: Awareness | AK16: Awareness | AL16: Working | AM16: Working | AN16: Working | AO16: Practitioner | AP16: Practitioner | AQ16: Practitioner | AR16: Practitioner | AS16: Practitioner | AT16: Practitioner | AU16: Practitioner | AV16: Practitioner | AW16: Practitioner | AX16: Practitioner
A17: CoSECore4 | B17: Demand Management | C17: Analysing and proactively managing business demand for new services or modifications to existing service features or volumes. | D17: Awareness | E17: Awareness | F17: Awareness | G17: Awareness | H17: Awareness | I17: Awareness | J17: Awareness | K17: Awareness | L17: Working | M17: Working | N17: Working | O17: Working | P17: Expert | Q17: Working | R17: Practitioner | S17: Practitioner | T17: Practitioner | U17: Practitioner | V17: Practitioner | W17: Working | X17: Practitioner | Y17: Practitioner | Z17: Practitioner | AA17: Awareness | AB17: Working | AC17: Working | AD17: Practitioner | AE17: Practitioner | AF17: Practitioner | AG17: Practitioner | AH17: Practitioner | AI17: Awareness | AJ17: Working | AK17: Working | AL17: Practitioner | AM17: Practitioner | AN17: Practitioner | AO17: Practitioner | AP17: Practitioner | AQ17: Practitioner | AR17: Practitioner | AS17: Practitioner | AT17: Practitioner | AU17: Working | AV17: Working | AW17: Working | AX17: Working
A18: CoSESvc05 | B18: Knowledge management | C18: Managing vital knowledge to create value for the organisation. | D18: Working | E18: Working | F18: Working | G18: Working | H18: Working | I18: Working | J18: Working | K18: Working | L18: Working | M18: Working | N18: Working | O18: Working | P18: Practitioner | Q18: Working | R18: Working | S18: Practitioner | T18: Practitioner | U18: Expert | V18: Expert | W18: Working | X18: Working | Y18: Practitioner | Z18: Working | AA18: Awareness | AB18: Working | AC18: Working | AD18: Practitioner | AE18: Practitioner | AF18: Practitioner | AG18: Practitioner | AH18: Practitioner | AI18: Working | AJ18: Working | AK18: Working | AL18: Working | AM18: Working | AN18: Working | AO18: Practitioner | AP18: Practitioner | AQ18: Practitioner | AR18: Practitioner | AS18: Practitioner | AT18: Practitioner
A19: CoSESvc06 | B19: Methods and tools | C19: Ensuring methods and tools are adopted and used effectively throughout the organisation. | D19: Awareness | E19: Awareness | F19: Awareness | G19: Awareness | H19: Awareness | I19: Practitioner | J19: Awareness | K19: Awareness | L19: Working | M19: Working | N19: Practitioner | O19: Expert | P19: Expert | Q19: Working | R19: Working | S19: Practitioner | T19: Practitioner | U19: Expert | V19: Expert | W19: Working | X19: Working | Y19: Practitioner | Z19: Practitioner | AA19: Awareness | AB19: Working | AC19: Practitioner | AD19: Expert | AE19: Expert | AF19: Practitioner | AG19: Practitioner | AH19: Practitioner | AI19: Awareness | AJ19: Awareness | AK19: Awareness | AL19: Practitioner | AM19: Practitioner | AN19: Expert | AO19: Practitioner | AP19: Practitioner | AQ19: Practitioner | AR19: Practitioner | AS19: Practitioner | AT19: Practitioner
A20: CoSESvc08 | B20: Release and deployment | C20: Applying the processes, systems and functions required to make new and changed services and features available for use. | D20: No Knowledge | E20: No Knowledge | F20: No Knowledge | G20: Awareness | H20: Awareness | I20: Awareness | J20: Awareness | K20: No Knowledge | L20: No Knowledge | M20: No Knowledge | N20: No Knowledge | O20: No Knowledge | P20: Working | Q20: Working | R20: Working | S20: Practitioner | T20: Practitioner | U20: Expert | V20: Expert | W20: Working | X20: Working | Y20: Practitioner | Z20: Practitioner | AA20: Awareness | AB20: Working | AC20: Practitioner | AD20: Expert | AE20: Expert | AF20: Practitioner | AG20: Practitioner | AH20: Practitioner | AI20: N/A | AJ20: No Knowledge | AK20: No Knowledge | AL20: Practitioner | AM20: Practitioner | AN20: Expert | AO20: Expert | AP20: Practitioner | AQ20: Practitioner | AR20: Practitioner | AS20: Practitioner | AT20: Practitioner
A21: CoSESvc09 | B21: Service acceptance | C21: Managing the process to obtain formal confirmation that service acceptance criteria have been met. | D21: No Knowledge | E21: No Knowledge | F21: No Knowledge | G21: Practitioner | H21: Working | I21: Working | J21: Practitioner | K21: No Knowledge | L21: No Knowledge | M21: No Knowledge | N21: No Knowledge | O21: Practitioner | P21: Expert | Q21: Working | R21: Working | S21: Practitioner | T21: Practitioner | U21: Expert | V21: Expert | W21: Working | X21: Working | Y21: Practitioner | Z21: Practitioner | AA21: Awareness | AB21: Working | AC21: Practitioner | AD21: Expert | AE21: Expert | AF21: Practitioner | AG21: Practitioner | AH21: Practitioner | AI21: N/A | AJ21: No Knowledge | AK21: No Knowledge | AL21: Practitioner | AM21: Practitioner | AN21: Expert | AO21: Practitioner | AP21: Practitioner | AQ21: Practitioner | AR21: Practitioner | AS21: Practitioner | AT21: Practitioner
A22: CoSESvc12 | B22: Stakeholder relationship management | C22: Influencing stakeholder attitudes, decisions, and actions for mutual benefit. | D22: Awareness | E22: Working | F22: Practitioner | G22: Practitioner | H22: Practitioner | I22: Expert | J22: Practitioner | K22: Awareness | L22: Working | M22: Practitioner | N22: Practitioner | O22: Practitioner | P22: Expert | Q22: Working | R22: Working | S22: Practitioner | T22: Practitioner | U22: Expert | V22: Expert | W22: Working | X22: Working | Y22: Practitioner | Z22: Working | AA22: Awareness | AB22: Working | AC22: Working | AD22: Practitioner | AE22: Practitioner | AF22: Practitioner | AG22: Practitioner | AH22: Practitioner | AI22: Awareness | AJ22: Working | AK22: Working | AL22: Working | AM22: Working | AN22: Practitioner | AO22: Practitioner | AP22: Practitioner | AQ22: Practitioner | AR22: Practitioner | AS22: Practitioner | AT22: Practitioner | AY22: Practitioner | AZ22: Practitioner
A23: CoSESvc14 | B23: Storage management | C23: Planning, implementing and optimising the technologies and processes used for data storage. | D23: Awareness | E23: Working | F23: Working | G23: Working | H23: Working | I23: Working | J23: Working | K23: Awareness | L23: Working | M23: Working | N23: Working | O23: Working | P23: Working | Q23: Working | R23: Working | S23: Practitioner | T23: Practitioner | U23: Expert | V23: Expert | W23: Working | X23: Working | Y23: Practitioner | Z23: Awareness | AA23: Awareness | AB23: Awareness | AC23: Awareness | AD23: Awareness | AE23: Awareness | AF23: Practitioner | AG23: Awareness | AH23: Practitioner | AI23: Awareness | AJ23: Working | AK23: Working | AL23: Awareness | AM23: Awareness | AN23: Awareness | AO23: Awareness | AP23: Practitioner | AQ23: Practitioner | AR23: Practitioner | AS23: Practitioner | AT23: Practitioner
A24: CoSESec01 | B24: Digital Forensics | C24: Recovering and investigating material found in digital devices. | D24: No Knowledge | E24: No Knowledge | F24: No Knowledge | G24: No Knowledge | H24: No Knowledge | I24: No Knowledge | J24: No Knowledge | K24: No Knowledge | L24: No Knowledge | M24: No Knowledge | N24: No Knowledge | O24: No Knowledge | P24: No Knowledge | Q24: No Knowledge | R24: No Knowledge | S24: No Knowledge | T24: No Knowledge | U24: No Knowledge | V24: No Knowledge | W24: Working | X24: Working | Y24: Working | Z24: Awareness | AA24: Working | AB24: Working | AC24: Practitioner | AD24: Practitioner | AE24: Practitioner | AF24: Practitioner | AG24: Practitioner | AH24: No Knowledge | AI24: No Knowledge | AJ24: No Knowledge | AK24: No Knowledge | AL24: Working | AM24: Practitioner | AN24: Practitioner | AO24: Expert | AP24: Practitioner | AQ24: Practitioner | AR24: Practitioner | AS24: Practitioner | AT24: Practitioner | AU24: Expert | AV24: Expert | AW24: Expert | AX24: Expert
A25: CoSESec02 | B25: Penetration testing | C25: Testing the effectiveness of security controls by emulating the tools and techniques of likely attackers. | D25: No Knowledge | E25: No Knowledge | F25: No Knowledge | G25: No Knowledge | H25: No Knowledge | I25: No Knowledge | J25: No Knowledge | K25: No Knowledge | L25: No Knowledge | M25: No Knowledge | N25: No Knowledge | O25: No Knowledge | P25: Awareness | Q25: Awareness | R25: Awareness | S25: Working | T25: Working | U25: Practitioner | V25: Practitioner | W25: Awareness | X25: Awareness | Y25: Working | Z25: Working | AA25: Working | AB25: Working | AC25: Working | AD25: Practitioner | AE25: Practitioner | AF25: Practitioner | AG25: Practitioner | AH25: Working | AI25: No Knowledge | AJ25: No Knowledge | AK25: No Knowledge | AL25: Practitioner | AM25: Practitioner | AN25: Expert | AO25: Expert | AP25: Practitioner | AQ25: Practitioner | AR25: Practitioner | AS25: Practitioner | AT25: Practitioner | AU25: Expert | AV25: Expert | AW25: Expert | AX25: Expert
A26: CoSESec03 | B26: Security Operations | C26: Delivering management, technical and administrative services to implement security controls and security management strategies. | D26: Awareness | E26: Working | F26: Practitioner | G26: Practitioner | H26: Practitioner | I26: Practitioner | J26: Practitioner | K26: Awareness | L26: Working | M26: Practitioner | N26: Practitioner | O26: No Knowledge | P26: Practitioner | Q26: Awareness | R26: Working | S26: Practitioner | T26: Practitioner | U26: Practitioner | V26: Practitioner | W26: Working | X26: Working | Y26: Practitioner | Z26: Practitioner | AA26: Working | AB26: Working | AC26: Practitioner | AD26: Practitioner | AE26: Practitioner | AF26: Expert | AG26: Practitioner | AH26: Practitioner | AI26: Awareness | AJ26: Working | AK26: Practitioner | AL26: Practitioner | AM26: Practitioner | AN26: Expert | AO26: Expert | AP26: Expert | AQ26: Expert | AR26: Expert | AS26: Expert | AT26: Expert | AU26: Expert | AV26: Expert | AW26: Expert | AX26: Expert
A27: CoSESec04 | B27: Threat Intelligence | C27: Developing and sharing actionable insights on current and potential security threats to the success or integrity of an organisation. | D27: No Knowledge | E27: No Knowledge | F27: No Knowledge | G27: No Knowledge | H27: No Knowledge | I27: No Knowledge | J27: No Knowledge | K27: No Knowledge | L27: No Knowledge | M27: No Knowledge | N27: No Knowledge | O27: No Knowledge | P27: No Knowledge | Q27: No Knowledge | R27: No Knowledge | S27: Awareness | T27: Awareness | U27: Working | V27: Working | W27: Awareness | X27: Awareness | Y27: Working | Z27: Working | AA27: Awareness | AB27: Working | AC27: Working | AD27: Practitioner | AE27: Practitioner | AF27: Expert | AG27: Practitioner | AH27: Awareness | AI27: No Knowledge | AJ27: No Knowledge | AK27: No Knowledge | AL27: Practitioner | AM27: Practitioner | AN27: Expert | AO27: Expert | AP27: Expert | AQ27: Expert | AR27: Expert | AS27: Expert | AT27: Expert | AU27: Expert | AV27: Expert | AW27: Expert | AX27: Expert
A28: CoSESec05 | B28: Vulnerability assessment | C28: Identifying and classifying security vulnerabilities in networks, systems and applications and mitigating or eliminating their impact. | D28: Awareness | E28: Working | F28: Working | G28: Working | H28: Working | I28: Working | J28: Working | K28: Awareness | L28: Working | M28: Working | N28: Working | O28: No Knowledge | P28: Working | Q28: Awareness | R28: Working | S28: Practitioner | T28: Practitioner | U28: Practitioner | V28: Practitioner | W28: Working | X28: Working | Y28: Working | Z28: Practitioner | AA28: Working | AB28: Working | AC28: Working | AD28: Practitioner | AE28: Practitioner | AF28: Expert | AG28: Practitioner | AH28: Practitioner | AI28: Awareness | AJ28: Working | AK28: Working | AL28: Practitioner | AM28: Practitioner | AN28: Expert | AO28: Expert | AP28: Expert | AQ28: Expert | AR28: Expert | AS28: Expert | AT28: Expert | AU28: No Knowledge | AV28: No Knowledge | AW28: No Knowledge | AX28: No Knowledge
A29: CoSESec06 | B29: Vulnerability Research | C29: Conducting applied research to discover, evaluate and mitigate new or unknown security vulnerabilities and weaknesses. | D29: No Knowledge | E29: No Knowledge | F29: No Knowledge | G29: No Knowledge | H29: No Knowledge | I29: No Knowledge | J29: No Knowledge | K29: No Knowledge | L29: No Knowledge | M29: No Knowledge | N29: No Knowledge | O29: No Knowledge | P29: No Knowledge | Q29: No Knowledge | R29: No Knowledge | S29: Awareness | T29: Awareness | U29: Working | V29: Working | W29: Awareness | X29: Awareness | Y29: Awareness | Z29: Awareness | AA29: No Knowledge | AB29: No Knowledge | AC29: No Knowledge | AD29: No Knowledge | AE29: No Knowledge | AF29: No Knowledge | AG29: Practitioner | AH29: Awareness | AI29: No Knowledge | AJ29: No Knowledge | AK29: No Knowledge | AL29: No Knowledge | AM29: No Knowledge | AN29: No Knowledge | AO29: Expert | AP29: No Knowledge | AQ29: No Knowledge | AR29: No Knowledge | AS29: No Knowledge | AT29: No Knowledge | AU29: Awareness | AV29: Awareness | AW29: Awareness | AX29: Awareness | AY29: Awareness | AZ29: Awareness
A30: CoseMgt01 | B30: Competency assessment | C30: Assessing knowledge, skills, competency and behaviours by any means, whether formal or informal, against frameworks such as SFIA. | D30: Awareness | E30: Awareness | F30: Awareness | G30: Working | H30: Awareness | I30: Awareness | J30: Working | K30: Awareness | L30: Awareness | M30: Awareness | N30: Working | O30: Awareness | P30: Practitioner | Q30: Awareness | R30: Awareness | S30: Awareness | T30: Awareness | U30: Awareness | V30: Working | W30: Awareness | X30: Awareness | Y30: Awareness | Z30: Working | AA30: Awareness | AB30: Awareness | AC30: Awareness | AD30: Awareness | AE30: Awareness | AF30: Practitioner | AG30: Awareness | AH30: Awareness | AI30: Awareness | AJ30: Awareness | AK30: Working | AL30: Awareness | AM30: Awareness | AN30: Awareness | AO30: Practitioner | AP30: Practitioner | AQ30: Working | AR30: Working | AS30: Working | AT30: Working | AU30: Awareness | AV30: Awareness | AW30: Awareness | AX30: Awareness | AY30: Awareness | AZ30: Awareness
A31: CoseMgt03 | B31: Financial management | C31: Supporting the effective use and control of financial resources. | D31: Awareness | E31: Awareness | F31: Awareness | G31: Working | H31: Awareness | I31: Awareness | J31: Working | K31: Working | L31: Working | M31: Working | N31: Working | O31: Awareness | P31: Awareness | Q31: Awareness | R31: Awareness | S31: Awareness | T31: Awareness | U31: Working | V31: Working | W31: No Knowledge | X31: No Knowledge | Y31: No Knowledge | Z31: Working | AA31: No Knowledge | AB31: No Knowledge | AC31: No Knowledge | AD31: No Knowledge | AE31: No Knowledge | AF31: Awareness | AG31: Awareness | AH31: Awareness | AI31: Awareness | AJ31: Working | AK31: Working | AL31: No Knowledge | AM31: No Knowledge | AN31: No Knowledge | AO31: Awareness | AP31: Awareness | AQ31: Practitioner | AR31: Practitioner | AS31: Practitioner | AT31: Practitioner | AU31: No Knowledge | AV31: No Knowledge | AW31: No Knowledge | AX31: No Knowledge | AY31: N/A | AZ31: N/A
A32: CoseMgt04 | B32: Organisation design and implementation | C32: Planning, designing and implementing an integrated organisation structure and culture. | D32: No Knowledge | E32: No Knowledge | F32: No Knowledge | G32: No Knowledge | H32: No Knowledge | I32: No Knowledge | J32: No Knowledge | K32: No Knowledge | L32: No Knowledge | M32: No Knowledge | N32: No Knowledge | O32: No Knowledge | P32: Awareness | Q32: No Knowledge | R32: No Knowledge | S32: No Knowledge | T32: No Knowledge | U32: No Knowledge | V32: No Knowledge | W32: No Knowledge | X32: No Knowledge | Y32: No Knowledge | Z32: No Knowledge | AA32: No Knowledge | AB32: No Knowledge | AC32: No Knowledge | AD32: No Knowledge | AE32: No Knowledge | AF32: Awareness | AG32: No Knowledge | AH32: No Knowledge | AI32: No Knowledge | AJ32: No Knowledge | AK32: No Knowledge | AL32: No Knowledge | AM32: No Knowledge | AN32: No Knowledge | AO32: Awareness | AP32: Awareness | AQ32: No Knowledge | AR32: No Knowledge | AS32: No Knowledge | AT32: No Knowledge | AU32: No Knowledge | AV32: No Knowledge | AW32: No Knowledge | AX32: No Knowledge | AY32: N/A | AZ32: N/A
A33: CoseMgt05 | B33: Organisational capability development | C33: Providing leadership, advice and implementation support to assess organisational capabilities and to identify, prioritise and implement improvements. | D33: No Knowledge | E33: No Knowledge | F33: No Knowledge | G33: No Knowledge | H33: No Knowledge | I33: No Knowledge | J33: No Knowledge | K33: No Knowledge | L33: No Knowledge | M33: No Knowledge | N33: No Knowledge | O33: No Knowledge | P33: Awareness | Q33: No Knowledge | R33: No Knowledge | S33: No Knowledge | T33: No Knowledge | U33: No Knowledge | V33: No Knowledge | W33: No Knowledge | X33: No Knowledge | Y33: No Knowledge | Z33: No Knowledge | AA33: No Knowledge | AB33: No Knowledge | AC33: No Knowledge | AD33: No Knowledge | AE33: No Knowledge | AF33: Awareness | AG33: No Knowledge | AH33: No Knowledge | AI33: No Knowledge | AJ33: No Knowledge | AK33: No Knowledge | AL33: No Knowledge | AM33: No Knowledge | AN33: No Knowledge | AO33: Awareness | AP33: Awareness | AQ33: No Knowledge | AR33: No Knowledge | AS33: No Knowledge | AT33: No Knowledge | AU33: No Knowledge | AV33: No Knowledge | AW33: No Knowledge | AX33: No Knowledge | AY33: N/A | AZ33: N/A
A34: CoseMgt06 | B34: Organisational change management | C34: Planning, designing and implementing activities to transition the organisation and people to the required future state. | D34: No Knowledge | E34: No Knowledge | F34: No Knowledge | G34: Awareness | H34: No Knowledge | I34: No Knowledge | J34: Awareness | K34: No Knowledge | L34: No Knowledge | M34: No Knowledge | N34: No Knowledge | O34: No Knowledge | P34: Working | Q34: No Knowledge | R34: No Knowledge | S34: No Knowledge | T34: No Knowledge | U34: Awareness | V34: Awareness | W34: No Knowledge | X34: No Knowledge | Y34: No Knowledge | Z34: Awareness | AA34: No Knowledge | AB34: No Knowledge | AC34: No Knowledge | AD34: No Knowledge | AE34: No Knowledge | AF34: Working | AG34: No Knowledge | AH34: No Knowledge | AI34: N/A | AJ34: No Knowledge | AK34: No Knowledge | AL34: No Knowledge | AM34: No Knowledge | AN34: No Knowledge | AO34: No Knowledge | AP34: Awareness | AQ34: No Knowledge | AR34: No Knowledge | AS34: No Knowledge | AT34: No Knowledge | AU34: No Knowledge | AV34: No Knowledge | AW34: No Knowledge | AX34: No Knowledge | AY34: N/A | AZ34: N/A
A35: CoseMgt07 | B35: Performance Management | C35: Improving organisational performance by developing the performance of individuals and workgroups to meet agreed objectives with measurable results. | D35: No Knowledge | E35: No Knowledge | F35: No Knowledge | G35: Working | H35: No Knowledge | I35: No Knowledge | J35: Working | K35: No Knowledge | L35: No Knowledge | M35: No Knowledge | N35: Working | O35: No Knowledge | P35: Working | Q35: No Knowledge | R35: No Knowledge | S35: No Knowledge | T35: No Knowledge | U35: Awareness | V35: Working | W35: No Knowledge | X35: No Knowledge | Y35: No Knowledge | Z35: Working | AA35: No Knowledge | AB35: Awareness | AC35: Awareness | AD35: Awareness | AE35: Awareness | AF35: Working | AG35: No Knowledge | AH35: No Knowledge | AI35: N/A | AJ35: No Knowledge | AK35: Working | AL35: No Knowledge | AM35: No Knowledge | AN35: No Knowledge | AO35: Working | AP35: No Knowledge | AQ35: No Knowledge | AR35: No Knowledge | AS35: No Knowledge | AT35: No Knowledge | AU35: Awareness | AV35: Awareness | AW35: Awareness | AX35: Awareness | AY35: Awareness | AZ35: Awareness
A36: CoseMgt08 | B36: Professional Development | C36: Facilitating the professional development of individuals in line with their career goals and organisational requirements. | D36: Awareness | E36: Awareness | F36: Awareness | G36: Working | H36: Awareness | I36: Awareness | J36: Working | K36: No Knowledge | L36: No Knowledge | M36: No Knowledge | N36: Working | O36: No Knowledge | P36: Practitioner | Q36: Awareness | R36: Awareness | S36: Awareness | T36: Awareness | U36: Awareness | V36: Working | W36: Awareness | X36: Awareness | Y36: Awareness | Z36: Working | AA36: Working | AB36: Working | AC36: Working | AD36: Working | AE36: Working | AF36: Practitioner | AG36: Awareness | AH36: Awareness | AI36: Awareness | AJ36: Awareness | AK36: Awareness | AL36: Awareness | AM36: Awareness | AN36: Awareness | AO36: Practitioner | AP36: Awareness | AQ36: Awareness | AR36: Awareness | AS36: Awareness | AT36: Awareness | AU36: N/A | AV36: N/A | AW36: N/A | AX36: N/A | AY36: N/A | AZ36: N/A
A37: CoseMgt09 | B37: Strategic Planning | C37: Creating and maintaining a strategy to align organisational actions, plans and resources with business objectives. | D37: No Knowledge | E37: No Knowledge | F37: No Knowledge | G37: Awareness | H37: No Knowledge | I37: No Knowledge | J37: Awareness | K37: No Knowledge | L37: No Knowledge | M37: No Knowledge | N37: No Knowledge | O37: No Knowledge | P37: Working | Q37: No Knowledge | R37: No Knowledge | S37: No Knowledge | T37: No Knowledge | U37: Awareness | V37: Awareness | W37: No Knowledge | X37: No Knowledge | Y37: No Knowledge | Z37: Awareness | AA37: No Knowledge | AB37: No Knowledge | AC37: No Knowledge | AD37: No Knowledge | AE37: No Knowledge | AF37: Working | AG37: No Knowledge | AH37: No Knowledge | AI37: N/A | AJ37: No Knowledge | AK37: No Knowledge | AL37: No Knowledge | AM37: No Knowledge | AN37: No Knowledge | AO37: Working | AP37: Working | AQ37: Working | AR37: Working | AS37: Working | AT37: Working | AU37: N/A | AV37: N/A | AW37: N/A | AX37: N/A | AY37: N/A | AZ37: N/A
A38: CoseMgt09 | B38: Workforce Planning | C38: Estimating the demand for people and skills and planning the supply needed to meet that demand. | D38: No Knowledge | E38: No Knowledge | F38: No Knowledge | G38: Working | H38: No Knowledge | I38: No Knowledge | J38: Working | K38: No Knowledge | L38: No Knowledge | M38: No Knowledge | N38: Working | O38: No Knowledge | P38: Practitioner | Q38: No Knowledge | R38: No Knowledge | S38: No Knowledge | T38: No Knowledge | U38: Awareness | V38: Working | W38: No Knowledge | X38: No Knowledge | Y38: No Knowledge | Z38: Working | AA38: No Knowledge | AB38: No Knowledge | AC38: No Knowledge | AD38: No Knowledge | AE38: No Knowledge | AF38: Practitioner | AG38: No Knowledge | AH38: No Knowledge | AI38: N/A | AJ38: No Knowledge | AK38: Working | AL38: No Knowledge | AM38: No Knowledge | AN38: No Knowledge | AO38: Practitioner | AP38: Working | AQ38: Working | AR38: Working | AS38: Working | AT38: Working
A39: CoSEGov01 | B39: Audit | C39: Delivering independent, risk-based assessments of the effectiveness of processes, the controls, and the compliance environment of an organisation. | D39: Awareness | E39: Awareness | F39: Working | G39: Working | H39: Working | I39: Working | J39: Working | K39: Awareness | L39: Working | M39: Working | N39: Practitioner | O39: No Knowledge | P39: Working | Q39: Working | R39: Working | S39: Working | T39: Working | U39: Working | V39: Working | W39: Working | X39: Working | Y39: Working | Z39: Practitioner | AA39: Awareness | AB39: Working | AC39: Working | AD39: Practitioner | AE39: Practitioner | AF39: Practitioner | AG39: Practitioner | AH39: Working | AI39: Awareness | AJ39: Working | AK39: Working | AL39: Working | AM39: Working | AN39: Practitioner | AO39: Expert | AP39: Practitioner | AQ39: Practitioner | AR39: Practitioner | AS39: Practitioner | AT39: Practitioner | AY39: Practitioner | AZ39: Practitioner
A40: CoSEGov02 | B40: Contract management | C40: Managing and controlling the operation of formal contracts for the supply of products and services. | D40: No Knowledge | E40: No Knowledge | F40: No Knowledge | G40: No Knowledge | H40: No Knowledge | I40: No Knowledge | J40: No Knowledge | K40: Awareness | L40: Working | M40: Working | N40: Expert | O40: No Knowledge | P40: Working | Q40: Working | R40: Working | S40: Working | T40: Working | U40: Working | V40: Working | W40: Awareness | X40: Awareness | Y40: Awareness | Z40: Practitioner | AA40: Awareness | AB40: Awareness | AC40: Awareness | AD40: Practitioner | AE40: Practitioner | AF40: Practitioner | AG40: Practitioner | AH40: Working | AI40: Working | AJ40: Working | AK40: Practitioner | AL40: Working | AM40: No Knowledge | AN40: Practitioner | AO40: Practitioner | AP40: Practitioner | AQ40: Practitioner | AR40: Practitioner | AS40: Practitioner | AT40: Practitioner | AY40: Practitioner | AZ40: Practitioner
A41: CoSEGov03 | B41: Feasibility assessment | C41: Defining, evaluating and describing business change options for financial, technical and business feasibility, and strategic alignment. | D41: No Knowledge | E41: No Knowledge | F41: No Knowledge | G41: No Knowledge | H41: No Knowledge | I41: No Knowledge | J41: No Knowledge | K41: Awareness | L41: Working | M41: Working | N41: Working | O41: No Knowledge | P41: Working | Q41: Awareness | R41: Awareness | S41: Working | T41: Working | U41: Working | V41: Working | W41: Awareness | X41: Working | Y41: Awareness | Z41: Practitioner | AA41: Awareness | AB41: Working | AC41: Working | AD41: Practitioner | AE41: Practitioner | AF41: Practitioner | AG41: Working | AH41: Working | AI41: N/A | AJ41: No Knowledge | AK41: No Knowledge | AL41: Working | AM41: No Knowledge | AN41: Practitioner | AO41: Working | AP41: Practitioner | AQ41: Practitioner | AR41: Practitioner | AS41: Practitioner | AT41: Practitioner
A42: CoSEGov04 | B42: Governance | C42: Defining and operating a framework for making decisions, managing stakeholder relationships, and identifying legitimate authority. | D42: Awareness | E42: Awareness | F42: Awareness | G42: Working | H42: Awareness | I42: Awareness | J42: Working | K42: Awareness | L42: Working | M42: Working | N42: Working | O42: No Knowledge | P42: Working | Q42: Awareness | R42: Awareness | S42: Awareness | T42: Awareness | U42: Practitioner | V42: Practitioner | W42: Working | X42: Working | Y42: Awareness | Z42: Practitioner | AA42: Awareness | AB42: Working | AC42: Working | AD42: Practitioner | AE42: Practitioner | AF42: Practitioner | AG42: Practitioner | AH42: Awareness | AI42: Working | AJ42: Practitioner | AK42: Expert | AL42: Working | AM42: Working | AN42: Practitioner | AO42: Practitioner | AP42: Practitioner | AQ42: Practitioner | AR42: Practitioner | AS42: Practitioner | AT42: Practitioner
A43: CoSEGov05 | B43: Risk management | C43: Planning and implementing organisation-wide processes and procedures for the management of risk to the success or integrity of the enterprise. | D43: No Knowledge | E43: No Knowledge | F43: No Knowledge | G43: No Knowledge | H43: No Knowledge | I43: No Knowledge | J43: No Knowledge | K43: No Knowledge | L43: No Knowledge | M43: No Knowledge | N43: Working | O43: No Knowledge | P43: Practitioner | Q43: Awareness | R43: Awareness | S43: Awareness | T43: Awareness | U43: Practitioner | V43: Practitioner | W43: Working | X43: Working | Y43: No Knowledge | Z43: Practitioner | AA43: Awareness | AB43: Working | AC43: Working | AD43: Working | AE43: Working | AF43: Practitioner | AG43: Practitioner | AH43: Awareness | AI43: Awareness | AJ43: Working | AK43: Working | AL43: Working | AM43: Working | AN43: Practitioner | AO43: Practitioner | AP43: Practitioner | AQ43: Practitioner | AR43: Practitioner | AS43: Practitioner | AT43: Practitioner
A44: CoSEGov06 | B44: Sourcing | C44: Managing, or providing advice on, the procurement or commissioning of products and services. | D44: Awareness | E44: Awareness | F44: Awareness | G44: Awareness | H44: Awareness | I44: Awareness | J44: Awareness | K44: Awareness | L44: Working | M44: Practitioner | N44: Practitioner | O44: No Knowledge | P44: Practitioner | Q44: Awareness | R44: Awareness | S44: Awareness | T44: Awareness | U44: Awareness | V44: Awareness | W44: Working | X44: Working | Y44: Awareness | Z44: Practitioner | AA44: Awareness | AB44: Working | AC44: Working | AD44: Practitioner | AE44: Practitioner | AF44: Practitioner | AG44: Working | AH44: Awareness | AI44: Awareness | AJ44: Working | AK44: Working | AL44: Working | AM44: Working | AN44: Practitioner | AO44: Practitioner | AP44: Practitioner | AQ44: Practitioner | AR44: Practitioner | AS44: Practitioner | AT44: Practitioner
A45: CoSEGov07 | B45: Supplier management | C45: Aligning the organisation’s supplier performance objectives and activities with sourcing strategies and plans, balancing costs, efficiencies and service quality. | D45: No Knowledge | E45: Awareness | F45: Awareness | G45: Working | H45: Awareness | I45: Awareness | J45: Working | K45: Awareness | L45: Practitioner | M45: Practitioner | N45: Practitioner | O45: Practitioner | P45: Practitioner | Q45: Awareness | R45: Working | S45: Working | T45: Working | U45: Practitioner | V45: Practitioner | W45: Working | X45: Working | Y45: Awareness | Z45: Practitioner | AA45: Awareness | AB45: Working | AC45: Working | AD45: Practitioner | AE45: Practitioner | AF45: Practitioner | AG45: Practitioner | AH45: Working | AI45: Awareness | AJ45: Practitioner | AK45: Practitioner | AL45: Working | AM45: Working | AN45: Practitioner | AO45: Practitioner | AP45: Practitioner | AQ45: Practitioner | AR45: Practitioner | AS45: Practitioner | AT45: Practitioner | AU45: Awareness | AV45: Awareness | AW45: Awareness | AX45: Awareness | AY45: Awareness | AZ45: Working
A46: CoSEGov08 | B46: Sustainability | C46: Providing advice, assistance and leadership to enable the organisation to minimise negative environmental impact. | D46: Awareness | E46: Awareness | F46: Awareness | G46: Awareness | H46: Awareness | I46: Awareness | J46: Awareness | K46: Awareness | L46: Awareness | M46: Awareness | N46: Awareness | O46: Awareness | P46: Awareness | Q46: Awareness | R46: Awareness | S46: Awareness | T46: Awareness | U46: Awareness | V46: Awareness | W46: Awareness | X46: Awareness | Y46: Awareness | Z46: Awareness | AA46: Awareness | AB46: Awareness | AC46: Awareness | AD46: Awareness | AE46: Awareness | AF46: Awareness | AG46: Awareness | AH46: Awareness | AI46: Awareness | AJ46: Awareness | AK46: Awareness | AL46: Awareness | AM46: Awareness | AN46: Awareness | AO46: Awareness | AP46: Awareness | AQ46: Awareness | AR46: Awareness | AS46: Awareness | AT46: Awareness | AU46: Working | AV46: Working | AW46: Practitioner | AX46: Practitioner | AY46: Practitioner | AZ46: Practitioner
A47: CoSETec15 | B47: Acceptance testing | C47: Validating systems, products, business processes or services to determine whether the acceptance criteria have been satisfied. | D47: Awareness | E47: Awareness | F47: Awareness | G47: Awareness | H47: Awareness | I47: Awareness | J47: Awareness | K47: Awareness | L47: Working | M47: Working | N47: Practitioner | O47: No Knowledge | P47: Practitioner | Q47: Working | R47: Working | S47: Working | T47: Working | U47: Working | V47: Working | W47: Working | X47: Working | Y47: Working | Z47: Working | AA47: Awareness | AB47: Working | AC47: Working | AD47: Practitioner | AE47: Practitioner | AF47: Practitioner | AG47: Practitioner | AH47: Working | AI47: N/A | AJ47: No Knowledge | AK47: No Knowledge | AL47: Working | AM47: Working | AN47: Practitioner | AO47: Practitioner | AP47: Practitioner | AQ47: Practitioner | AR47: Practitioner | AS47: Practitioner | AT47: Practitioner | AU47: Practitioner | AV47: Practitioner | AW47: Practitioner | AX47: Practitioner
A48: CoSETec16 | B48: Application support | C48: Delivering management, technical and administrative services to support and maintain live applications. | D48: Awareness | E48: Working | F48: Working | G48: Working | H48: Working | I48: Working | J48: Working | K48: Awareness | L48: Working | M48: Working | N48: Working | O48: No Knowledge | P48: Working | Q48: Awareness | R48: Awareness | S48: Awareness | T48: Awareness | U48: Awareness | V48: Awareness | W48: Awareness | X48: Working | Y48: Working | Z48: Working | AA48: Awareness | AB48: Working | AC48: Practitioner | AD48: Practitioner | AE48: Practitioner | AF48: Working | AG48: Awareness | AH48: Awareness | AI48: N/A | AJ48: No Knowledge | AK48: No Knowledge | AL48: Practitioner | AM48: Practitioner | AN48: Practitioner | AO48: Awareness | AP48: Practitioner | AQ48: Working | AR48: Working | AS48: Working | AT48: Working | AU48: N/A | AV48: N/A | AW48: N/A | AX48: N/A | AY48: No Knowledge | AZ48: No Knowledge
A49: CoSETec17 | B49: Data Engineering | C49: Designing, building, operationalising, securing and monitoring data pipelines and data stores. | D49: No Knowledge | E49: No Knowledge | F49: No Knowledge | G49: No Knowledge | H49: No Knowledge | I49: No Knowledge | J49: No Knowledge | K49: No Knowledge | L49: No Knowledge | M49: No Knowledge | N49: No Knowledge | O49: No Knowledge | P49: No Knowledge | Q49: No Knowledge | R49: No Knowledge | S49: No Knowledge | T49: No Knowledge | U49: No Knowledge | V49: No Knowledge | W49: No Knowledge | X49: No Knowledge | Y49: No Knowledge | Z49: Practitioner | AA49: No Knowledge | AB49: Awareness | AC49: Awareness | AD49: Awareness | AE49: Awareness | AF49: No Knowledge | AG49: No Knowledge | AH49: No Knowledge | AI49: No Knowledge | AJ49: No Knowledge | AK49: No Knowledge | AL49: Working | AM49: Practitioner | AN49: Practitioner | AO49: No Knowledge | AP49: No Knowledge | AQ49: No Knowledge | AR49: No Knowledge | AS49: No Knowledge | AT49: No Knowledge | AU49: No Knowledge | AV49: No Knowledge | AW49: No Knowledge | AX49: No Knowledge | AY49: No Knowledge | AZ49: No Knowledge
A50: CoSETec18 | B50: Data Management | C50: Developing and implementing plans, policies, and practices that control, protect and optimise the value of data assets. | D50: No Knowledge | E50: No Knowledge | F50: No Knowledge | G50: No Knowledge | H50: No Knowledge | I50: No Knowledge | J50: No Knowledge | K50: No Knowledge | L50: No Knowledge | M50: No Knowledge | N50: No Knowledge | O50: No Knowledge | P50: No Knowledge | Q50: No Knowledge | R50: No Knowledge | S50: No Knowledge | T50: No Knowledge | U50: No Knowledge | V50: No Knowledge | W50: No Knowledge | X50: No Knowledge | Y50: No Knowledge | Z50: Practitioner | AA50: No Knowledge | AB50: No Knowledge | AC50: No Knowledge | AD50: No Knowledge | AE50: No Knowledge | AF50: No Knowledge | AG50: No Knowledge | AH50: No Knowledge | AI50: No Knowledge | AJ50: No Knowledge | AK50: No Knowledge | AL50: No Knowledge | AM50: No Knowledge | AN50: No Knowledge | AO50: No Knowledge | AP50: No Knowledge | AQ50: No Knowledge | AR50: No Knowledge | AS50: No Knowledge | AT50: No Knowledge | AU50: No Knowledge | AV50: No Knowledge | AW50: No Knowledge | AX50: No Knowledge | AY50: No Knowledge | AZ50: No Knowledge
A51: CoSETec19 | B51: Data Modelling and Design | C51: Developing models and diagrams to represent and communicate data requirements and data assets. | D51: No Knowledge | E51: No Knowledge | F51: No Knowledge | G51: No Knowledge | H51: No Knowledge | I51: No Knowledge | J51: No Knowledge | K51: No Knowledge | L51: No Knowledge | M51: No Knowledge | N51: No Knowledge | O51: No Knowledge | P51: No Knowledge | Q51: No Knowledge | R51: No Knowledge | S51: No Knowledge | T51: No Knowledge | U51: No Knowledge | V51: No Knowledge | W51: No Knowledge | X51: No Knowledge | Y51: No Knowledge | Z51: Practitioner | AA51: No Knowledge | AB51: No Knowledge | AC51: No Knowledge | AD51: No Knowledge | AE51: No Knowledge | AF51: No Knowledge | AG51: No Knowledge | AH51: No Knowledge | AI51: No Knowledge | AJ51: No Knowledge | AK51: No Knowledge | AL51: No Knowledge | AM51: No Knowledge | AN51: No Knowledge | AO51: No Knowledge | AP51: No Knowledge | AQ51: No Knowledge | AR51: No Knowledge | AS51: No Knowledge | AT51: No Knowledge | AU51: No Knowledge | AV51: No Knowledge | AW51: No Knowledge | AX51: No Knowledge | AY51: No Knowledge | AZ51: No Knowledge
A52: CoSETec20 | B52: Data science | C52: Applying mathematics, statistics, data mining and predictive modelling techniques to gain insights, predict behaviours and generate value from data. | D52: No Knowledge | E52: No Knowledge | F52: No Knowledge | G52: No Knowledge | H52: No Knowledge | I52: No Knowledge | J52: No Knowledge | K52: No Knowledge | L52: No Knowledge | M52: No Knowledge | N52: No Knowledge | O52: No Knowledge | P52: No Knowledge | Q52: No Knowledge | R52: No Knowledge | S52: No Knowledge | T52: No Knowledge | U52: No Knowledge | V52: No Knowledge | W52: No Knowledge | X52: No Knowledge | Y52: No Knowledge | Z52: Practitioner | AA52: No Knowledge | AB52: No Knowledge | AC52: No Knowledge | AD52: No Knowledge | AE52: No Knowledge | AF52: No Knowledge | AG52: No Knowledge | AH52: No Knowledge | AI52: No Knowledge | AJ52: No Knowledge | AK52: No Knowledge | AL52: No Knowledge | AM52: No Knowledge | AN52: No Knowledge | AO52: No Knowledge | AP52: No Knowledge | AQ52: No Knowledge | AR52: No Knowledge | AS52: No Knowledge | AT52: No Knowledge | AU52: No Knowledge | AV52: No Knowledge | AW52: No Knowledge | AX52: No Knowledge | AY52: No Knowledge | AZ52: No Knowledge
A53: CoSETec21 | B53: Data visualisation | C53: Facilitating understanding of data by displaying concepts, ideas, and facts using graphical representations. | D53: No Knowledge | E53: No Knowledge | F53: No Knowledge | G53: No Knowledge | H53: No Knowledge | I53: No Knowledge | J53: No Knowledge | K53: No Knowledge | L53: No Knowledge | M53: No Knowledge | N53: No Knowledge | O53: No Knowledge | P53: No Knowledge | Q53: No Knowledge | R53: No Knowledge | S53: No Knowledge | T53: No Knowledge | U53: No Knowledge | V53: No Knowledge | W53: No Knowledge | X53: No Knowledge | Y53: No Knowledge | Z53: Practitioner | AA53: No Knowledge | AB53: No Knowledge | AC53: No Knowledge | AD53: No Knowledge | AE53: No Knowledge | AF53: No Knowledge | AG53: No Knowledge | AH53: No Knowledge | AI53: No Knowledge | AJ53: No Knowledge | AK53: No Knowledge | AL53: No Knowledge | AM53: No Knowledge | AN53: No Knowledge | AO53: No Knowledge | AP53: No Knowledge | AQ53: No Knowledge | AR53: No Knowledge | AS53: No Knowledge | AT53: No Knowledge | AU53: Working | AV53: Working | AW53: Practitioner | AX53: Practitioner | AY53: Awareness | AZ53: Awareness
A54: CoSETec22 | B54: Database Administration | C54: Installing, configuring, monitoring, maintaining and improving the performance of databases and data stores. | D54: No Knowledge | E54: No Knowledge | F54: No Knowledge | G54: No Knowledge | H54: No Knowledge | I54: No Knowledge | J54: No Knowledge | K54: No Knowledge | L54: No Knowledge | M54: No Knowledge | N54: No Knowledge | O54: No Knowledge | P54: No Knowledge | Q54: Working | R54: Working | S54: Working | T54: Working | U54: Working | V54: Working | W54: Working | X54: Working | Y54: Working | Z54: Working | AA54: Awareness | AB54: Awareness | AC54: Working | AD54: Working | AE54: Working | AF54: Awareness | AG54: Awareness | AH54: Working | AI54: No Knowledge | AJ54: No Knowledge | AK54: No Knowledge | AL54: Working | AM54: Working | AN54: Working | AO54: Awareness | AP54: Awareness | AQ54: Practitioner | AR54: Practitioner | AS54: Practitioner | AT54: Practitioner | AU54: No Knowledge | AV54: No Knowledge | AW54: No Knowledge | AX54: No Knowledge | AY54: N/A | AZ54: N/A
A55: CoSETec23 | B55: Database Design | C55: Specifying, designing and maintaining mechanisms for storing and accessing data. | D55: No Knowledge | E55: No Knowledge | F55: No Knowledge | G55: No Knowledge | H55: No Knowledge | I55: No Knowledge | J55: No Knowledge | K55: No Knowledge | L55: No Knowledge | M55: No Knowledge | N55: No Knowledge | O55: No Knowledge | P55: No Knowledge | Q55: No Knowledge | R55: No Knowledge | S55: No Knowledge | T55: No Knowledge | U55: No Knowledge | V55: No Knowledge | W55: No Knowledge | X55: Awareness | Y55: Awareness | Z55: No Knowledge | AA55: No Knowledge | AB55: Awareness | AC55: Working | AD55: Working | AE55: Working | AF55: No Knowledge | AG55: Working | AH55: No Knowledge | AI55: No Knowledge | AJ55: No Knowledge | AK55: No Knowledge | AL55: No Knowledge | AM55: No Knowledge | AN55: No Knowledge | AO55: Practitioner | AP55: No Knowledge | AQ55: No Knowledge | AR55: No Knowledge | AS55: No Knowledge | AT55: No Knowledge
A56: CoSETec24 | B56: Hardware design | C56: Specifying a hardware design model for a defined system architecture. | D56: No Knowledge | E56: No Knowledge | F56: No Knowledge | G56: No Knowledge | H56: No Knowledge | I56: Working | J56: No Knowledge | K56: No Knowledge | L56: No Knowledge | M56: No Knowledge | N56: No Knowledge | O56: No Knowledge | P56: No Knowledge | Q56: Working | R56: Practitioner | S56: Practitioner | T56: Working | U56: Expert | V56: Practitioner | W56: Awareness | X56: Working | Y56: Practitioner | Z56: Working | AA56: No Knowledge | AB56: No Knowledge | AC56: No Knowledge | AD56: No Knowledge | AE56: No Knowledge | AF56: Practitioner | AG56: Working | AH56: Practitioner | AI56: No Knowledge | AJ56: No Knowledge | AK56: No Knowledge | AL56: No Knowledge | AM56: No Knowledge | AN56: No Knowledge | AO56: Working | AP56: Practitioner | AQ56: Expert | AR56: Expert | AS56: Practitioner | AT56: Practitioner
A57: CoSETec25 | B57: High Performance Computing | C57: Using advanced computer systems and special programming techniques to solve complex computational problems. | D57: Awareness | E57: Awareness | F57: Awareness | G57: Awareness | H57: Awareness | I57: Awareness | J57: Awareness | K57: Awareness | L57: Awareness | M57: Awareness | N57: Awareness | O57: No Knowledge | P57: Awareness | Q57: Awareness | R57: Awareness | S57: Awareness | T57: Awareness | U57: Working | V57: Working | W57: Working | X57: Practitioner | Y57: Expert | Z57: Working | AA57: No Knowledge | AB57: No Knowledge | AC57: No Knowledge | AD57: No Knowledge | AE57: No Knowledge | AF57: Practitioner | AG57: Awareness | AH57: Awareness | AI57: Awareness | AJ57: Awareness | AK57: Awareness | AL57: No Knowledge | AM57: No Knowledge | AN57: No Knowledge | AO57: Awareness | AP57: Working | AQ57: Expert | AR57: Working | AS57: Practitioner | AT57: Practitioner
A58: CoSETec25 | B58: Research Computing | C58: #N/A | D58: Awareness | E58: Awareness | F58: Awareness | G58: Awareness | H58: Awareness | I58: Awareness | J58: Awareness | K58: Awareness | L58: Awareness | M58: Awareness | N58: Awareness | O58: No Knowledge | P58: Awareness | Q58: Awareness | R58: Awareness | S58: Awareness | T58: Awareness | U58: Working | V58: Working | W58: Working | X58: Practitioner | Y58: Expert | Z58: Working | AA58: No Knowledge | AB58: No Knowledge | AC58: Awareness | AD58: Awareness | AE58: Awareness | AF58: Practitioner | AG58: Awareness | AH58: Awareness | AI58: Awareness | AJ58: Awareness | AK58: Awareness | AL58: No Knowledge | AM58: No Knowledge | AN58: No Knowledge | AO58: Awareness | AP58: Working | AQ58: Expert | AR58: Working | AS58: Practitioner | AT58: Practitioner | AY58: Expert | AZ58: Expert
A59: CoSETec26 | B59: Information assurance | C59: Protecting against and managing risks related to the use, storage and transmission of data and information systems. | D59: Working | E59: Working | F59: Practitioner | G59: Practitioner | H59: Practitioner | I59: Practitioner | J59: Practitioner | K59: Working | L59: Working | M59: Working | N59: Practitioner | O59: Practitioner | P59: Practitioner | Q59: Working | R59: Working | S59: Practitioner | T59: Working | U59: Practitioner | V59: Practitioner | W59: Working | X59: Practitioner | Y59: Practitioner | Z59: Practitioner | AA59: Awareness | AB59: Working | AC59: Practitioner | AD59: Practitioner | AE59: Practitioner | AF59: Expert | AG59: Expert | AH59: Practitioner | AI59: Working | AJ59: Working | AK59: Practitioner | AL59: Practitioner | AM59: No Knowledge | AN59: Practitioner | AO59: Expert | AP59: Practitioner | AQ59: Expert | AR59: Expert | AS59: Expert | AT59: Expert | AY59: Practitioner | AZ59: Practitioner
A60: CoSETec27 | B60: Information management | C60: Planning, implementing and controlling the full life cycle management of digitally organised information and records. | D60: Awareness | E60: Awareness | F60: Awareness | G60: Awareness | H60: Awareness | I60: Awareness | J60: Awareness | K60: Awareness | L60: Awareness | M60: Awareness | N60: Awareness | O60: Awareness | P60: Awareness | Q60: Working | R60: Practitioner | S60: Practitioner | T60: Working | U60: Expert | V60: Practitioner | W60: Working | X60: Practitioner | Y60: Practitioner | Z60: Practitioner | AA60: Awareness | AB60: Working | AC60: Practitioner | AD60: Practitioner | AE60: Practitioner | AF60: Practitioner | AG60: Practitioner | AH60: Practitioner | AI60: Awareness | AJ60: Awareness | AK60: Awareness | AL60: Practitioner | AM60: No Knowledge | AN60: Practitioner | AO60: Practitioner | AP60: Practitioner | AQ60: Practitioner | AR60: Practitioner | AS60: Practitioner | AT60: Practitioner | AY60: Practitioner | AZ60: Practitioner
A61: CoSETec28 | B61: Infrastructure | C61: Deploying, configuring and operating IT Infrastructure. | D61: Awareness | E61: Awareness | F61: Working | G61: Working | H61: Working | I61: Practitioner | J61: Working | K61: Awareness | L61: Working | M61: Working | N61: Working | O61: N/A | P61: Working | Q61: Working | R61: Working | S61: Expert | T61: Working | U61: Expert | V61: Expert | W61: Working | X61: Practitioner | Y61: Expert | Z61: Working | AA61: Awareness | AB61: Working | AC61: Working | AD61: Working | AE61: Working | AF61: Practitioner | AG61: Working | AH61: Expert | AI61: Awareness | AJ61: Awareness | AK61: Working | AL61: Working | AM61: Working | AN61: Working | AO61: Working | AP61: Practitioner | AQ61: Expert | AR61: Expert | AS61: Practitioner | AT61: Practitioner | AY61: Working | AZ61: Working
A62: CoSETec29 | B62: Network design | C62: Designing communication networks to support strategic and operational requirements and producing network strategies, architectures, policies and related documentation. | D62: No Knowledge | E62: No Knowledge | F62: No Knowledge | G62: No Knowledge | H62: No Knowledge | I62: No Knowledge | J62: No Knowledge | K62: No Knowledge | L62: No Knowledge | M62: No Knowledge | N62: No Knowledge | O62: No Knowledge | P62: No Knowledge | Q62: No Knowledge | R62: Working | S62: Practitioner | T62: Expert | U62: Practitioner | V62: Practitioner | W62: Awareness | X62: Awareness | Y62: Awareness | Z62: Practitioner | AA62: Awareness | AB62: Awareness | AC62: Awareness | AD62: Awareness | AE62: Awareness | AF62: Working | AG62: Working | AH62: Practitioner | AI62: No Knowledge | AJ62: No Knowledge | AK62: No Knowledge | AL62: Awareness | AM62: No Knowledge | AN62: Awareness | AO62: Working | AP62: Working | AQ62: Working | AR62: Working | AS62: Working | AT62: Working | AY62: Working | AZ62: Working
A63: CoSETec30 | B63: Network Analytics | C63: Use of advanced tools to diagnose netweork issues, traffic shaping, packet loss | D63: No Knowledge | E63: No Knowledge | F63: No Knowledge | G63: No Knowledge | H63: No Knowledge | I63: No Knowledge | J63: No Knowledge | K63: No Knowledge | L63: No Knowledge | M63: No Knowledge | N63: No Knowledge | O63: No Knowledge | P63: No Knowledge | Q63: No Knowledge | R63: Working | S63: Practitioner | T63: Expert | U63: Practitioner | V63: Practitioner | W63: No Knowledge | X63: No Knowledge | Y63: No Knowledge | Z63: No Knowledge | AA63: No Knowledge | AB63: No Knowledge | AC63: No Knowledge | AD63: No Knowledge | AE63: No Knowledge | AF63: Working | AG63: Working | AH63: Practitioner | AI63: No Knowledge | AJ63: No Knowledge | AK63: No Knowledge | AL63: No Knowledge | AM63: No Knowledge | AN63: No Knowledge | AO63: Working | AP63: Working | AQ63: Working | AR63: Working | AS63: Working | AT63: Working | AY63: Working | AZ63: Working
A64: CoSETec31 | B64: Network support | C64: Providing maintenance and support services for communications networks. | D64: Awareness | E64: Working | F64: Working | G64: Working | H64: Working | I64: Working | J64: Working | K64: Awareness | L64: Working | M64: Working | N64: Working | O64: No Knowledge | P64: Working | Q64: Working | R64: Practitioner | S64: Practitioner | T64: Expert | U64: Practitioner | V64: Practitioner | W64: Awareness | X64: Awareness | Y64: Awareness | Z64: Practitioner | AA64: No Knowledge | AB64: No Knowledge | AC64: No Knowledge | AD64: No Knowledge | AE64: No Knowledge | AF64: Working | AG64: Working | AH64: Practitioner | AI64: Awareness | AJ64: Awareness | AK64: Awareness | AL64: No Knowledge | AM64: No Knowledge | AN64: No Knowledge | AO64: Working | AP64: Working | AQ64: Working | AR64: Working | AS64: Working | AT64: Working
A65: CoSETec32 | B65: Programming/software development | C65: Developing software components to deliver value to stakeholders. | D65: No Knowledge | E65: No Knowledge | F65: No Knowledge | G65: No Knowledge | H65: No Knowledge | I65: No Knowledge | J65: No Knowledge | K65: No Knowledge | L65: No Knowledge | M65: No Knowledge | N65: No Knowledge | O65: No Knowledge | P65: No Knowledge | Q65: No Knowledge | R65: No Knowledge | S65: No Knowledge | T65: No Knowledge | U65: No Knowledge | V65: No Knowledge | W65: Awareness | X65: Working | Y65: Working | Z65: Awareness | AA65: Awareness | AB65: Working | AC65: Practitioner | AD65: Expert | AE65: Expert | AF65: Working | AG65: No Knowledge | AH65: No Knowledge | AI65: No Knowledge | AJ65: No Knowledge | AK65: No Knowledge | AL65: Practitioner | AM65: No Knowledge | AN65: Expert | AO65: No Knowledge | AP65: Working | AQ65: Working | AR65: Working | AS65: Practitioner | AT65: Practitioner | AY65: No Knowledge | AZ65: No Knowledge
A66: CoSETec33 | B66: Real-time/embedded systems development | C66: Designing and developing reliable real-time software typically within embedded systems. | D66: No Knowledge | E66: No Knowledge | F66: No Knowledge | G66: No Knowledge | H66: No Knowledge | I66: No Knowledge | J66: No Knowledge | K66: No Knowledge | L66: No Knowledge | M66: No Knowledge | N66: No Knowledge | O66: No Knowledge | P66: No Knowledge | Q66: No Knowledge | R66: No Knowledge | S66: No Knowledge | T66: No Knowledge | U66: No Knowledge | V66: No Knowledge | W66: No Knowledge | X66: No Knowledge | Y66: No Knowledge | Z66: Awareness | AA66: No Knowledge | AB66: Awareness | AC66: Awareness | AD66: Expert | AE66: Expert | AF66: No Knowledge | AG66: No Knowledge | AH66: No Knowledge | AI66: No Knowledge | AJ66: No Knowledge | AK66: No Knowledge | AL66: Practitioner | AM66: No Knowledge | AN66: Expert | AO66: No Knowledge | AP66: No Knowledge | AQ66: Awareness | AR66: Awareness | AS66: Awareness | AT66: Awareness | AY66: Practitioner | AZ66: Practitioner
A67: CoSETec34 | B67: Requirements definition and management | C67: Managing requirements through the entire delivery and operational life cycle. | D67: No Knowledge | E67: No Knowledge | F67: No Knowledge | G67: No Knowledge | H67: No Knowledge | I67: No Knowledge | J67: No Knowledge | K67: No Knowledge | L67: No Knowledge | M67: No Knowledge | N67: No Knowledge | O67: No Knowledge | P67: No Knowledge | Q67: No Knowledge | R67: No Knowledge | S67: No Knowledge | T67: No Knowledge | U67: No Knowledge | V67: No Knowledge | W67: No Knowledge | X67: No Knowledge | Y67: No Knowledge | Z67: Awareness | AA67: No Knowledge | AB67: Working | AC67: Practitioner | AD67: Practitioner | AE67: Expert | AF67: Practitioner | AG67: Practitioner | AH67: No Knowledge | AI67: No Knowledge | AJ67: No Knowledge | AK67: No Knowledge | AL67: Practitioner | AM67: No Knowledge | AN67: Expert | AO67: Practitioner | AP67: Practitioner | AQ67: Practitioner | AR67: Practitioner | AS67: Practitioner | AT67: Practitioner | AY67: Awareness | AZ67: Awareness
A68: CoSETec35 | B68: Software configuration | C68: Designing and deploying software product configurations into software environments or platforms. | D68: No Knowledge | E68: No Knowledge | F68: No Knowledge | G68: No Knowledge | H68: No Knowledge | I68: No Knowledge | J68: No Knowledge | K68: No Knowledge | L68: No Knowledge | M68: No Knowledge | N68: No Knowledge | O68: No Knowledge | P68: No Knowledge | Q68: No Knowledge | R68: No Knowledge | S68: No Knowledge | T68: No Knowledge | U68: No Knowledge | V68: No Knowledge | W68: No Knowledge | X68: No Knowledge | Y68: No Knowledge | Z68: Awareness | AA68: No Knowledge | AB68: Working | AC68: Practitioner | AD68: Practitioner | AE68: Expert | AF68: Awareness | AG68: Awareness | AH68: No Knowledge | AI68: No Knowledge | AJ68: No Knowledge | AK68: No Knowledge | AL68: Practitioner | AM68: No Knowledge | AN68: Expert | AO68: Awareness | AP68: Awareness | AQ68: Awareness | AR68: Awareness | AS68: Awareness | AT68: Awareness | AY68: Awareness | AZ68: Awareness
A69: CoSETec36 | B69: Software design | C69: Specifying and designing software to meet defined requirements by following agreed design standards and principles. | D69: No Knowledge | E69: No Knowledge | F69: No Knowledge | G69: No Knowledge | H69: No Knowledge | I69: No Knowledge | J69: No Knowledge | K69: No Knowledge | L69: No Knowledge | M69: No Knowledge | N69: No Knowledge | O69: No Knowledge | P69: No Knowledge | Q69: No Knowledge | R69: No Knowledge | S69: No Knowledge | T69: No Knowledge | U69: No Knowledge | V69: No Knowledge | W69: No Knowledge | X69: No Knowledge | Y69: No Knowledge | Z69: Awareness | AA69: No Knowledge | AB69: Practitioner | AC69: Practitioner | AD69: Expert | AE69: Expert | AF69: Awareness | AG69: Awareness | AH69: No Knowledge | AI69: No Knowledge | AJ69: No Knowledge | AK69: No Knowledge | AL69: Practitioner | AM69: No Knowledge | AN69: Expert | AO69: Awareness | AP69: Awareness | AQ69: Awareness | AR69: Awareness | AS69: Awareness | AT69: Awareness | AU69: Working | AV69: Working | AW69: Working | AX69: Working | AY69: Working | AZ69: Working
A70: CoSETec37 | B70: Solution architecture | C70: Developing and communicating a multi-dimensional solution architecture to deliver agreed business outcomes. | D70: No Knowledge | E70: No Knowledge | F70: No Knowledge | G70: No Knowledge | H70: No Knowledge | I70: No Knowledge | J70: No Knowledge | K70: No Knowledge | L70: No Knowledge | M70: No Knowledge | N70: No Knowledge | O70: No Knowledge | P70: No Knowledge | Q70: Working | R70: Working | S70: Working | T70: Working | U70: Working | V70: Working | W70: Working | X70: Working | Y70: Working | Z70: Working | AA70: No Knowledge | AB70: Awareness | AC70: Awareness | AD70: Working | AE70: Working | AF70: Practitioner | AG70: Working | AH70: Working | AI70: No Knowledge | AJ70: No Knowledge | AK70: No Knowledge | AL70: Working | AM70: Working | AN70: Working | AO70: Working | AP70: Practitioner | AQ70: Practitioner | AR70: Practitioner | AS70: Practitioner | AT70: Practitioner | AY70: Expert | AZ70: Expert
A71: CoSETec38 | B71: System software | C71: Installing, managing, controlling, deploying and maintaining infrastructure systems software, to meet operational needs and service levels. | D71: No Knowledge | E71: No Knowledge | F71: No Knowledge | G71: No Knowledge | H71: No Knowledge | I71: No Knowledge | J71: No Knowledge | K71: No Knowledge | L71: No Knowledge | M71: No Knowledge | N71: No Knowledge | O71: No Knowledge | P71: No Knowledge | Q71: No Knowledge | R71: No Knowledge | S71: No Knowledge | T71: No Knowledge | U71: No Knowledge | V71: No Knowledge | W71: No Knowledge | X71: No Knowledge | Y71: No Knowledge | Z71: Awareness | AA71: Awareness | AB71: Working | AC71: Practitioner | AD71: Expert | AE71: Expert | AF71: Expert | AG71: Working | AH71: No Knowledge | AI71: No Knowledge | AJ71: No Knowledge | AK71: No Knowledge | AL71: Practitioner | AM71: No Knowledge | AN71: Expert | AO71: Working | AP71: Expert | AQ71: Expert | AR71: Expert | AS71: Expert | AT71: Expert
A72: CoSETec39 | B72: Systems and software life cycle engineering | C72: Establishing and deploying an environment for developing, continually improving, and securely operating software and systems products and services. | D72: No Knowledge | E72: No Knowledge | F72: No Knowledge | G72: No Knowledge | H72: No Knowledge | I72: No Knowledge | J72: No Knowledge | K72: No Knowledge | L72: No Knowledge | M72: No Knowledge | N72: No Knowledge | O72: No Knowledge | P72: No Knowledge | Q72: No Knowledge | R72: No Knowledge | S72: No Knowledge | T72: No Knowledge | U72: No Knowledge | V72: No Knowledge | W72: Working | X72: Working | Y72: Working | Z72: Working | AA72: Awareness | AB72: Working | AC72: Practitioner | AD72: Expert | AE72: Expert | AF72: Expert | AG72: Working | AH72: No Knowledge | AI72: No Knowledge | AJ72: No Knowledge | AK72: No Knowledge | AL72: Practitioner | AM72: No Knowledge | AN72: Expert | AO72: Working | AP72: Expert | AQ72: Expert | AR72: Expert | AS72: Expert | AT72: Expert
A73: CoSETec40 | B73: Systems design | C73: Designing systems to meet specified requirements and agreed systems architectures. | D73: No Knowledge | E73: No Knowledge | F73: No Knowledge | G73: No Knowledge | H73: No Knowledge | I73: No Knowledge | J73: No Knowledge | K73: No Knowledge | L73: No Knowledge | M73: No Knowledge | N73: No Knowledge | O73: No Knowledge | P73: No Knowledge | Q73: No Knowledge | R73: No Knowledge | S73: No Knowledge | T73: No Knowledge | U73: No Knowledge | V73: No Knowledge | W73: No Knowledge | X73: No Knowledge | Y73: No Knowledge | Z73: Awareness | AA73: Awareness | AB73: Awareness | AC73: Awareness | AD73: Awareness | AE73: Awareness | AF73: Expert | AG73: Working | AH73: No Knowledge | AI73: No Knowledge | AJ73: No Knowledge | AK73: No Knowledge | AL73: Awareness | AM73: Awareness | AN73: Awareness | AO73: Working | AP73: Expert | AQ73: Expert | AR73: Expert | AS73: Expert | AT73: Expert
A74: CoSETec41 | B74: Systems development management | C74: Planning, estimating and executing systems development work to time, budget and quality targets. | D74: No Knowledge | E74: No Knowledge | F74: No Knowledge | G74: No Knowledge | H74: No Knowledge | I74: No Knowledge | J74: No Knowledge | K74: No Knowledge | L74: No Knowledge | M74: No Knowledge | N74: No Knowledge | O74: No Knowledge | P74: No Knowledge | Q74: No Knowledge | R74: No Knowledge | S74: No Knowledge | T74: No Knowledge | U74: No Knowledge | V74: No Knowledge | W74: No Knowledge | X74: No Knowledge | Y74: No Knowledge | Z74: Awareness | AA74: Awareness | AB74: Awareness | AC74: Awareness | AD74: Awareness | AE74: Awareness | AF74: Practitioner | AG74: Working | AH74: No Knowledge | AI74: No Knowledge | AJ74: No Knowledge | AK74: No Knowledge | AL74: Awareness | AM74: Awareness | AN74: Awareness | AO74: Working | AP74: Practitioner | AQ74: Practitioner | AR74: Practitioner | AS74: Practitioner | AT74: Practitioner | AU74: Working | AV74: Working | AW74: Working | AX74: Working | AY74: Working | AZ74: Working
A75: CoSETec42 | B75: Systems installation and removal | C75: Installing and testing, or decommissioning and removing, systems or system components. | D75: Awareness | E75: Working | F75: Practitioner | G75: Practitioner | H75: Practitioner | I75: Practitioner | J75: Practitioner | K75: Working | L75: Working | M75: Working | N75: Working | O75: Working | P75: Working | Q75: Working | R75: Working | S75: Working | T75: Working | U75: Working | V75: Working | W75: Working | X75: Working | Y75: Working | Z75: Practitioner | AA75: Awareness | AB75: Awareness | AC75: Awareness | AD75: Awareness | AE75: Awareness | AF75: Working | AG75: Working | AH75: Working | AI75: Awareness | AJ75: Awareness | AK75: Awareness | AL75: Awareness | AM75: Awareness | AN75: Awareness | AO75: Working | AP75: Working | AQ75: Expert | AR75: Expert | AS75: Expert | AT75: Expert | AU75: Working | AV75: Working | AW75: Working | AY75: Practitioner | AZ75: Practitioner
A76: CoSETec43 | B76: Testing | C76: Investigating products, systems and services to assess behaviour and whether this meets specified or unspecified requirements and characteristics. | D76: Working | E76: Working | F76: Working | G76: Working | H76: Working | I76: Practitioner | J76: Working | K76: Working | L76: Working | M76: Working | N76: Working | O76: Working | P76: Working | Q76: Awareness | R76: Working | S76: Working | T76: Working | U76: Working | V76: Working | W76: Working | X76: Working | Y76: Working | Z76: Practitioner | AA76: Awareness | AB76: Working | AC76: Practitioner | AD76: Practitioner | AE76: Practitioner | AF76: Practitioner | AG76: Practitioner | AH76: Working | AI76: Working | AJ76: Working | AK76: Working | AL76: Practitioner | AM76: Working | AN76: Practitioner | AO76: Practitioner | AP76: Practitioner | AQ76: Practitioner | AR76: Practitioner | AS76: Practitioner | AT76: Practitioner
A77: CoSETec45 | B77: Innovation | C77: Identifying, prioritising, incubating and exploiting opportunities provided by information, communication and digital technologies. | D77: No Knowledge | E77: No Knowledge | F77: No Knowledge | G77: No Knowledge | H77: No Knowledge | I77: No Knowledge | J77: No Knowledge | K77: No Knowledge | L77: No Knowledge | M77: No Knowledge | N77: No Knowledge | O77: No Knowledge | P77: No Knowledge | Q77: No Knowledge | R77: No Knowledge | S77: Practitioner | T77: Practitioner | U77: Practitioner | V77: Practitioner | W77: Working | X77: Working | Y77: Working | Z77: Working | AA77: Working | AB77: Working | AC77: Working | AD77: Practitioner | AE77: Practitioner | AF77: Expert | AG77: Practitioner | AH77: Practitioner | AI77: No Knowledge | AJ77: No Knowledge | AK77: No Knowledge | AL77: Working | AM77: Working | AN77: Practitioner | AO77: Practitioner | AP77: Expert | AQ77: Expert | AR77: Expert | AS77: Expert | AT77: Expert | AU77: Working | AV77: Working | AW77: Working | AX77: Working | AY77: Expert | AZ77: Expert
A78: CoSETec46 | B78: Specialist Advice | C78: Providing authoritative advice and direction in a specialist area. | D78: No Knowledge | E78: No Knowledge | F78: No Knowledge | G78: No Knowledge | H78: No Knowledge | I78: Practitioner | J78: No Knowledge | K78: No Knowledge | L78: No Knowledge | M78: No Knowledge | N78: No Knowledge | O78: No Knowledge | P78: Awareness | Q78: No Knowledge | R78: No Knowledge | S78: Practitioner | T78: Practitioner | U78: Practitioner | V78: Practitioner | W78: Working | X78: Working | Y78: Practitioner | Z78: Practitioner | AA78: Working | AB78: Working | AC78: Working | AD78: Practitioner | AE78: Practitioner | AF78: Expert | AG78: Expert | AH78: Practitioner | AI78: No Knowledge | AJ78: No Knowledge | AK78: No Knowledge | AL78: Working | AM78: Working | AN78: Practitioner | AO78: Expert | AP78: Expert | AQ78: Expert | AR78: Expert | AS78: Expert | AT78: Expert | AU78: N/A | AV78: N/A | AW78: N/A | AX78: N/A | AY78: N/A | AZ78: N/A
A79: CoseMgt02 | B79: Emerging technology monitoring | C79: Identifying and assessing new and emerging technologies, products, services, methods and techniques. | D79: No Knowledge | E79: No Knowledge | F79: No Knowledge | G79: Working | H79: No Knowledge | I79: No Knowledge | J79: Working | K79: No Knowledge | L79: No Knowledge | M79: No Knowledge | N79: Working | O79: No Knowledge | P79: Practitioner | Q79: No Knowledge | R79: No Knowledge | S79: No Knowledge | T79: No Knowledge | U79: Working | V79: Working | W79: No Knowledge | X79: Awareness | Y79: Working | Z79: Working | AA79: Awareness | AB79: Awareness | AC79: Awareness | AD79: Awareness | AE79: Awareness | AF79: Practitioner | AG79: Working | AH79: No Knowledge | AI79: N/A | AJ79: No Knowledge | AK79: No Knowledge | AL79: Awareness | AM79: Awareness | AN79: Awareness | AO79: Practitioner | AP79: Practitioner | AQ79: Practitioner | AR79: Practitioner | AS79: Practitioner | AT79: Practitioner
B80: Systems integration and build | C80: Planning, implementing and controlling activities to synthesise system components to create operational systems, products or services. | D80: Awareness | E80: Working | F80: Practitioner | G80: Practitioner | H80: Practitioner | I80: Practitioner | J80: Practitioner | K80: Awareness | L80: Working | M80: Practitioner | N80: Practitioner | O80: Practitioner | P80: Practitioner | Q80: Practitioner | R80: Practitioner | S80: Practitioner | T80: Practitioner | U80: Practitioner | V80: Practitioner | W80: Working | X80: Working | Y80: Practitioner | Z80: Working | AA80: No Knowledge | AB80: No Knowledge | AC80: No Knowledge | AD80: No Knowledge | AE80: No Knowledge | AF80: Practitioner | AG80: Working | AH80: Practitioner | AI80: Awareness | AJ80: Awareness | AK80: Awareness | AL80: No Knowledge | AM80: No Knowledge | AN80: No Knowledge | AO80: Practitioner | AP80: Practitioner | AQ80: Working | AR80: Working | AS80: Working | AT80: Working
B81: Audio Visual | C81: Setting up and supporting of multimedia equipment such as TV screens, Projectors, microphones and speakers. | D81: Awareness | E81: Awareness | F81: Awareness | G81: Practitioner | H81: Practitioner | I81: Practitioner | J81: Practitioner | K81: Awareness | L81: No Knowledge | M81: Awareness | P81: Working | Q81: No Knowledge | R81: No Knowledge | S81: Awareness | T81: Awareness | U81: Awareness | V81: Awareness | W81: No Knowledge | X81: No Knowledge | Y81: No Knowledge | Z81: No Knowledge | AA81: No Knowledge | AB81: No Knowledge | AC81: No Knowledge | AD81: No Knowledge | AE81: No Knowledge | AF81: Working | AG81: No Knowledge | AH81: Awareness | AJ81: Awareness | AK81: Awareness | AL81: No Knowledge | AM81: No Knowledge | AN81: No Knowledge | AO81: Working | AQ81: No Knowledge | AR81: No Knowledge | AS81: No Knowledge | AT81: No Knowledge
B82: Augmented Reality | C82: Setting up and supporting of multimedia equipment such as TV screens, Projectors, microphones and speakers. | D82: No Knowledge | E82: No Knowledge | F82: No Knowledge | G82: Awareness | H82: Awareness | I82: Awareness | J82: Awareness | K82: Awareness | L82: Awareness | M82: Awareness | N82: Awareness | O82: Awareness | P82: Awareness | Q82: No Knowledge | R82: No Knowledge | S82: No Knowledge | T82: No Knowledge | U82: No Knowledge | V82: No Knowledge | W82: No Knowledge | X82: No Knowledge | Y82: Practitioner | Z82: No Knowledge | AA82: No Knowledge | AB82: No Knowledge | AC82: No Knowledge | AD82: No Knowledge | AE82: No Knowledge | AF82: Working | AG82: No Knowledge | AH82: Awareness | AJ82: Awareness | AK82: Awareness | AL82: No Knowledge | AM82: No Knowledge | AN82: No Knowledge | AO82: Working | AQ82: No Knowledge | AR82: No Knowledge | AS82: No Knowledge | AT82: No Knowledge
A83: CoSEBus01 | B83: Benefits management | C83: Forecasting, planning and monitoring the emergence and effective realisation of anticipated benefits from projects and programmes. | D83: No Knowledge | E83: No Knowledge | F83: No Knowledge | G83: No Knowledge | H83: No Knowledge | I83: No Knowledge | J83: No Knowledge | K83: No Knowledge | L83: No Knowledge | M83: No Knowledge | N83: No Knowledge | O83: No Knowledge | P83: No Knowledge | Q83: Working | R83: Working | S83: Practitioner | T83: Practitioner | U83: Practitioner | V83: Practitioner | W83: Working | X83: Working | Y83: Practitioner | Z83: Practitioner | AA83: No Knowledge | AB83: No Knowledge | AC83: No Knowledge | AD83: No Knowledge | AE83: No Knowledge | AF83: Practitioner | AG83: Working | AH83: Practitioner | AI83: No Knowledge | AJ83: No Knowledge | AK83: No Knowledge | AL83: No Knowledge | AM83: No Knowledge | AN83: No Knowledge | AO83: Working | AP83: Practitioner | AQ83: Working | AR83: Working | AS83: Working | AT83: Working
A84: CoSEBus02 | B84: Business administration | C84: Managing and performing administrative services and tasks to enable individuals, teams and organisations to succeed in their objectives. | D84: No Knowledge | E84: No Knowledge | F84: No Knowledge | G84: No Knowledge | H84: No Knowledge | I84: No Knowledge | J84: No Knowledge | K84: No Knowledge | L84: No Knowledge | M84: No Knowledge | N84: No Knowledge | O84: No Knowledge | P84: No Knowledge | Q84: Working | R84: Working | S84: Practitioner | T84: Practitioner | U84: Practitioner | V84: Practitioner | W84: No Knowledge | X84: No Knowledge | Y84: Awareness | Z84: Working | AA84: No Knowledge | AB84: No Knowledge | AC84: No Knowledge | AD84: No Knowledge | AE84: No Knowledge | AF84: Practitioner | AG84: No Knowledge | AH84: Practitioner | AI84: No Knowledge | AJ84: No Knowledge | AK84: No Knowledge | AL84: No Knowledge | AM84: No Knowledge | AN84: No Knowledge | AO84: No Knowledge | AP84: Working | AQ84: Working | AR84: Working | AS84: Working | AT84: Working
A85: CoSEBus03 | B85: Business intelligence | C85: Developing, producing and delivering regular and one-off management information to provide insights and aid decision-making. | D85: No Knowledge | E85: No Knowledge | F85: No Knowledge | G85: No Knowledge | H85: No Knowledge | I85: No Knowledge | J85: No Knowledge | K85: No Knowledge | L85: No Knowledge | M85: No Knowledge | N85: No Knowledge | O85: No Knowledge | P85: No Knowledge | Q85: No Knowledge | R85: No Knowledge | S85: Practitioner | T85: Working | U85: Practitioner | V85: Practitioner | W85: No Knowledge | X85: No Knowledge | Y85: No Knowledge | Z85: Working | AA85: No Knowledge | AB85: No Knowledge | AC85: No Knowledge | AD85: No Knowledge | AE85: No Knowledge | AF85: Working | AG85: No Knowledge | AH85: Practitioner | AI85: No Knowledge | AJ85: No Knowledge | AK85: No Knowledge | AL85: No Knowledge | AM85: No Knowledge | AN85: No Knowledge | AO85: No Knowledge | AP85: Practitioner | AQ85: Working | AR85: Working | AS85: Working | AT85: Working | AY85: No Knowledge | AZ85: No Knowledge
A86: CoSEBus04 | B86: Business modelling | C86: Producing abstract or distilled representations of real-world, business or gaming situations. | D86: No Knowledge | E86: No Knowledge | F86: No Knowledge | G86: No Knowledge | H86: No Knowledge | I86: No Knowledge | J86: No Knowledge | K86: No Knowledge | L86: No Knowledge | M86: No Knowledge | N86: No Knowledge | O86: No Knowledge | P86: No Knowledge | Q86: No Knowledge | R86: No Knowledge | S86: No Knowledge | T86: Practitioner | U86: Practitioner | V86: Practitioner | W86: No Knowledge | X86: No Knowledge | Y86: No Knowledge | Z86: No Knowledge | AA86: No Knowledge | AB86: No Knowledge | AC86: No Knowledge | AD86: No Knowledge | AE86: No Knowledge | AF86: No Knowledge | AG86: No Knowledge | AH86: No Knowledge | AI86: No Knowledge | AJ86: No Knowledge | AK86: No Knowledge | AL86: No Knowledge | AM86: No Knowledge | AN86: No Knowledge | AO86: No Knowledge | AP86: No Knowledge | AQ86: No Knowledge | AR86: No Knowledge | AS86: No Knowledge | AT86: No Knowledge
A87: CoSEBus05 | B87: Business process improvement | C87: Creating new and potentially disruptive approaches to performing business activities. | D87: No Knowledge | E87: No Knowledge | F87: No Knowledge | G87: No Knowledge | H87: No Knowledge | I87: No Knowledge | J87: No Knowledge | K87: No Knowledge | L87: No Knowledge | M87: No Knowledge | N87: No Knowledge | O87: No Knowledge | P87: No Knowledge | Q87: Working | R87: Working | S87: Practitioner | T87: Practitioner | U87: Practitioner | V87: Practitioner | W87: Awareness | X87: Awareness | Y87: Working | Z87: Working | AA87: No Knowledge | AB87: No Knowledge | AC87: No Knowledge | AD87: No Knowledge | AE87: No Knowledge | AF87: Practitioner | AG87: No Knowledge | AH87: Practitioner | AI87: No Knowledge | AJ87: No Knowledge | AK87: No Knowledge | AL87: No Knowledge | AM87: No Knowledge | AN87: No Knowledge | AO87: No Knowledge | AP87: Practitioner | AQ87: Working | AR87: Working | AS87: Working | AT87: Working
A88: CoSEBus06 | B88: Business situation analysis | C88: Investigating business situations to define recommendations for improvement action. | D88: No Knowledge | E88: No Knowledge | F88: No Knowledge | G88: No Knowledge | H88: No Knowledge | I88: No Knowledge | J88: No Knowledge | K88: No Knowledge | L88: No Knowledge | M88: No Knowledge | N88: No Knowledge | O88: No Knowledge | P88: No Knowledge | Q88: No Knowledge | R88: No Knowledge | S88: No Knowledge | T88: No Knowledge | U88: No Knowledge | V88: No Knowledge | W88: No Knowledge | X88: No Knowledge | Y88: Working | Z88: Working | AA88: No Knowledge | AB88: No Knowledge | AC88: No Knowledge | AD88: No Knowledge | AE88: No Knowledge | AF88: Practitioner | AG88: No Knowledge | AH88: No Knowledge | AI88: No Knowledge | AJ88: No Knowledge | AK88: No Knowledge | AL88: No Knowledge | AM88: No Knowledge | AN88: No Knowledge | AO88: No Knowledge | AP88: Practitioner | AQ88: Working | AR88: Working | AS88: Working | AT88: Working
A89: CoSEBus07 | B89: Programme management | C89: Identifying, planning and coordinating a set of related projects and activities in support of specific business strategies and objectives. | D89: No Knowledge | E89: No Knowledge | F89: No Knowledge | G89: No Knowledge | H89: No Knowledge | I89: No Knowledge | J89: No Knowledge | K89: No Knowledge | L89: No Knowledge | M89: No Knowledge | N89: No Knowledge | O89: No Knowledge | P89: No Knowledge | Q89: Working | R89: Working | S89: Practitioner | T89: Practitioner | U89: Practitioner | V89: Practitioner | W89: No Knowledge | X89: No Knowledge | Y89: No Knowledge | Z89: Practitioner | AA89: No Knowledge | AB89: No Knowledge | AC89: No Knowledge | AD89: No Knowledge | AE89: No Knowledge | AF89: Practitioner | AG89: No Knowledge | AH89: Practitioner | AI89: No Knowledge | AJ89: No Knowledge | AK89: No Knowledge | AL89: No Knowledge | AM89: No Knowledge | AN89: No Knowledge | AO89: No Knowledge | AP89: Practitioner | AQ89: Working | AR89: Working | AS89: Working | AT89: Working
A90: CoSEBus08 | B90: Project management | C90: Delivering agreed outcomes from projects using appropriate management techniques, collaboration, leadership and governance. | D90: No Knowledge | E90: No Knowledge | F90: No Knowledge | G90: No Knowledge | H90: No Knowledge | I90: No Knowledge | J90: No Knowledge | K90: No Knowledge | L90: No Knowledge | M90: No Knowledge | N90: No Knowledge | O90: No Knowledge | P90: Awareness | Q90: Working | R90: Working | S90: Practitioner | T90: Practitioner | U90: Practitioner | V90: Practitioner | W90: Awareness | X90: Awareness | Y90: Working | Z90: Practitioner | AA90: No Knowledge | AB90: No Knowledge | AC90: No Knowledge | AD90: No Knowledge | AE90: No Knowledge | AF90: Practitioner | AG90: Working | AH90: Practitioner | AI90: No Knowledge | AJ90: No Knowledge | AK90: No Knowledge | AL90: No Knowledge | AM90: No Knowledge | AN90: No Knowledge | AO90: Working | AP90: Practitioner | AQ90: Working | AR90: Working | AS90: Working | AT90: Working
A91: CoSEBus09 | B91: Quality assurance | C91: Assuring, through ongoing and periodic assessments and reviews, that the organisation’s quality objectives are being met. | D91: Awareness | E91: Awareness | F91: Working | G91: Working | H91: Working | I91: Working | J91: Working | K91: Awareness | L91: Awareness | M91: Working | N91: Working | O91: Awareness | P91: Working | Q91: Working | R91: Working | S91: Practitioner | T91: Practitioner | U91: Practitioner | V91: Practitioner | W91: Working | X91: Working | Y91: Practitioner | Z91: Practitioner | AA91: No Knowledge | AB91: No Knowledge | AC91: No Knowledge | AD91: No Knowledge | AE91: No Knowledge | AF91: Practitioner | AG91: Practitioner | AH91: Practitioner | AI91: Awareness | AJ91: Awareness | AK91: Working | AL91: No Knowledge | AM91: No Knowledge | AN91: No Knowledge | AO91: Practitioner | AP91: Practitioner | AQ91: Practitioner | AR91: Practitioner | AS91: Practitioner | AT91: Practitioner | AU91: {=SUM(INDEX($C$95:$C$99,MATCH(AU4:AU90,$B$95:$B$99,0)))} -> #N/A | AV91: {=SUM(INDEX($C$95:$C$99,MATCH(AV4:AV90,$B$95:$B$99,0)))} -> #N/A | AW91: {=SUM(INDEX($C$95:$C$99,MATCH(AW4:AW90,$B$95:$B$99,0)))} -> #N/A | AX91: {=SUM(INDEX($C$95:$C$99,MATCH(AX4:AX90,$B$95:$B$99,0)))} -> #N/A | AY91: {=SUM(INDEX($C$95:$C$99,MATCH(AY4:AY90,$B$95:$B$99,0)))} -> #N/A | AZ91: {=SUM(INDEX($C$95:$C$99,MATCH(AZ4:AZ90,$B$95:$B$99,0)))} -> #N/A
C92: Total | D92: {=SUM(INDEX($C$95:$C$99,MATCH(D4:D91,$B$95:$B$99,0)))} -> 51 | E92: {=SUM(INDEX($C$95:$C$99,MATCH(E4:E91,$B$95:$B$99,0)))} -> 62 | F92: {=SUM(INDEX($C$95:$C$99,MATCH(F4:F91,$B$95:$B$99,0)))} -> 77 | G92: {=SUM(INDEX($C$95:$C$99,MATCH(G4:G91,$B$95:$B$99,0)))} -> 104 | H92: {=SUM(INDEX($C$95:$C$99,MATCH(H4:H91,$B$95:$B$99,0)))} -> 83 | I92: {=SUM(INDEX($C$95:$C$99,MATCH(I4:I91,$B$95:$B$99,0)))} -> 94 | J92: {=SUM(INDEX($C$95:$C$99,MATCH(J4:J91,$B$95:$B$99,0)))} -> 104 | K92: {=SUM(INDEX($C$95:$C$99,MATCH(K4:K91,$B$95:$B$99,0)))} -> 57 | ... Z92: {=SUM(INDEX($C$95:$C$99,MATCH(Z4:Z91,$B$95:$B$99,0)))} -> 179 | AA92: {=SUM(INDEX($C$94:$C$98,MATCH(AA4:AA91,$B$94:$B$98,0)))} -> 65 | AB92: {=SUM(INDEX($C$95:$C$99,MATCH(AB4:AB91,$B$95:$B$99,0)))} -> 108 | AC92: {=SUM(INDEX($C$95:$C$99,MATCH(AC4:AC91,$B$95:$B$99,0)))} -> 127 | AD92: {=SUM(INDEX($C$95:$C$99,MATCH(AD4:AD91,$B$95:$B$99,0)))} -> 155 | AE92: {=SUM(INDEX($C$95:$C$99,MATCH(AE4:AE91,$B$95:$B$99,0)))} -> 157 | AF92: {=SUM(INDEX($C$95:$C$99,MATCH(AF4:AF91,$B$95:$B$99,0)))} -> 217 | AG92: {=SUM(INDEX($C$95:$C$99,MATCH(AG4:AG91,$B$95:$B$99,0)))} -> 151 | AH92: {=SUM(INDEX($C$95:$C$99,MATCH(AH4:AH91,$B$95:$B$99,0)))} -> 150 | AI92: {=SUM(INDEX($C$95:$C$99,MATCH(AI4:AI91,$B$95:$B$99,0)))} -> #N/A | ... AT92: {=SUM(INDEX($C$95:$C$99,MATCH(AT4:AT91,$B$95:$B$99,0)))} -> 204
B94: Competence Level | C94: Score
B95: No Knowledge | C95: 0
B96: Awareness | C96: 1
B97: Working | C97: 2
B98: Practitioner | C98: 3
B99: Expert | C99: 4
A107: CoSETec47 | B107: Augmented Reality | C107: Setting up and supporting of technology that integrates a computer-generated image on a user's view of the real world, thus providing a composite view. | D107: No Knowledge | E107: No Knowledge | F107: No Knowledge | G107: Awareness | H107: Awareness | I107: Awareness | J107: Awareness | P107: Awareness | Q107: No Knowledge | R107: No Knowledge | S107: No Knowledge | T107: No Knowledge | U107: No Knowledge | V107: No Knowledge | W107: No Knowledge | X107: Awareness | Y107: Practitioner | Z107: No Knowledge | AA107: No Knowledge | AB107: No Knowledge | AC107: No Knowledge | AD107: No Knowledge | AE107: No Knowledge | AF107: No Knowledge | AG107: No Knowledge | AH107: No Knowledge | AJ107: No Knowledge | AK107: No Knowledge | AL107: No Knowledge | AM107: No Knowledge | AN107: No Knowledge | AO107: Awareness | AQ107: Working | AR107: No Knowledge | AS107: No Knowledge | AT107: No Knowledge | AY107: Working | AZ107: Working

Sheet Master
A1: Name | B1: New Role | C1: Competency | D1: Desired Description | E1: Comp Area | F1: Desired Level | G1: ActuaL | H1: Knowledge Gap | I1: Actual Copied (VLOOKUP)
A2: John Watson | B2: Senior Systems Administrator | C2: =VLOOKUP([1]Competence!$B12,[1]Competence!$B$12:$B$100,1,FALSE) -> Asset Management | D2: {=_xlfn.XLOOKUP(B2,[1]Baseline!$D$3:$AZ$3,_xlfn.XLOOKUP(C2,[1]Baseline!$B$4:$B$91,[1]Baseline!$D$4:$AZ$91))} -> Practitioner | E2: Business | F2: =VLOOKUP($D2,'[1]SFIA Level'!$A$2:$B$6,2,FALSE) -> 3 | G2: 3 | H2: =I2-F2 -> 0 | I2: 3
A3: John Watson | B3: Senior Systems Administrator | C3: =VLOOKUP([1]Competence!$B13,[1]Competence!$B$12:$B$100,1,FALSE) -> Change Control | D3: {=_xlfn.XLOOKUP(B3,[1]Baseline!$D$3:$AZ$3,_xlfn.XLOOKUP(C3,[1]Baseline!$B$4:$B$91,[1]Baseline!$D$4:$AZ$91))} -> Practitioner | E3: Business | F3: =VLOOKUP($D3,'[1]SFIA Level'!$A$2:$B$6,2,FALSE) -> 3 | G3: 3 | H3: =I3-F3 -> 0 | I3: 3
A4: John Watson | B4: Senior Systems Administrator | C4: =VLOOKUP([1]Competence!$B14,[1]Competence!$B$12:$B$100,1,FALSE) -> Customer Service Support | D4: {=_xlfn.XLOOKUP(B4,[1]Baseline!$D$3:$AZ$3,_xlfn.XLOOKUP(C4,[1]Baseline!$B$4:$B$91,[1]Baseline!$D$4:$AZ$91))} -> Practitioner | E4: Business | F4: =VLOOKUP($D4,'[1]SFIA Level'!$A$2:$B$6,2,FALSE) -> 3 | G4: 3 | H4: =I4-F4 -> 0 | I4: 3
A5: John Watson | B5: Senior Systems Administrator | C5: =VLOOKUP([1]Competence!$B15,[1]Competence!$B$12:$B$100,1,FALSE) -> Incident management | D5: {=_xlfn.XLOOKUP(B5,[1]Baseline!$D$3:$AZ$3,_xlfn.XLOOKUP(C5,[1]Baseline!$B$4:$B$91,[1]Baseline!$D$4:$AZ$91))} -> Practitioner | E5: Business | F5: =VLOOKUP($D5,'[1]SFIA Level'!$A$2:$B$6,2,FALSE) -> 3 | G5: 3 | H5: =I5-F5 -> 0 | I5: 3
A6: John Watson | B6: Senior Systems Administrator | C6: =VLOOKUP([1]Competence!$B16,[1]Competence!$B$12:$B$100,1,FALSE) -> Information security | D6: {=_xlfn.XLOOKUP(B6,[1]Baseline!$D$3:$AZ$3,_xlfn.XLOOKUP(C6,[1]Baseline!$B$4:$B$91,[1]Baseline!$D$4:$AZ$91))} -> Practitioner | E6: Service | F6: =VLOOKUP($D6,'[1]SFIA Level'!$A$2:$B$6,2,FALSE) -> 3 | G6: 2 | H6: =I6-F6 -> -1 | I6: 2
A7: John Watson | B7: Senior Systems Administrator | C7: =VLOOKUP([1]Competence!$B17,[1]Competence!$B$12:$B$100,1,FALSE) -> Personal data protection | D7: {=_xlfn.XLOOKUP(B7,[1]Baseline!$D$3:$AZ$3,_xlfn.XLOOKUP(C7,[1]Baseline!$B$4:$B$91,[1]Baseline!$D$4:$AZ$91))} -> Practitioner | E7: Governance | F7: =VLOOKUP($D7,'[1]SFIA Level'!$A$2:$B$6,2,FALSE) -> 3 | G7: 3 | H7: =I7-F7 -> 0 | I7: 3
A8: John Watson | B8: Senior Systems Administrator | C8: =VLOOKUP([1]Competence!$B18,[1]Competence!$B$12:$B$100,1,FALSE) -> Problem management | D8: {=_xlfn.XLOOKUP(B8,[1]Baseline!$D$3:$AZ$3,_xlfn.XLOOKUP(C8,[1]Baseline!$B$4:$B$91,[1]Baseline!$D$4:$AZ$91))} -> Working | E8: Governance | F8: =VLOOKUP($D8,'[1]SFIA Level'!$A$2:$B$6,2,FALSE) -> 2 | G8: 3 | H8: =I8-F8 -> 1 | I8: 3
A9: John Watson | B9: Senior Systems Administrator | C9: =VLOOKUP([1]Competence!$B19,[1]Competence!$B$12:$B$100,1,FALSE) -> Service catalogue management | D9: {=_xlfn.XLOOKUP(B9,[1]Baseline!$D$3:$AZ$3,_xlfn.XLOOKUP(C9,[1]Baseline!$B$4:$B$91,[1]Baseline!$D$4:$AZ$91))} -> Working | E9: Governance | F9: =VLOOKUP($D9,'[1]SFIA Level'!$A$2:$B$6,2,FALSE) -> 2 | G9: 2 | H9: =I9-F9 -> 0 | I9: 2
A10: John Watson | B10: Senior Systems Administrator | C10: =VLOOKUP([1]Competence!$B20,[1]Competence!$B$12:$B$100,1,FALSE) -> Service level management | D10: {=_xlfn.XLOOKUP(B10,[1]Baseline!$D$3:$AZ$3,_xlfn.XLOOKUP(C10,[1]Baseline!$B$4:$B$91,[1]Baseline!$D$4:$AZ$91))} -> Practitioner | E10: Technical | F10: =VLOOKUP($D10,'[1]SFIA Level'!$A$2:$B$6,2,FALSE) -> 3 | G10: 2 | H10: =I10-F10 -> -1 | I10: 2
A11: John Watson | B11: Senior Systems Administrator | C11: =VLOOKUP([1]Competence!$B21,[1]Competence!$B$12:$B$100,1,FALSE) -> Availability Management | D11: {=_xlfn.XLOOKUP(B11,[1]Baseline!$D$3:$AZ$3,_xlfn.XLOOKUP(C11,[1]Baseline!$B$4:$B$91,[1]Baseline!$D$4:$AZ$91))} -> Awareness | E11: Technical | F11: =VLOOKUP($D11,'[1]SFIA Level'!$A$2:$B$6,2,FALSE) -> 1 | G11: 3 | H11: =I11-F11 -> 2 | I11: 3
A12: John Watson | B12: Senior Systems Administrator | C12: =VLOOKUP([1]Competence!$B22,[1]Competence!$B$12:$B$100,1,FALSE) -> Capacity management | D12: {=_xlfn.XLOOKUP(B12,[1]Baseline!$D$3:$AZ$3,_xlfn.XLOOKUP(C12,[1]Baseline!$B$4:$B$91,[1]Baseline!$D$4:$AZ$91))} -> No Knowledge | E12: Business | F12: =VLOOKUP($D12,'[1]SFIA Level'!$A$2:$B$6,2,FALSE) -> 0 | G12: 3 | H12: =I12-F12 -> 3 | I12: 3
A13: John Watson | B13: Senior Systems Administrator | C13: =VLOOKUP([1]Competence!$B23,[1]Competence!$B$12:$B$100,1,FALSE) -> Configuration Management | D13: {=_xlfn.XLOOKUP(B13,[1]Baseline!$D$3:$AZ$3,_xlfn.XLOOKUP(C13,[1]Baseline!$B$4:$B$91,[1]Baseline!$D$4:$AZ$91))} -> Working | E13: Business | F13: =VLOOKUP($D13,'[1]SFIA Level'!$A$2:$B$6,2,FALSE) -> 2 | G13: 3 | H13: =I13-F13 -> 1 | I13: 3
... A89: John Watson | B89: Senior Systems Administrator | C89: =VLOOKUP([1]Competence!$B99,[1]Competence!$B$12:$B$100,1,FALSE) -> Quality assurance | D89: {=_xlfn.XLOOKUP(B89,[1]Baseline!$D$3:$AZ$3,_xlfn.XLOOKUP(C89,[1]Baseline!$B$4:$B$91,[1]Baseline!$D$4:$AZ$91))} -> Working | E89: Technical | F89: =VLOOKUP($D89,'[1]SFIA Level'!$A$2:$B$6,2,FALSE) -> 2 | G89: 0 | H89: =I89-F89 -> -2 | I89: 0
A90: Jane Marple | B90: Systems Analyst | C90: =VLOOKUP([1]Competence!$B12,[1]Competence!$B$12:$B$100,1,FALSE) -> Asset Management | D90: {=_xlfn.XLOOKUP(B90,[1]Baseline!$D$3:$AZ$3,_xlfn.XLOOKUP(C90,[1]Baseline!$B$4:$B$91,[1]Baseline!$D$4:$AZ$91))} -> Working | E90: Core | F90: =VLOOKUP($D90,'[1]SFIA Level'!$A$2:$B$6,2,FALSE) -> 2 | G90: 2 | H90: =I90-F90 -> 0 | I90: 2
A91: Jane Marple | B91: Systems Analyst | C91: =VLOOKUP([1]Competence!$B13,[1]Competence!$B$12:$B$100,1,FALSE) -> Change Control | D91: {=_xlfn.XLOOKUP(B91,[1]Baseline!$D$3:$AZ$3,_xlfn.XLOOKUP(C91,[1]Baseline!$B$4:$B$91,[1]Baseline!$D$4:$AZ$91))} -> Working | E91: Core | F91: =VLOOKUP($D91,'[1]SFIA Level'!$A$2:$B$6,2,FALSE) -> 2 | G91: 1 | H91: =I91-F91 -> -1 | I91: 1
A92: Jane Marple | B92: Systems Analyst | C92: =VLOOKUP([1]Competence!$B14,[1]Competence!$B$12:$B$100,1,FALSE) -> Customer Service Support | D92: {=_xlfn.XLOOKUP(B92,[1]Baseline!$D$3:$AZ$3,_xlfn.XLOOKUP(C92,[1]Baseline!$B$4:$B$91,[1]Baseline!$D$4:$AZ$91))} -> Practitioner | E92: Core | F92: =VLOOKUP($D92,'[1]SFIA Level'!$A$2:$B$6,2,FALSE) -> 3 | G92: 3 | H92: =I92-F92 -> 0 | I92: 3
A93: Jane Marple | B93: Systems Analyst | C93: =VLOOKUP([1]Competence!$B15,[1]Competence!$B$12:$B$100,1,FALSE) -> Incident management | D93: {=_xlfn.XLOOKUP(B93,[1]Baseline!$D$3:$AZ$3,_xlfn.XLOOKUP(C93,[1]Baseline!$B$4:$B$91,[1]Baseline!$D$4:$AZ$91))} -> Working | E93: Core | F93: =VLOOKUP($D93,'[1]SFIA Level'!$A$2:$B$6,2,FALSE) -> 2 | G93: 3 | H93: =I93-F93 -> 1 | I93: 3
A94: Jane Marple | B94: Systems Analyst | C94: =VLOOKUP([1]Competence!$B16,[1]Competence!$B$12:$B$100,1,FALSE) -> Information security | D94: {=_xlfn.XLOOKUP(B94,[1]Baseline!$D$3:$AZ$3,_xlfn.XLOOKUP(C94,[1]Baseline!$B$4:$B$91,[1]Baseline!$D$4:$AZ$91))} -> Working | E94: Core | F94: =VLOOKUP($D94,'[1]SFIA Level'!$A$2:$B$6,2,FALSE) -> 2 | G94: 1 | H94: =I94-F94 -> -1 | I94: 1
A95: Jane Marple | B95: Systems Analyst | C95: =VLOOKUP([1]Competence!$B17,[1]Competence!$B$12:$B$100,1,FALSE) -> Personal data protection | D95: {=_xlfn.XLOOKUP(B95,[1]Baseline!$D$3:$AZ$3,_xlfn.XLOOKUP(C95,[1]Baseline!$B$4:$B$91,[1]Baseline!$D$4:$AZ$91))} -> Practitioner | E95: Service | F95: =VLOOKUP($D95,'[1]SFIA Level'!$A$2:$B$6,2,FALSE) -> 3 | G95: 2 | H95: =I95-F95 -> -1 | I95: 2
A96: Jane Marple | B96: Systems Analyst | C96: =VLOOKUP([1]Competence!$B18,[1]Competence!$B$12:$B$100,1,FALSE) -> Problem management | D96: {=_xlfn.XLOOKUP(B96,[1]Baseline!$D$3:$AZ$3,_xlfn.XLOOKUP(C96,[1]Baseline!$B$4:$B$91,[1]Baseline!$D$4:$AZ$91))} -> Working | E96: Service | F96: =VLOOKUP($D96,'[1]SFIA Level'!$A$2:$B$6,2,FALSE) -> 2 | G96: 1 | H96: =I96-F96 -> -1 | I96: 1
A97: Jane Marple | B97: Systems Analyst | C97: =VLOOKUP([1]Competence!$B19,[1]Competence!$B$12:$B$100,1,FALSE) -> Service catalogue management | D97: {=_xlfn.XLOOKUP(B97,[1]Baseline!$D$3:$AZ$3,_xlfn.XLOOKUP(C97,[1]Baseline!$B$4:$B$91,[1]Baseline!$D$4:$AZ$91))} -> Working | E97: Service | F97: =VLOOKUP($D97,'[1]SFIA Level'!$A$2:$B$6,2,FALSE) -> 2 | G97: 3 | H97: =I97-F97 -> 1 | I97: 3
A98: Jane Marple | B98: Systems Analyst | C98: =VLOOKUP([1]Competence!$B20,[1]Competence!$B$12:$B$100,1,FALSE) -> Service level management | D98: {=_xlfn.XLOOKUP(B98,[1]Baseline!$D$3:$AZ$3,_xlfn.XLOOKUP(C98,[1]Baseline!$B$4:$B$91,[1]Baseline!$D$4:$AZ$91))} -> Working | E98: Security | F98: =VLOOKUP($D98,'[1]SFIA Level'!$A$2:$B$6,2,FALSE) -> 2 | G98: 1 | H98: =I98-F98 -> -1 | I98: 1
A99: Jane Marple | B99: Systems Analyst | C99: =VLOOKUP([1]Competence!$B21,[1]Competence!$B$12:$B$100,1,FALSE) -> Availability Management | D99: {=_xlfn.XLOOKUP(B99,[1]Baseline!$D$3:$AZ$3,_xlfn.XLOOKUP(C99,[1]Baseline!$B$4:$B$91,[1]Baseline!$D$4:$AZ$91))} -> Awareness | E99: Security | F99: =VLOOKUP($D99,'[1]SFIA Level'!$A$2:$B$6,2,FALSE) -> 1 | G99: 1 | H99: =I99-F99 -> 0 | I99: 1
A100: Jane Marple | B100: Systems Analyst | C100: =VLOOKUP([1]Competence!$B22,[1]Competence!$B$12:$B$100,1,FALSE) -> Capacity management | D100: {=_xlfn.XLOOKUP(B100,[1]Baseline!$D$3:$AZ$3,_xlfn.XLOOKUP(C100,[1]Baseline!$B$4:$B$91,[1]Baseline!$D$4:$AZ$91))} -> No Knowledge | E100: Management | F100: =VLOOKUP($D100,'[1]SFIA Level'!$A$2:$B$6,2,FALSE) -> 0 | G100: 2 | H100: =I100-F100 -> 2 | I100: 2
A101: Jane Marple | B101: Systems Analyst | C101: =VLOOKUP([1]Competence!$B23,[1]Competence!$B$12:$B$100,1,FALSE) -> Configuration Management | D101: {=_xlfn.XLOOKUP(B101,[1]Baseline!$D$3:$AZ$3,_xlfn.XLOOKUP(C101,[1]Baseline!$B$4:$B$91,[1]Baseline!$D$4:$AZ$91))} -> Awareness | E101: Governance | F101: =VLOOKUP($D101,'[1]SFIA Level'!$A$2:$B$6,2,FALSE) -> 1 | G101: 3 | H101: =I101-F101 -> 2 | I101: 3
... A177: Jane Marple | B177: Systems Analyst | C177: =VLOOKUP([1]Competence!$B99,[1]Competence!$B$12:$B$100,1,FALSE) -> Quality assurance | D177: {=_xlfn.XLOOKUP(B177,[1]Baseline!$D$3:$AZ$3,_xlfn.XLOOKUP(C177,[1]Baseline!$B$4:$B$91,[1]Baseline!$D$4:$AZ$91))} -> Awareness | E177: Technical | F177: =VLOOKUP($D177,'[1]SFIA Level'!$A$2:$B$6,2,FALSE) -> 1 | G177: 1 | H177: =I177-F177 -> 0 | I177: 1
A178: Endeavour Morse | B178: Systems Administrator | C178: =VLOOKUP([1]Competence!$B12,[1]Competence!$B$12:$B$100,1,FALSE) -> Asset Management | D178: {=_xlfn.XLOOKUP(B178,[1]Baseline!$D$3:$AZ$3,_xlfn.XLOOKUP(C178,[1]Baseline!$B$4:$B$91,[1]Baseline!$D$4:$AZ$91))} -> Working | E178: Service | F178: 3 | G178: 3 | H178: =I178-F178 -> 0 | I178: 3
A179: Endeavour Morse | B179: Systems Administrator | C179: =VLOOKUP([1]Competence!$B13,[1]Competence!$B$12:$B$100,1,FALSE) -> Change Control | D179: {=_xlfn.XLOOKUP(B179,[1]Baseline!$D$3:$AZ$3,_xlfn.XLOOKUP(C179,[1]Baseline!$B$4:$B$91,[1]Baseline!$D$4:$AZ$91))} -> Working | E179: Core | F179: 3 | G179: 1 | H179: =I179-F179 -> -2 | I179: 1
A180: Endeavour Morse | B180: Systems Administrator | C180: =VLOOKUP([1]Competence!$B14,[1]Competence!$B$12:$B$100,1,FALSE) -> Customer Service Support | D180: {=_xlfn.XLOOKUP(B180,[1]Baseline!$D$3:$AZ$3,_xlfn.XLOOKUP(C180,[1]Baseline!$B$4:$B$91,[1]Baseline!$D$4:$AZ$91))} -> Practitioner | E180: Service | F180: 2 | G180: 3 | H180: =I180-F180 -> 1 | I180: 3
A181: Endeavour Morse | B181: Systems Administrator | C181: =VLOOKUP([1]Competence!$B15,[1]Competence!$B$12:$B$100,1,FALSE) -> Incident management | D181: {=_xlfn.XLOOKUP(B181,[1]Baseline!$D$3:$AZ$3,_xlfn.XLOOKUP(C181,[1]Baseline!$B$4:$B$91,[1]Baseline!$D$4:$AZ$91))} -> Practitioner | E181: Service | F181: 2 | G181: 4 | H181: =I181-F181 -> 2 | I181: 4
A182: Endeavour Morse | B182: Systems Administrator | C182: =VLOOKUP([1]Competence!$B16,[1]Competence!$B$12:$B$100,1,FALSE) -> Information security | D182: {=_xlfn.XLOOKUP(B182,[1]Baseline!$D$3:$AZ$3,_xlfn.XLOOKUP(C182,[1]Baseline!$B$4:$B$91,[1]Baseline!$D$4:$AZ$91))} -> Working | E182: Service | F182: 2 | G182: 3 | H182: =I182-F182 -> 1 | I182: 3
A183: Endeavour Morse | B183: Systems Administrator | C183: =VLOOKUP([1]Competence!$B17,[1]Competence!$B$12:$B$100,1,FALSE) -> Personal data protection | D183: {=_xlfn.XLOOKUP(B183,[1]Baseline!$D$3:$AZ$3,_xlfn.XLOOKUP(C183,[1]Baseline!$B$4:$B$91,[1]Baseline!$D$4:$AZ$91))} -> Practitioner | E183: Security | F183: 2 | G183: 3 | H183: =I183-F183 -> 1 | I183: 3
A184: Endeavour Morse | B184: Systems Administrator | C184: =VLOOKUP([1]Competence!$B18,[1]Competence!$B$12:$B$100,1,FALSE) -> Problem management | D184: {=_xlfn.XLOOKUP(B184,[1]Baseline!$D$3:$AZ$3,_xlfn.XLOOKUP(C184,[1]Baseline!$B$4:$B$91,[1]Baseline!$D$4:$AZ$91))} -> Working | E184: Governance | F184: 2 | G184: 3 | H184: =I184-F184 -> 1 | I184: 3
A185: Endeavour Morse | B185: Systems Administrator | C185: =VLOOKUP([1]Competence!$B19,[1]Competence!$B$12:$B$100,1,FALSE) -> Service catalogue management | D185: {=_xlfn.XLOOKUP(B185,[1]Baseline!$D$3:$AZ$3,_xlfn.XLOOKUP(C185,[1]Baseline!$B$4:$B$91,[1]Baseline!$D$4:$AZ$91))} -> Working | E185: Governance | F185: 2 | G185: 3 | H185: =I185-F185 -> 1 | I185: 3
A186: Endeavour Morse | B186: Systems Administrator | C186: =VLOOKUP([1]Competence!$B20,[1]Competence!$B$12:$B$100,1,FALSE) -> Service level management | D186: {=_xlfn.XLOOKUP(B186,[1]Baseline!$D$3:$AZ$3,_xlfn.XLOOKUP(C186,[1]Baseline!$B$4:$B$91,[1]Baseline!$D$4:$AZ$91))} -> Working | E186: Technical | F186: 3 | G186: 3 | H186: =I186-F186 -> 0 | I186: 3
A187: Endeavour Morse | B187: Systems Administrator | C187: =VLOOKUP([1]Competence!$B21,[1]Competence!$B$12:$B$100,1,FALSE) -> Availability Management | D187: {=_xlfn.XLOOKUP(B187,[1]Baseline!$D$3:$AZ$3,_xlfn.XLOOKUP(C187,[1]Baseline!$B$4:$B$91,[1]Baseline!$D$4:$AZ$91))} -> Awareness | E187: Technical | F187: 2 | G187: 3 | H187: =I187-F187 -> 1 | I187: 3
A188: Endeavour Morse | B188: Systems Administrator | C188: =VLOOKUP([1]Competence!$B22,[1]Competence!$B$12:$B$100,1,FALSE) -> Capacity management | D188: {=_xlfn.XLOOKUP(B188,[1]Baseline!$D$3:$AZ$3,_xlfn.XLOOKUP(C188,[1]Baseline!$B$4:$B$91,[1]Baseline!$D$4:$AZ$91))} -> No Knowledge | E188: Technical | F188: 3 | G188: 0 | H188: =I188-F188 -> -3 | I188: 0
A189: Endeavour Morse | B189: Systems Administrator | C189: =VLOOKUP([1]Competence!$B23,[1]Competence!$B$12:$B$100,1,FALSE) -> Configuration Management | D189: {=_xlfn.XLOOKUP(B189,[1]Baseline!$D$3:$AZ$3,_xlfn.XLOOKUP(C189,[1]Baseline!$B$4:$B$91,[1]Baseline!$D$4:$AZ$91))} -> Awareness | E189: Technical | F189: 2 | G189: 1 | H189: =I189-F189 -> -1 | I189: 1
... A265: Endeavour Morse | B265: Systems Administrator | C265: =VLOOKUP([1]Competence!$B99,[1]Competence!$B$12:$B$100,1,FALSE) -> Quality assurance | D265: {=_xlfn.XLOOKUP(B265,[1]Baseline!$D$3:$AZ$3,_xlfn.XLOOKUP(C265,[1]Baseline!$B$4:$B$91,[1]Baseline!$D$4:$AZ$91))} -> Awareness | E265: Technical | F265: 0 | G265: 0 | H265: =I265-F265 -> 0 | I265: 0
A266: Robbie Lewis | B266: Senior Systems Analyst Ful | C266: =VLOOKUP([1]Competence!$B12,[1]Competence!$B$12:$B$100,1,FALSE) -> Asset Management | D266: {=_xlfn.XLOOKUP(B266,[1]Baseline!$D$3:$AZ$3,_xlfn.XLOOKUP(C266,[1]Baseline!$B$4:$B$91,[1]Baseline!$D$4:$AZ$91))} -> Practitioner | E266: Governance | F266: 4 | G266: 3 | H266: =I266-F266 -> -1 | I266: 3
A267: Robbie Lewis | B267: Senior Systems Analyst Ful | C267: =VLOOKUP([1]Competence!$B13,[1]Competence!$B$12:$B$100,1,FALSE) -> Change Control | D267: {=_xlfn.XLOOKUP(B267,[1]Baseline!$D$3:$AZ$3,_xlfn.XLOOKUP(C267,[1]Baseline!$B$4:$B$91,[1]Baseline!$D$4:$AZ$91))} -> Practitioner | E267: Management | F267: 2 | G267: 3 | H267: =I267-F267 -> 1 | I267: 3
A268: Robbie Lewis | B268: Senior Systems Analyst Ful | C268: =VLOOKUP([1]Competence!$B14,[1]Competence!$B$12:$B$100,1,FALSE) -> Customer Service Support | D268: {=_xlfn.XLOOKUP(B268,[1]Baseline!$D$3:$AZ$3,_xlfn.XLOOKUP(C268,[1]Baseline!$B$4:$B$91,[1]Baseline!$D$4:$AZ$91))} -> Practitioner | E268: Governance | F268: 3 | G268: 3 | H268: =I268-F268 -> 0 | I268: 3
A269: Robbie Lewis | B269: Senior Systems Analyst Ful | C269: =VLOOKUP([1]Competence!$B15,[1]Competence!$B$12:$B$100,1,FALSE) -> Incident management | D269: {=_xlfn.XLOOKUP(B269,[1]Baseline!$D$3:$AZ$3,_xlfn.XLOOKUP(C269,[1]Baseline!$B$4:$B$91,[1]Baseline!$D$4:$AZ$91))} -> Practitioner | E269: Governance | F269: 2 | G269: 3 | H269: =I269-F269 -> 1 | I269: 3
A270: Robbie Lewis | B270: Senior Systems Analyst Ful | C270: =VLOOKUP([1]Competence!$B16,[1]Competence!$B$12:$B$100,1,FALSE) -> Information security | D270: {=_xlfn.XLOOKUP(B270,[1]Baseline!$D$3:$AZ$3,_xlfn.XLOOKUP(C270,[1]Baseline!$B$4:$B$91,[1]Baseline!$D$4:$AZ$91))} -> Practitioner | E270: Governance | F270: 3 | G270: 2 | H270: =I270-F270 -> -1 | I270: 2
A271: Robbie Lewis | B271: Senior Systems Analyst Ful | C271: =VLOOKUP([1]Competence!$B17,[1]Competence!$B$12:$B$100,1,FALSE) -> Personal data protection | D271: {=_xlfn.XLOOKUP(B271,[1]Baseline!$D$3:$AZ$3,_xlfn.XLOOKUP(C271,[1]Baseline!$B$4:$B$91,[1]Baseline!$D$4:$AZ$91))} -> Practitioner | E271: Core | F271: 4 | G271: 3 | H271: =I271-F271 -> -1 | I271: 3
A272: Robbie Lewis | B272: Senior Systems Analyst Ful | C272: =VLOOKUP([1]Competence!$B18,[1]Competence!$B$12:$B$100,1,FALSE) -> Problem management | D272: {=_xlfn.XLOOKUP(B272,[1]Baseline!$D$3:$AZ$3,_xlfn.XLOOKUP(C272,[1]Baseline!$B$4:$B$91,[1]Baseline!$D$4:$AZ$91))} -> Practitioner | E272: Core | F272: 3 | G272: 3 | H272: =I272-F272 -> 0 | I272: 3
A273: Robbie Lewis | B273: Senior Systems Analyst Ful | C273: =VLOOKUP([1]Competence!$B19,[1]Competence!$B$12:$B$100,1,FALSE) -> Service catalogue management | D273: {=_xlfn.XLOOKUP(B273,[1]Baseline!$D$3:$AZ$3,_xlfn.XLOOKUP(C273,[1]Baseline!$B$4:$B$91,[1]Baseline!$D$4:$AZ$91))} -> Practitioner | E273: Service | F273: 2 | G273: 3 | H273: =I273-F273 -> 1 | I273: 3
A274: Robbie Lewis | B274: Senior Systems Analyst Ful | C274: =VLOOKUP([1]Competence!$B20,[1]Competence!$B$12:$B$100,1,FALSE) -> Service level management | D274: {=_xlfn.XLOOKUP(B274,[1]Baseline!$D$3:$AZ$3,_xlfn.XLOOKUP(C274,[1]Baseline!$B$4:$B$91,[1]Baseline!$D$4:$AZ$91))} -> Working | E274: Security | F274: 3 | G274: 2 | H274: =I274-F274 -> -1 | I274: 2
A275: Robbie Lewis | B275: Senior Systems Analyst Ful | C275: =VLOOKUP([1]Competence!$B21,[1]Competence!$B$12:$B$100,1,FALSE) -> Availability Management | D275: {=_xlfn.XLOOKUP(B275,[1]Baseline!$D$3:$AZ$3,_xlfn.XLOOKUP(C275,[1]Baseline!$B$4:$B$91,[1]Baseline!$D$4:$AZ$91))} -> Working | E275: Management | F275: 2 | G275: 2 | H275: =I275-F275 -> 0 | I275: 2
A276: Robbie Lewis | B276: Senior Systems Analyst Ful | C276: =VLOOKUP([1]Competence!$B22,[1]Competence!$B$12:$B$100,1,FALSE) -> Capacity management | D276: {=_xlfn.XLOOKUP(B276,[1]Baseline!$D$3:$AZ$3,_xlfn.XLOOKUP(C276,[1]Baseline!$B$4:$B$91,[1]Baseline!$D$4:$AZ$91))} -> No Knowledge | E276: Management | F276: 2 | G276: 1 | H276: =I276-F276 -> -1 | I276: 1
A277: Robbie Lewis | B277: Senior Systems Analyst Ful | C277: =VLOOKUP([1]Competence!$B23,[1]Competence!$B$12:$B$100,1,FALSE) -> Configuration Management | D277: {=_xlfn.XLOOKUP(B277,[1]Baseline!$D$3:$AZ$3,_xlfn.XLOOKUP(C277,[1]Baseline!$B$4:$B$91,[1]Baseline!$D$4:$AZ$91))} -> Awareness | E277: Governance | F277: 2 | G277: 1 | H277: =I277-F277 -> -1 | I277: 1
... A353: Robbie Lewis | B353: Senior Systems Analyst Ful | C353: =VLOOKUP([1]Competence!$B99,[1]Competence!$B$12:$B$100,1,FALSE) -> Quality assurance | D353: {=_xlfn.XLOOKUP(B353,[1]Baseline!$D$3:$AZ$3,_xlfn.XLOOKUP(C353,[1]Baseline!$B$4:$B$91,[1]Baseline!$D$4:$AZ$91))} -> Working | E353: Business | F353: 0 | G353: 1 | H353: =I353-F353 -> 1 | I353: 1
A354: James Hathaway | B354: Software Engineer | C354: =VLOOKUP([1]Competence!$B12,[1]Competence!$B$12:$B$100,1,FALSE) -> Asset Management | D354: {=_xlfn.XLOOKUP(B354,[1]Baseline!$D$3:$AZ$3,_xlfn.XLOOKUP(C354,[1]Baseline!$B$4:$B$91,[1]Baseline!$D$4:$AZ$91))} -> Working | E354: Security | F354: 3 | G354: 2 | H354: =I354-F354 -> -1 | I354: 2
A355: James Hathaway | B355: Software Engineer | C355: =VLOOKUP([1]Competence!$B13,[1]Competence!$B$12:$B$100,1,FALSE) -> Change Control | D355: {=_xlfn.XLOOKUP(B355,[1]Baseline!$D$3:$AZ$3,_xlfn.XLOOKUP(C355,[1]Baseline!$B$4:$B$91,[1]Baseline!$D$4:$AZ$91))} -> Practitioner | E355: Security | F355: 3 | G355: 2 | H355: =I355-F355 -> -1 | I355: 2
A356: James Hathaway | B356: Software Engineer | C356: =VLOOKUP([1]Competence!$B14,[1]Competence!$B$12:$B$100,1,FALSE) -> Customer Service Support | D356: {=_xlfn.XLOOKUP(B356,[1]Baseline!$D$3:$AZ$3,_xlfn.XLOOKUP(C356,[1]Baseline!$B$4:$B$91,[1]Baseline!$D$4:$AZ$91))} -> Practitioner | E356: Service | F356: 3 | G356: 2 | H356: =I356-F356 -> -1 | I356: 2
A357: James Hathaway | B357: Software Engineer | C357: =VLOOKUP([1]Competence!$B15,[1]Competence!$B$12:$B$100,1,FALSE) -> Incident management | D357: {=_xlfn.XLOOKUP(B357,[1]Baseline!$D$3:$AZ$3,_xlfn.XLOOKUP(C357,[1]Baseline!$B$4:$B$91,[1]Baseline!$D$4:$AZ$91))} -> Working | E357: Security | F357: 3 | G357: 2 | H357: =I357-F357 -> -1 | I357: 2
A358: James Hathaway | B358: Software Engineer | C358: =VLOOKUP([1]Competence!$B16,[1]Competence!$B$12:$B$100,1,FALSE) -> Information security | D358: {=_xlfn.XLOOKUP(B358,[1]Baseline!$D$3:$AZ$3,_xlfn.XLOOKUP(C358,[1]Baseline!$B$4:$B$91,[1]Baseline!$D$4:$AZ$91))} -> Practitioner | E358: Security | F358: 3 | G358: 2 | H358: =I358-F358 -> -1 | I358: 2
A359: James Hathaway | B359: Software Engineer | C359: =VLOOKUP([1]Competence!$B17,[1]Competence!$B$12:$B$100,1,FALSE) -> Personal data protection | D359: {=_xlfn.XLOOKUP(B359,[1]Baseline!$D$3:$AZ$3,_xlfn.XLOOKUP(C359,[1]Baseline!$B$4:$B$91,[1]Baseline!$D$4:$AZ$91))} -> Practitioner | E359: Governance | F359: 2 | G359: 2 | H359: =I359-F359 -> 0 | I359: 2
A360: James Hathaway | B360: Software Engineer | C360: =VLOOKUP([1]Competence!$B18,[1]Competence!$B$12:$B$100,1,FALSE) -> Problem management | D360: {=_xlfn.XLOOKUP(B360,[1]Baseline!$D$3:$AZ$3,_xlfn.XLOOKUP(C360,[1]Baseline!$B$4:$B$91,[1]Baseline!$D$4:$AZ$91))} -> Working | E360: Core | F360: 3 | G360: 2 | H360: =I360-F360 -> -1 | I360: 2
A361: James Hathaway | B361: Software Engineer | C361: =VLOOKUP([1]Competence!$B19,[1]Competence!$B$12:$B$100,1,FALSE) -> Service catalogue management | D361: {=_xlfn.XLOOKUP(B361,[1]Baseline!$D$3:$AZ$3,_xlfn.XLOOKUP(C361,[1]Baseline!$B$4:$B$91,[1]Baseline!$D$4:$AZ$91))} -> Working | E361: Core | F361: 3 | G361: 2 | H361: =I361-F361 -> -1 | I361: 2
A362: James Hathaway | B362: Software Engineer | C362: =VLOOKUP([1]Competence!$B20,[1]Competence!$B$12:$B$100,1,FALSE) -> Service level management | D362: {=_xlfn.XLOOKUP(B362,[1]Baseline!$D$3:$AZ$3,_xlfn.XLOOKUP(C362,[1]Baseline!$B$4:$B$91,[1]Baseline!$D$4:$AZ$91))} -> Working | E362: Core | F362: 3 | G362: 1 | H362: =I362-F362 -> -2 | I362: 1
A363: James Hathaway | B363: Software Engineer | C363: =VLOOKUP([1]Competence!$B21,[1]Competence!$B$12:$B$100,1,FALSE) -> Availability Management | D363: {=_xlfn.XLOOKUP(B363,[1]Baseline!$D$3:$AZ$3,_xlfn.XLOOKUP(C363,[1]Baseline!$B$4:$B$91,[1]Baseline!$D$4:$AZ$91))} -> Working | E363: Core | F363: 2 | G363: 1 | H363: =I363-F363 -> -1 | I363: 1
A364: James Hathaway | B364: Software Engineer | C364: =VLOOKUP([1]Competence!$B22,[1]Competence!$B$12:$B$100,1,FALSE) -> Capacity management | D364: {=_xlfn.XLOOKUP(B364,[1]Baseline!$D$3:$AZ$3,_xlfn.XLOOKUP(C364,[1]Baseline!$B$4:$B$91,[1]Baseline!$D$4:$AZ$91))} -> Working | E364: Service | F364: 2 | G364: 2 | H364: =I364-F364 -> 0 | I364: 2
A365: James Hathaway | B365: Software Engineer | C365: =VLOOKUP([1]Competence!$B23,[1]Competence!$B$12:$B$100,1,FALSE) -> Configuration Management | D365: {=_xlfn.XLOOKUP(B365,[1]Baseline!$D$3:$AZ$3,_xlfn.XLOOKUP(C365,[1]Baseline!$B$4:$B$91,[1]Baseline!$D$4:$AZ$91))} -> Working | E365: Service | F365: 2 | G365: 2 | H365: =I365-F365 -> 0 | I365: 2
... A441: James Hathaway | B441: Software Engineer | C441: =VLOOKUP([1]Competence!$B99,[1]Competence!$B$12:$B$100,1,FALSE) -> Quality assurance | D441: {=_xlfn.XLOOKUP(B441,[1]Baseline!$D$3:$AZ$3,_xlfn.XLOOKUP(C441,[1]Baseline!$B$4:$B$91,[1]Baseline!$D$4:$AZ$91))} -> No Knowledge | E441: Technical | F441: 0 | G441: 2 | H441: =I441-F441 -> 2 | I441: 2
A442: Jack Frost | B442: Senior Systems Administrator | C442: =VLOOKUP([1]Competence!$B12,[1]Competence!$B$12:$B$100,1,FALSE) -> Asset Management | D442: {=_xlfn.XLOOKUP(B442,[1]Baseline!$D$3:$AZ$3,_xlfn.XLOOKUP(C442,[1]Baseline!$B$4:$B$91,[1]Baseline!$D$4:$AZ$91))} -> Practitioner | E442: Governance | F442: 2 | G442: 3 | H442: =I442-F442 -> 1 | I442: 3
A443: Jack Frost | B443: Senior Systems Administrator | C443: =VLOOKUP([1]Competence!$B13,[1]Competence!$B$12:$B$100,1,FALSE) -> Change Control | D443: {=_xlfn.XLOOKUP(B443,[1]Baseline!$D$3:$AZ$3,_xlfn.XLOOKUP(C443,[1]Baseline!$B$4:$B$91,[1]Baseline!$D$4:$AZ$91))} -> Practitioner | E443: Technical | F443: 2 | G443: 2 | H443: =I443-F443 -> 0 | I443: 2
A444: Jack Frost | B444: Senior Systems Administrator | C444: =VLOOKUP([1]Competence!$B14,[1]Competence!$B$12:$B$100,1,FALSE) -> Customer Service Support | D444: {=_xlfn.XLOOKUP(B444,[1]Baseline!$D$3:$AZ$3,_xlfn.XLOOKUP(C444,[1]Baseline!$B$4:$B$91,[1]Baseline!$D$4:$AZ$91))} -> Practitioner | E444: Technical | F444: 3 | G444: 3 | H444: =I444-F444 -> 0 | I444: 3
A445: Jack Frost | B445: Senior Systems Administrator | C445: =VLOOKUP([1]Competence!$B15,[1]Competence!$B$12:$B$100,1,FALSE) -> Incident management | D445: {=_xlfn.XLOOKUP(B445,[1]Baseline!$D$3:$AZ$3,_xlfn.XLOOKUP(C445,[1]Baseline!$B$4:$B$91,[1]Baseline!$D$4:$AZ$91))} -> Practitioner | E445: Technical | F445: 3 | G445: 3 | H445: =I445-F445 -> 0 | I445: 3
A446: Jack Frost | B446: Senior Systems Administrator | C446: =VLOOKUP([1]Competence!$B16,[1]Competence!$B$12:$B$100,1,FALSE) -> Information security | D446: {=_xlfn.XLOOKUP(B446,[1]Baseline!$D$3:$AZ$3,_xlfn.XLOOKUP(C446,[1]Baseline!$B$4:$B$91,[1]Baseline!$D$4:$AZ$91))} -> Practitioner | E446: Technical | F446: 2 | G446: 2 | H446: =I446-F446 -> 0 | I446: 2
A447: Jack Frost | B447: Senior Systems Administrator | C447: =VLOOKUP([1]Competence!$B17,[1]Competence!$B$12:$B$100,1,FALSE) -> Personal data protection | D447: {=_xlfn.XLOOKUP(B447,[1]Baseline!$D$3:$AZ$3,_xlfn.XLOOKUP(C447,[1]Baseline!$B$4:$B$91,[1]Baseline!$D$4:$AZ$91))} -> Practitioner | E447: Technical | F447: 2 | G447: 3 | H447: =I447-F447 -> 1 | I447: 3
A448: Jack Frost | B448: Senior Systems Administrator | C448: =VLOOKUP([1]Competence!$B18,[1]Competence!$B$12:$B$100,1,FALSE) -> Problem management | D448: {=_xlfn.XLOOKUP(B448,[1]Baseline!$D$3:$AZ$3,_xlfn.XLOOKUP(C448,[1]Baseline!$B$4:$B$91,[1]Baseline!$D$4:$AZ$91))} -> Working | E448: Business | F448: 2 | G448: 3 | H448: =I448-F448 -> 1 | I448: 3
A449: Jack Frost | B449: Senior Systems Administrator | C449: =VLOOKUP([1]Competence!$B19,[1]Competence!$B$12:$B$100,1,FALSE) -> Service catalogue management | D449: {=_xlfn.XLOOKUP(B449,[1]Baseline!$D$3:$AZ$3,_xlfn.XLOOKUP(C449,[1]Baseline!$B$4:$B$91,[1]Baseline!$D$4:$AZ$91))} -> Working | E449: Business | F449: 2 | G449: 3 | H449: =I449-F449 -> 1 | I449: 3
A450: Jack Frost | B450: Senior Systems Administrator | C450: =VLOOKUP([1]Competence!$B20,[1]Competence!$B$12:$B$100,1,FALSE) -> Service level management | D450: {=_xlfn.XLOOKUP(B450,[1]Baseline!$D$3:$AZ$3,_xlfn.XLOOKUP(C450,[1]Baseline!$B$4:$B$91,[1]Baseline!$D$4:$AZ$91))} -> Practitioner | E450: Business | F450: 2 | G450: 2 | H450: =I450-F450 -> 0 | I450: 2
A451: Jack Frost | B451: Senior Systems Administrator | C451: =VLOOKUP([1]Competence!$B21,[1]Competence!$B$12:$B$100,1,FALSE) -> Availability Management | D451: {=_xlfn.XLOOKUP(B451,[1]Baseline!$D$3:$AZ$3,_xlfn.XLOOKUP(C451,[1]Baseline!$B$4:$B$91,[1]Baseline!$D$4:$AZ$91))} -> Awareness | E451: Business | F451: 2 | G451: 1 | H451: =I451-F451 -> -1 | I451: 1
A452: Jack Frost | B452: Senior Systems Administrator | C452: =VLOOKUP([1]Competence!$B22,[1]Competence!$B$12:$B$100,1,FALSE) -> Capacity management | D452: {=_xlfn.XLOOKUP(B452,[1]Baseline!$D$3:$AZ$3,_xlfn.XLOOKUP(C452,[1]Baseline!$B$4:$B$91,[1]Baseline!$D$4:$AZ$91))} -> No Knowledge | E452: Core | F452: 3 | G452: 1 | H452: =I452-F452 -> -2 | I452: 1
A453: Jack Frost | B453: Senior Systems Administrator | C453: =VLOOKUP([1]Competence!$B23,[1]Competence!$B$12:$B$100,1,FALSE) -> Configuration Management | D453: {=_xlfn.XLOOKUP(B453,[1]Baseline!$D$3:$AZ$3,_xlfn.XLOOKUP(C453,[1]Baseline!$B$4:$B$91,[1]Baseline!$D$4:$AZ$91))} -> Working | E453: Core | F453: 3 | G453: 1 | H453: =I453-F453 -> -2 | I453: 1
... A529: Jack Frost | B529: Senior Systems Administrator | C529: =VLOOKUP([1]Competence!$B99,[1]Competence!$B$12:$B$100,1,FALSE) -> Quality assurance | D529: {=_xlfn.XLOOKUP(B529,[1]Baseline!$D$3:$AZ$3,_xlfn.XLOOKUP(C529,[1]Baseline!$B$4:$B$91,[1]Baseline!$D$4:$AZ$91))} -> Working | E529: Technical | F529: 0 | G529: 2 | H529: =I529-F529 -> 2 | I529: 2
A530: Christopher Foyle | B530: Fulfilment Lead | C530: =VLOOKUP([1]Competence!$B12,[1]Competence!$B$12:$B$100,1,FALSE) -> Asset Management | D530: {=_xlfn.XLOOKUP(B530,[1]Baseline!$D$3:$AZ$3,_xlfn.XLOOKUP(C530,[1]Baseline!$B$4:$B$91,[1]Baseline!$D$4:$AZ$91))} -> Practitioner | E530: Technical | F530: 1 | G530: 3 | H530: =I530-F530 -> 2 | I530: 3
A531: Christopher Foyle | B531: Fulfilment Lead | C531: =VLOOKUP([1]Competence!$B13,[1]Competence!$B$12:$B$100,1,FALSE) -> Change Control | D531: {=_xlfn.XLOOKUP(B531,[1]Baseline!$D$3:$AZ$3,_xlfn.XLOOKUP(C531,[1]Baseline!$B$4:$B$91,[1]Baseline!$D$4:$AZ$91))} -> Expert | E531: Technical | F531: 2 | G531: 3 | H531: =I531-F531 -> 1 | I531: 3
A532: Christopher Foyle | B532: Fulfilment Lead | C532: =VLOOKUP([1]Competence!$B14,[1]Competence!$B$12:$B$100,1,FALSE) -> Customer Service Support | D532: {=_xlfn.XLOOKUP(B532,[1]Baseline!$D$3:$AZ$3,_xlfn.XLOOKUP(C532,[1]Baseline!$B$4:$B$91,[1]Baseline!$D$4:$AZ$91))} -> Expert | E532: Core | F532: 2 | G532: 4 | H532: =I532-F532 -> 2 | I532: 4
A533: Christopher Foyle | B533: Fulfilment Lead | C533: =VLOOKUP([1]Competence!$B15,[1]Competence!$B$12:$B$100,1,FALSE) -> Incident management | D533: {=_xlfn.XLOOKUP(B533,[1]Baseline!$D$3:$AZ$3,_xlfn.XLOOKUP(C533,[1]Baseline!$B$4:$B$91,[1]Baseline!$D$4:$AZ$91))} -> Expert | E533: Technical | F533: 1 | G533: 4 | H533: =I533-F533 -> 3 | I533: 4
A534: Christopher Foyle | B534: Fulfilment Lead | C534: =VLOOKUP([1]Competence!$B16,[1]Competence!$B$12:$B$100,1,FALSE) -> Information security | D534: {=_xlfn.XLOOKUP(B534,[1]Baseline!$D$3:$AZ$3,_xlfn.XLOOKUP(C534,[1]Baseline!$B$4:$B$91,[1]Baseline!$D$4:$AZ$91))} -> Practitioner | E534: Governance | F534: 1 | G534: 3 | H534: =I534-F534 -> 2 | I534: 3
A535: Christopher Foyle | B535: Fulfilment Lead | C535: =VLOOKUP([1]Competence!$B17,[1]Competence!$B$12:$B$100,1,FALSE) -> Personal data protection | D535: {=_xlfn.XLOOKUP(B535,[1]Baseline!$D$3:$AZ$3,_xlfn.XLOOKUP(C535,[1]Baseline!$B$4:$B$91,[1]Baseline!$D$4:$AZ$91))} -> Practitioner | E535: Technical | F535: 0 | G535: 3 | H535: =I535-F535 -> 3 | I535: 3
A536: Christopher Foyle | B536: Fulfilment Lead | C536: =VLOOKUP([1]Competence!$B18,[1]Competence!$B$12:$B$100,1,FALSE) -> Problem management | D536: {=_xlfn.XLOOKUP(B536,[1]Baseline!$D$3:$AZ$3,_xlfn.XLOOKUP(C536,[1]Baseline!$B$4:$B$91,[1]Baseline!$D$4:$AZ$91))} -> Expert | E536: Service | F536: 1 | G536: 2 | H536: =I536-F536 -> 1 | I536: 2
A537: Christopher Foyle | B537: Fulfilment Lead | C537: =VLOOKUP([1]Competence!$B19,[1]Competence!$B$12:$B$100,1,FALSE) -> Service catalogue management | D537: {=_xlfn.XLOOKUP(B537,[1]Baseline!$D$3:$AZ$3,_xlfn.XLOOKUP(C537,[1]Baseline!$B$4:$B$91,[1]Baseline!$D$4:$AZ$91))} -> Expert | E537: Business | F537: 0 | G537: 3 | H537: =I537-F537 -> 3 | I537: 3
A538: Christopher Foyle | B538: Fulfilment Lead | C538: =VLOOKUP([1]Competence!$B20,[1]Competence!$B$12:$B$100,1,FALSE) -> Service level management | D538: {=_xlfn.XLOOKUP(B538,[1]Baseline!$D$3:$AZ$3,_xlfn.XLOOKUP(C538,[1]Baseline!$B$4:$B$91,[1]Baseline!$D$4:$AZ$91))} -> Expert | E538: Business | F538: 0 | G538: 3 | H538: =I538-F538 -> 3 | I538: 3
A539: Christopher Foyle | B539: Fulfilment Lead | C539: =VLOOKUP([1]Competence!$B21,[1]Competence!$B$12:$B$100,1,FALSE) -> Availability Management | D539: {=_xlfn.XLOOKUP(B539,[1]Baseline!$D$3:$AZ$3,_xlfn.XLOOKUP(C539,[1]Baseline!$B$4:$B$91,[1]Baseline!$D$4:$AZ$91))} -> Working | E539: Business | F539: 0 | G539: 2 | H539: =I539-F539 -> 2 | I539: 2
A540: Christopher Foyle | B540: Fulfilment Lead | C540: =VLOOKUP([1]Competence!$B22,[1]Competence!$B$12:$B$100,1,FALSE) -> Capacity management | D540: {=_xlfn.XLOOKUP(B540,[1]Baseline!$D$3:$AZ$3,_xlfn.XLOOKUP(C540,[1]Baseline!$B$4:$B$91,[1]Baseline!$D$4:$AZ$91))} -> No Knowledge | E540: Business | F540: 0 | G540: 1 | H540: =I540-F540 -> 1 | I540: 1
A541: Christopher Foyle | B541: Fulfilment Lead | C541: =VLOOKUP([1]Competence!$B23,[1]Competence!$B$12:$B$100,1,FALSE) -> Configuration Management | D541: {=_xlfn.XLOOKUP(B541,[1]Baseline!$D$3:$AZ$3,_xlfn.XLOOKUP(C541,[1]Baseline!$B$4:$B$91,[1]Baseline!$D$4:$AZ$91))} -> Awareness | E541: Business | F541: 0 | G541: 1 | H541: =I541-F541 -> 1 | I541: 1
... A617: Christopher Foyle | B617: Fulfilment Lead | C617: =VLOOKUP([1]Competence!$B99,[1]Competence!$B$12:$B$100,1,FALSE) -> Quality assurance | D617: {=_xlfn.XLOOKUP(B617,[1]Baseline!$D$3:$AZ$3,_xlfn.XLOOKUP(C617,[1]Baseline!$B$4:$B$91,[1]Baseline!$D$4:$AZ$91))} -> Working | E617: Management | F617: 0 | G617: 1 | H617: =I617-F617 -> 1 | I617: 1
A618: Tom Barnaby | B618: Senior Systems Administrator | C618: =VLOOKUP([1]Competence!$B12,[1]Competence!$B$12:$B$100,1,FALSE) -> Asset Management | D618: {=_xlfn.XLOOKUP(B618,[1]Baseline!$D$3:$AZ$3,_xlfn.XLOOKUP(C618,[1]Baseline!$B$4:$B$91,[1]Baseline!$D$4:$AZ$91))} -> Practitioner | E618: Business | F618: 3 | G618: 3 | H618: =I618-F618 -> 0 | I618: 3
A619: Tom Barnaby | B619: Senior Systems Administrator | C619: =VLOOKUP([1]Competence!$B13,[1]Competence!$B$12:$B$100,1,FALSE) -> Change Control | D619: {=_xlfn.XLOOKUP(B619,[1]Baseline!$D$3:$AZ$3,_xlfn.XLOOKUP(C619,[1]Baseline!$B$4:$B$91,[1]Baseline!$D$4:$AZ$91))} -> Practitioner | E619: Business | F619: 3 | G619: 3 | H619: =I619-F619 -> 0 | I619: 3
A620: Tom Barnaby | B620: Senior Systems Administrator | C620: =VLOOKUP([1]Competence!$B14,[1]Competence!$B$12:$B$100,1,FALSE) -> Customer Service Support | D620: {=_xlfn.XLOOKUP(B620,[1]Baseline!$D$3:$AZ$3,_xlfn.XLOOKUP(C620,[1]Baseline!$B$4:$B$91,[1]Baseline!$D$4:$AZ$91))} -> Practitioner | E620: Business | F620: 3 | G620: 3 | H620: =I620-F620 -> 0 | I620: 3
A621: Tom Barnaby | B621: Senior Systems Administrator | C621: =VLOOKUP([1]Competence!$B15,[1]Competence!$B$12:$B$100,1,FALSE) -> Incident management | D621: {=_xlfn.XLOOKUP(B621,[1]Baseline!$D$3:$AZ$3,_xlfn.XLOOKUP(C621,[1]Baseline!$B$4:$B$91,[1]Baseline!$D$4:$AZ$91))} -> Practitioner | E621: Business | F621: 3 | G621: 3 | H621: =I621-F621 -> 0 | I621: 3
A622: Tom Barnaby | B622: Senior Systems Administrator | C622: =VLOOKUP([1]Competence!$B16,[1]Competence!$B$12:$B$100,1,FALSE) -> Information security | D622: {=_xlfn.XLOOKUP(B622,[1]Baseline!$D$3:$AZ$3,_xlfn.XLOOKUP(C622,[1]Baseline!$B$4:$B$91,[1]Baseline!$D$4:$AZ$91))} -> Practitioner | E622: Core | F622: 3 | G622: 2 | H622: =I622-F622 -> -1 | I622: 2
A623: Tom Barnaby | B623: Senior Systems Administrator | C623: =VLOOKUP([1]Competence!$B17,[1]Competence!$B$12:$B$100,1,FALSE) -> Personal data protection | D623: {=_xlfn.XLOOKUP(B623,[1]Baseline!$D$3:$AZ$3,_xlfn.XLOOKUP(C623,[1]Baseline!$B$4:$B$91,[1]Baseline!$D$4:$AZ$91))} -> Practitioner | E623: Service | F623: 3 | G623: 3 | H623: =I623-F623 -> 0 | I623: 3
A624: Tom Barnaby | B624: Senior Systems Administrator | C624: =VLOOKUP([1]Competence!$B18,[1]Competence!$B$12:$B$100,1,FALSE) -> Problem management | D624: {=_xlfn.XLOOKUP(B624,[1]Baseline!$D$3:$AZ$3,_xlfn.XLOOKUP(C624,[1]Baseline!$B$4:$B$91,[1]Baseline!$D$4:$AZ$91))} -> Working | E624: Service | F624: 3 | G624: 3 | H624: =I624-F624 -> 0 | I624: 3
A625: Tom Barnaby | B625: Senior Systems Administrator | C625: =VLOOKUP([1]Competence!$B19,[1]Competence!$B$12:$B$100,1,FALSE) -> Service catalogue management | D625: {=_xlfn.XLOOKUP(B625,[1]Baseline!$D$3:$AZ$3,_xlfn.XLOOKUP(C625,[1]Baseline!$B$4:$B$91,[1]Baseline!$D$4:$AZ$91))} -> Working | E625: Service | F625: 3 | G625: 3 | H625: =I625-F625 -> 0 | I625: 3
...

Sheet Competence Heatmap
B1: Core | K1: Service | P1: Technical | BF1: Governance | BN1: Management | CE1: Security | CK1: Business
A2: Competence | B2: Asset Management | C2: Incident management | D2: Customer Service Support | E2: Problem management | F2: Personal data protection | G2: Service catalogue management | H2: Change Control | I2: Information security | J2: Service level management | K2: Availability Management | L2: Capacity management | M2: Configuration Management | N2: Continuity Management | O2: Demand Management | P2: Knowledge management | Q2: Methods and tools | R2: Release and deployment | S2: Service acceptance | T2: Stakeholder relationship management | U2: Storage management | V2: Acceptance testing | W2: Application support | X2: Data Engineering | Y2: Data Management | Z2: Data Modelling and Design | AA2: Data science | AB2: Data visualisation | AC2: Database Administration | AD2: Database Design | AE2: Hardware design | AF2: High Performance Computing | AG2: Research Computing | AH2: Information assurance | AI2: Information management | AJ2: Infrastructure | AK2: Network design | AL2: Network Analytics | AM2: Network support | AN2: Programming/software development | AO2: Real-time/embedded systems development | AP2: Requirements definition and management | AQ2: Software configuration | AR2: Software design | AS2: Solution architecture | AT2: System software | AU2: Systems and software life cycle engineering | AV2: Systems design | AW2: Systems development management | AX2: Systems installation and removal | AY2: Testing | AZ2: Innovation | BA2: Specialist Advice | BB2: Emerging technology monitoring | BC2: Systems integration and build | BD2: Audio Visual | BE2: Augmented Reality | BF2: Audit | BG2: Contract management | BH2: Feasibility assessment | BI2: Governance | BJ2: Risk management | BK2: Sourcing | BL2: Supplier management | BM2: Sustainability | BN2: Competency assessment | BO2: Financial management | BP2: Organisation design and implementation | BQ2: Organisational capability development | BR2: Organisational change management | BS2: Performance Management | BT2: Professional Development | BU2: Strategic Planning | BV2: Workforce Planning | BW2: Audit | BX2: Contract management | BY2: Feasibility assessment | BZ2: Governance | CA2: Risk management | CB2: Sourcing | CC2: Supplier management | CD2: Sustainability | CE2: Digital Forensics | CF2: Penetration testing | CG2: Security Operations | CH2: Threat Intelligence | CI2: Vulnerability assessment | CJ2: Vulnerability Research | CK2: Benefits management | CL2: Business administration | CM2: Business intelligence | CN2: Business modelling | CO2: Business process improvement | CP2: Business situation analysis | CQ2: Programme management | CR2: Project management | CS2: Quality assurance
A4: =VLOOKUP(Staff!$A1,Staff!$A$1:A$73,1,FALSE) -> Steve Arnott | B4: {=INDEX(Master!$I$2:'Master'!$I$4384,MATCH($A4&B$2,Master!$A$2:'Master'!$A$4384&Master!$C$2:'Master'!$C$4384,0))} -> 4 | C4: {=INDEX(Master!$I$2:'Master'!$I$4384,MATCH($A4&C$2,Master!$A$2:'Master'!$A$4384&Master!$C$2:'Master'!$C$4384,0))} -> 4 | D4: {=INDEX(Master!$I$2:'Master'!$I$4384,MATCH($A4&D$2,Master!$A$2:'Master'!$A$4384&Master!$C$2:'Master'!$C$4384,0))} -> 4 | E4: {=INDEX(Master!$I$2:'Master'!$I$4384,MATCH($A4&E$2,Master!$A$2:'Master'!$A$4384&Master!$C$2:'Master'!$C$4384,0))} -> 4 | F4: {=INDEX(Master!$I$2:'Master'!$I$4384,MATCH($A4&F$2,Master!$A$2:'Master'!$A$4384&Master!$C$2:'Master'!$C$4384,0))} -> 3 | G4: {=INDEX(Master!$I$2:'Master'!$I$4384,MATCH($A4&G$2,Master!$A$2:'Master'!$A$4384&Master!$C$2:'Master'!$C$4384,0))} -> 4 | H4: {=INDEX(Master!$I$2:'Master'!$I$4384,MATCH($A4&H$2,Master!$A$2:'Master'!$A$4384&Master!$C$2:'Master'!$C$4384,0))} -> 4 | I4: {=INDEX(Master!$I$2:'Master'!$I$4384,MATCH($A4&I$2,Master!$A$2:'Master'!$A$4384&Master!$C$2:'Master'!$C$4384,0))} -> 3 | ... CS4: {=INDEX(Master!$I$2:'Master'!$I$4384,MATCH($A4&CS$2,Master!$A$2:'Master'!$A$4384&Master!$C$2:'Master'!$C$4384,0))} -> 3
A5: =VLOOKUP(Staff!$A2,Staff!$A$1:A$73,1,FALSE) -> Humphrey Goodman | B5: {=INDEX(Master!$I$2:'Master'!$I$4384,MATCH($A5&B$2,Master!$A$2:'Master'!$A$4384&Master!$C$2:'Master'!$C$4384,0))} -> 3 | C5: {=INDEX(Master!$I$2:'Master'!$I$4384,MATCH($A5&C$2,Master!$A$2:'Master'!$A$4384&Master!$C$2:'Master'!$C$4384,0))} -> 4 | D5: {=INDEX(Master!$I$2:'Master'!$I$4384,MATCH($A5&D$2,Master!$A$2:'Master'!$A$4384&Master!$C$2:'Master'!$C$4384,0))} -> 4 | E5: {=INDEX(Master!$I$2:'Master'!$I$4384,MATCH($A5&E$2,Master!$A$2:'Master'!$A$4384&Master!$C$2:'Master'!$C$4384,0))} -> 4 | F5: {=INDEX(Master!$I$2:'Master'!$I$4384,MATCH($A5&F$2,Master!$A$2:'Master'!$A$4384&Master!$C$2:'Master'!$C$4384,0))} -> 4 | G5: {=INDEX(Master!$I$2:'Master'!$I$4384,MATCH($A5&G$2,Master!$A$2:'Master'!$A$4384&Master!$C$2:'Master'!$C$4384,0))} -> 4 | H5: {=INDEX(Master!$I$2:'Master'!$I$4384,MATCH($A5&H$2,Master!$A$2:'Master'!$A$4384&Master!$C$2:'Master'!$C$4384,0))} -> 3 | I5: {=INDEX(Master!$I$2:'Master'!$I$4384,MATCH($A5&I$2,Master!$A$2:'Master'!$A$4384&Master!$C$2:'Master'!$C$4384,0))} -> 3 | ... CS5: {=INDEX(Master!$I$2:'Master'!$I$4384,MATCH($A5&CS$2,Master!$A$2:'Master'!$A$4384&Master!$C$2:'Master'!$C$4384,0))} -> 2
A6: =VLOOKUP(Staff!$A3,Staff!$A$1:A$73,1,FALSE) -> Ted Hastings | B6: {=INDEX(Master!$I$2:'Master'!$I$4384,MATCH($A6&B$2,Master!$A$2:'Master'!$A$4384&Master!$C$2:'Master'!$C$4384,0))} -> 2 | C6: {=INDEX(Master!$I$2:'Master'!$I$4384,MATCH($A6&C$2,Master!$A$2:'Master'!$A$4384&Master!$C$2:'Master'!$C$4384,0))} -> 3 | D6: {=INDEX(Master!$I$2:'Master'!$I$4384,MATCH($A6&D$2,Master!$A$2:'Master'!$A$4384&Master!$C$2:'Master'!$C$4384,0))} -> 3 | E6: {=INDEX(Master!$I$2:'Master'!$I$4384,MATCH($A6&E$2,Master!$A$2:'Master'!$A$4384&Master!$C$2:'Master'!$C$4384,0))} -> 2 | F6: {=INDEX(Master!$I$2:'Master'!$I$4384,MATCH($A6&F$2,Master!$A$2:'Master'!$A$4384&Master!$C$2:'Master'!$C$4384,0))} -> 3 | G6: {=INDEX(Master!$I$2:'Master'!$I$4384,MATCH($A6&G$2,Master!$A$2:'Master'!$A$4384&Master!$C$2:'Master'!$C$4384,0))} -> 2 | H6: {=INDEX(Master!$I$2:'Master'!$I$4384,MATCH($A6&H$2,Master!$A$2:'Master'!$A$4384&Master!$C$2:'Master'!$C$4384,0))} -> 2 | I6: {=INDEX(Master!$I$2:'Master'!$I$4384,MATCH($A6&I$2,Master!$A$2:'Master'!$A$4384&Master!$C$2:'Master'!$C$4384,0))} -> 2 | ... CS6: {=INDEX(Master!$I$2:'Master'!$I$4384,MATCH($A6&CS$2,Master!$A$2:'Master'!$A$4384&Master!$C$2:'Master'!$C$4384,0))} -> 1
A7: Neville Parker | B7: {=INDEX(Master!$I$2:'Master'!$I$4384,MATCH($A7&B$2,Master!$A$2:'Master'!$A$4384&Master!$C$2:'Master'!$C$4384,0))} -> 99 | C7: {=INDEX(Master!$I$2:'Master'!$I$4384,MATCH($A7&C$2,Master!$A$2:'Master'!$A$4384&Master!$C$2:'Master'!$C$4384,0))} -> 99 | D7: {=INDEX(Master!$I$2:'Master'!$I$4384,MATCH($A7&D$2,Master!$A$2:'Master'!$A$4384&Master!$C$2:'Master'!$C$4384,0))} -> 99 | E7: {=INDEX(Master!$I$2:'Master'!$I$4384,MATCH($A7&E$2,Master!$A$2:'Master'!$A$4384&Master!$C$2:'Master'!$C$4384,0))} -> 99 | F7: {=INDEX(Master!$I$2:'Master'!$I$4384,MATCH($A7&F$2,Master!$A$2:'Master'!$A$4384&Master!$C$2:'Master'!$C$4384,0))} -> 99 | G7: {=INDEX(Master!$I$2:'Master'!$I$4384,MATCH($A7&G$2,Master!$A$2:'Master'!$A$4384&Master!$C$2:'Master'!$C$4384,0))} -> 99 | H7: {=INDEX(Master!$I$2:'Master'!$I$4384,MATCH($A7&H$2,Master!$A$2:'Master'!$A$4384&Master!$C$2:'Master'!$C$4384,0))} -> 99 | I7: {=INDEX(Master!$I$2:'Master'!$I$4384,MATCH($A7&I$2,Master!$A$2:'Master'!$A$4384&Master!$C$2:'Master'!$C$4384,0))} -> 99 | ... CS7: {=INDEX(Master!$I$2:'Master'!$I$4384,MATCH($A7&CS$2,Master!$A$2:'Master'!$A$4384&Master!$C$2:'Master'!$C$4384,0))} -> 99
A8: =VLOOKUP(Staff!$A5,Staff!$A$1:A$73,1,FALSE) -> Christopher Foyle | B8: {=INDEX(Master!$I$2:'Master'!$I$4384,MATCH($A8&B$2,Master!$A$2:'Master'!$A$4384&Master!$C$2:'Master'!$C$4384,0))} -> 3 | C8: {=INDEX(Master!$I$2:'Master'!$I$4384,MATCH($A8&C$2,Master!$A$2:'Master'!$A$4384&Master!$C$2:'Master'!$C$4384,0))} -> 4 | D8: {=INDEX(Master!$I$2:'Master'!$I$4384,MATCH($A8&D$2,Master!$A$2:'Master'!$A$4384&Master!$C$2:'Master'!$C$4384,0))} -> 4 | E8: {=INDEX(Master!$I$2:'Master'!$I$4384,MATCH($A8&E$2,Master!$A$2:'Master'!$A$4384&Master!$C$2:'Master'!$C$4384,0))} -> 2 | F8: {=INDEX(Master!$I$2:'Master'!$I$4384,MATCH($A8&F$2,Master!$A$2:'Master'!$A$4384&Master!$C$2:'Master'!$C$4384,0))} -> 3 | G8: {=INDEX(Master!$I$2:'Master'!$I$4384,MATCH($A8&G$2,Master!$A$2:'Master'!$A$4384&Master!$C$2:'Master'!$C$4384,0))} -> 3 | H8: {=INDEX(Master!$I$2:'Master'!$I$4384,MATCH($A8&H$2,Master!$A$2:'Master'!$A$4384&Master!$C$2:'Master'!$C$4384,0))} -> 3 | I8: {=INDEX(Master!$I$2:'Master'!$I$4384,MATCH($A8&I$2,Master!$A$2:'Master'!$A$4384&Master!$C$2:'Master'!$C$4384,0))} -> 3 | ... CS8: {=INDEX(Master!$I$2:'Master'!$I$4384,MATCH($A8&CS$2,Master!$A$2:'Master'!$A$4384&Master!$C$2:'Master'!$C$4384,0))} -> 1
A9: =VLOOKUP(Staff!$A6,Staff!$A$1:A$73,1,FALSE) -> Robbie Lewis | B9: {=INDEX(Master!$I$2:'Master'!$I$4384,MATCH($A9&B$2,Master!$A$2:'Master'!$A$4384&Master!$C$2:'Master'!$C$4384,0))} -> 3 | C9: {=INDEX(Master!$I$2:'Master'!$I$4384,MATCH($A9&C$2,Master!$A$2:'Master'!$A$4384&Master!$C$2:'Master'!$C$4384,0))} -> 3 | D9: {=INDEX(Master!$I$2:'Master'!$I$4384,MATCH($A9&D$2,Master!$A$2:'Master'!$A$4384&Master!$C$2:'Master'!$C$4384,0))} -> 3 | E9: {=INDEX(Master!$I$2:'Master'!$I$4384,MATCH($A9&E$2,Master!$A$2:'Master'!$A$4384&Master!$C$2:'Master'!$C$4384,0))} -> 3 | F9: {=INDEX(Master!$I$2:'Master'!$I$4384,MATCH($A9&F$2,Master!$A$2:'Master'!$A$4384&Master!$C$2:'Master'!$C$4384,0))} -> 3 | G9: {=INDEX(Master!$I$2:'Master'!$I$4384,MATCH($A9&G$2,Master!$A$2:'Master'!$A$4384&Master!$C$2:'Master'!$C$4384,0))} -> 3 | H9: {=INDEX(Master!$I$2:'Master'!$I$4384,MATCH($A9&H$2,Master!$A$2:'Master'!$A$4384&Master!$C$2:'Master'!$C$4384,0))} -> 3 | I9: {=INDEX(Master!$I$2:'Master'!$I$4384,MATCH($A9&I$2,Master!$A$2:'Master'!$A$4384&Master!$C$2:'Master'!$C$4384,0))} -> 2 | ... CS9: {=INDEX(Master!$I$2:'Master'!$I$4384,MATCH($A9&CS$2,Master!$A$2:'Master'!$A$4384&Master!$C$2:'Master'!$C$4384,0))} -> 1
A10: George Gently | B10: {=INDEX(Master!$I$2:'Master'!$I$4384,MATCH($A10&B$2,Master!$A$2:'Master'!$A$4384&Master!$C$2:'Master'!$C$4384,0))} -> 3 | C10: {=INDEX(Master!$I$2:'Master'!$I$4384,MATCH($A10&C$2,Master!$A$2:'Master'!$A$4384&Master!$C$2:'Master'!$C$4384,0))} -> 4 | D10: {=INDEX(Master!$I$2:'Master'!$I$4384,MATCH($A10&D$2,Master!$A$2:'Master'!$A$4384&Master!$C$2:'Master'!$C$4384,0))} -> 4 | E10: {=INDEX(Master!$I$2:'Master'!$I$4384,MATCH($A10&E$2,Master!$A$2:'Master'!$A$4384&Master!$C$2:'Master'!$C$4384,0))} -> 3 | F10: {=INDEX(Master!$I$2:'Master'!$I$4384,MATCH($A10&F$2,Master!$A$2:'Master'!$A$4384&Master!$C$2:'Master'!$C$4384,0))} -> 3 | G10: {=INDEX(Master!$I$2:'Master'!$I$4384,MATCH($A10&G$2,Master!$A$2:'Master'!$A$4384&Master!$C$2:'Master'!$C$4384,0))} -> 3 | H10: {=INDEX(Master!$I$2:'Master'!$I$4384,MATCH($A10&H$2,Master!$A$2:'Master'!$A$4384&Master!$C$2:'Master'!$C$4384,0))} -> 3 | I10: {=INDEX(Master!$I$2:'Master'!$I$4384,MATCH($A10&I$2,Master!$A$2:'Master'!$A$4384&Master!$C$2:'Master'!$C$4384,0))} -> 3 | ... CS10: {=INDEX(Master!$I$2:'Master'!$I$4384,MATCH($A10&CS$2,Master!$A$2:'Master'!$A$4384&Master!$C$2:'Master'!$C$4384,0))} -> 0
A11: =VLOOKUP(Staff!$A8,Staff!$A$1:A$73,1,FALSE) -> Kate Fleming | B11: {=INDEX(Master!$I$2:'Master'!$I$4384,MATCH($A11&B$2,Master!$A$2:'Master'!$A$4384&Master!$C$2:'Master'!$C$4384,0))} -> 4 | C11: {=INDEX(Master!$I$2:'Master'!$I$4384,MATCH($A11&C$2,Master!$A$2:'Master'!$A$4384&Master!$C$2:'Master'!$C$4384,0))} -> 4 | D11: {=INDEX(Master!$I$2:'Master'!$I$4384,MATCH($A11&D$2,Master!$A$2:'Master'!$A$4384&Master!$C$2:'Master'!$C$4384,0))} -> 4 | E11: {=INDEX(Master!$I$2:'Master'!$I$4384,MATCH($A11&E$2,Master!$A$2:'Master'!$A$4384&Master!$C$2:'Master'!$C$4384,0))} -> 3 | F11: {=INDEX(Master!$I$2:'Master'!$I$4384,MATCH($A11&F$2,Master!$A$2:'Master'!$A$4384&Master!$C$2:'Master'!$C$4384,0))} -> 3 | G11: {=INDEX(Master!$I$2:'Master'!$I$4384,MATCH($A11&G$2,Master!$A$2:'Master'!$A$4384&Master!$C$2:'Master'!$C$4384,0))} -> 3 | H11: {=INDEX(Master!$I$2:'Master'!$I$4384,MATCH($A11&H$2,Master!$A$2:'Master'!$A$4384&Master!$C$2:'Master'!$C$4384,0))} -> 3 | I11: {=INDEX(Master!$I$2:'Master'!$I$4384,MATCH($A11&I$2,Master!$A$2:'Master'!$A$4384&Master!$C$2:'Master'!$C$4384,0))} -> 3 | ... CS11: {=INDEX(Master!$I$2:'Master'!$I$4384,MATCH($A11&CS$2,Master!$A$2:'Master'!$A$4384&Master!$C$2:'Master'!$C$4384,0))} -> 2
A12: =VLOOKUP(Staff!$A9,Staff!$A$1:A$73,1,FALSE) -> Ellie Miller | B12: {=INDEX(Master!$I$2:'Master'!$I$4384,MATCH($A12&B$2,Master!$A$2:'Master'!$A$4384&Master!$C$2:'Master'!$C$4384,0))} -> 3 | C12: {=INDEX(Master!$I$2:'Master'!$I$4384,MATCH($A12&C$2,Master!$A$2:'Master'!$A$4384&Master!$C$2:'Master'!$C$4384,0))} -> 4 | D12: {=INDEX(Master!$I$2:'Master'!$I$4384,MATCH($A12&D$2,Master!$A$2:'Master'!$A$4384&Master!$C$2:'Master'!$C$4384,0))} -> 4 | E12: {=INDEX(Master!$I$2:'Master'!$I$4384,MATCH($A12&E$2,Master!$A$2:'Master'!$A$4384&Master!$C$2:'Master'!$C$4384,0))} -> 4 | F12: {=INDEX(Master!$I$2:'Master'!$I$4384,MATCH($A12&F$2,Master!$A$2:'Master'!$A$4384&Master!$C$2:'Master'!$C$4384,0))} -> 3 | G12: {=INDEX(Master!$I$2:'Master'!$I$4384,MATCH($A12&G$2,Master!$A$2:'Master'!$A$4384&Master!$C$2:'Master'!$C$4384,0))} -> 4 | H12: {=INDEX(Master!$I$2:'Master'!$I$4384,MATCH($A12&H$2,Master!$A$2:'Master'!$A$4384&Master!$C$2:'Master'!$C$4384,0))} -> 3 | I12: {=INDEX(Master!$I$2:'Master'!$I$4384,MATCH($A12&I$2,Master!$A$2:'Master'!$A$4384&Master!$C$2:'Master'!$C$4384,0))} -> 2 | ... CS12: {=INDEX(Master!$I$2:'Master'!$I$4384,MATCH($A12&CS$2,Master!$A$2:'Master'!$A$4384&Master!$C$2:'Master'!$C$4384,0))} -> 1
A13: =VLOOKUP(Staff!$A11,Staff!$A$1:A$73,1,FALSE) -> Cormoran Strike | B13: {=INDEX(Master!$I$2:'Master'!$I$4384,MATCH($A13&B$2,Master!$A$2:'Master'!$A$4384&Master!$C$2:'Master'!$C$4384,0))} -> 2 | C13: {=INDEX(Master!$I$2:'Master'!$I$4384,MATCH($A13&C$2,Master!$A$2:'Master'!$A$4384&Master!$C$2:'Master'!$C$4384,0))} -> 3 | D13: {=INDEX(Master!$I$2:'Master'!$I$4384,MATCH($A13&D$2,Master!$A$2:'Master'!$A$4384&Master!$C$2:'Master'!$C$4384,0))} -> 4 | E13: {=INDEX(Master!$I$2:'Master'!$I$4384,MATCH($A13&E$2,Master!$A$2:'Master'!$A$4384&Master!$C$2:'Master'!$C$4384,0))} -> 2 | F13: {=INDEX(Master!$I$2:'Master'!$I$4384,MATCH($A13&F$2,Master!$A$2:'Master'!$A$4384&Master!$C$2:'Master'!$C$4384,0))} -> 3 | G13: {=INDEX(Master!$I$2:'Master'!$I$4384,MATCH($A13&G$2,Master!$A$2:'Master'!$A$4384&Master!$C$2:'Master'!$C$4384,0))} -> 3 | H13: {=INDEX(Master!$I$2:'Master'!$I$4384,MATCH($A13&H$2,Master!$A$2:'Master'!$A$4384&Master!$C$2:'Master'!$C$4384,0))} -> 3 | I13: {=INDEX(Master!$I$2:'Master'!$I$4384,MATCH($A13&I$2,Master!$A$2:'Master'!$A$4384&Master!$C$2:'Master'!$C$4384,0))} -> 3 | ... CS13: {=INDEX(Master!$I$2:'Master'!$I$4384,MATCH($A13&CS$2,Master!$A$2:'Master'!$A$4384&Master!$C$2:'Master'!$C$4384,0))} -> 3
A14: =VLOOKUP(Staff!$A12,Staff!$A$1:A$73,1,FALSE) -> Marcella Backland | B14: {=INDEX(Master!$I$2:'Master'!$I$4384,MATCH($A14&B$2,Master!$A$2:'Master'!$A$4384&Master!$C$2:'Master'!$C$4384,0))} -> 99 | C14: {=INDEX(Master!$I$2:'Master'!$I$4384,MATCH($A14&C$2,Master!$A$2:'Master'!$A$4384&Master!$C$2:'Master'!$C$4384,0))} -> 99 | D14: {=INDEX(Master!$I$2:'Master'!$I$4384,MATCH($A14&D$2,Master!$A$2:'Master'!$A$4384&Master!$C$2:'Master'!$C$4384,0))} -> 99 | E14: {=INDEX(Master!$I$2:'Master'!$I$4384,MATCH($A14&E$2,Master!$A$2:'Master'!$A$4384&Master!$C$2:'Master'!$C$4384,0))} -> 99 | F14: {=INDEX(Master!$I$2:'Master'!$I$4384,MATCH($A14&F$2,Master!$A$2:'Master'!$A$4384&Master!$C$2:'Master'!$C$4384,0))} -> 99 | G14: {=INDEX(Master!$I$2:'Master'!$I$4384,MATCH($A14&G$2,Master!$A$2:'Master'!$A$4384&Master!$C$2:'Master'!$C$4384,0))} -> 99 | H14: {=INDEX(Master!$I$2:'Master'!$I$4384,MATCH($A14&H$2,Master!$A$2:'Master'!$A$4384&Master!$C$2:'Master'!$C$4384,0))} -> 99 | I14: {=INDEX(Master!$I$2:'Master'!$I$4384,MATCH($A14&I$2,Master!$A$2:'Master'!$A$4384&Master!$C$2:'Master'!$C$4384,0))} -> 99 | ... CS14: {=INDEX(Master!$I$2:'Master'!$I$4384,MATCH($A14&CS$2,Master!$A$2:'Master'!$A$4384&Master!$C$2:'Master'!$C$4384,0))} -> 99
A15: =VLOOKUP(Staff!$A13,Staff!$A$1:A$73,1,FALSE) -> Jack Frost | B15: {=INDEX(Master!$I$2:'Master'!$I$4384,MATCH($A15&B$2,Master!$A$2:'Master'!$A$4384&Master!$C$2:'Master'!$C$4384,0))} -> 3 | C15: {=INDEX(Master!$I$2:'Master'!$I$4384,MATCH($A15&C$2,Master!$A$2:'Master'!$A$4384&Master!$C$2:'Master'!$C$4384,0))} -> 3 | D15: {=INDEX(Master!$I$2:'Master'!$I$4384,MATCH($A15&D$2,Master!$A$2:'Master'!$A$4384&Master!$C$2:'Master'!$C$4384,0))} -> 3 | E15: {=INDEX(Master!$I$2:'Master'!$I$4384,MATCH($A15&E$2,Master!$A$2:'Master'!$A$4384&Master!$C$2:'Master'!$C$4384,0))} -> 3 | F15: {=INDEX(Master!$I$2:'Master'!$I$4384,MATCH($A15&F$2,Master!$A$2:'Master'!$A$4384&Master!$C$2:'Master'!$C$4384,0))} -> 3 | G15: {=INDEX(Master!$I$2:'Master'!$I$4384,MATCH($A15&G$2,Master!$A$2:'Master'!$A$4384&Master!$C$2:'Master'!$C$4384,0))} -> 3 | H15: {=INDEX(Master!$I$2:'Master'!$I$4384,MATCH($A15&H$2,Master!$A$2:'Master'!$A$4384&Master!$C$2:'Master'!$C$4384,0))} -> 2 | I15: {=INDEX(Master!$I$2:'Master'!$I$4384,MATCH($A15&I$2,Master!$A$2:'Master'!$A$4384&Master!$C$2:'Master'!$C$4384,0))} -> 2 | ... CS15: {=INDEX(Master!$I$2:'Master'!$I$4384,MATCH($A15&CS$2,Master!$A$2:'Master'!$A$4384&Master!$C$2:'Master'!$C$4384,0))} -> 2
A16: =VLOOKUP(Staff!$A14,Staff!$A$1:A$73,1,FALSE) -> John Watson | B16: {=INDEX(Master!$I$2:'Master'!$I$4384,MATCH($A16&B$2,Master!$A$2:'Master'!$A$4384&Master!$C$2:'Master'!$C$4384,0))} -> 3 | C16: {=INDEX(Master!$I$2:'Master'!$I$4384,MATCH($A16&C$2,Master!$A$2:'Master'!$A$4384&Master!$C$2:'Master'!$C$4384,0))} -> 3 | D16: {=INDEX(Master!$I$2:'Master'!$I$4384,MATCH($A16&D$2,Master!$A$2:'Master'!$A$4384&Master!$C$2:'Master'!$C$4384,0))} -> 3 | E16: {=INDEX(Master!$I$2:'Master'!$I$4384,MATCH($A16&E$2,Master!$A$2:'Master'!$A$4384&Master!$C$2:'Master'!$C$4384,0))} -> 3 | F16: {=INDEX(Master!$I$2:'Master'!$I$4384,MATCH($A16&F$2,Master!$A$2:'Master'!$A$4384&Master!$C$2:'Master'!$C$4384,0))} -> 3 | G16: {=INDEX(Master!$I$2:'Master'!$I$4384,MATCH($A16&G$2,Master!$A$2:'Master'!$A$4384&Master!$C$2:'Master'!$C$4384,0))} -> 2 | H16: {=INDEX(Master!$I$2:'Master'!$I$4384,MATCH($A16&H$2,Master!$A$2:'Master'!$A$4384&Master!$C$2:'Master'!$C$4384,0))} -> 3 | I16: {=INDEX(Master!$I$2:'Master'!$I$4384,MATCH($A16&I$2,Master!$A$2:'Master'!$A$4384&Master!$C$2:'Master'!$C$4384,0))} -> 2 | ... CS16: {=INDEX(Master!$I$2:'Master'!$I$4384,MATCH($A16&CS$2,Master!$A$2:'Master'!$A$4384&Master!$C$2:'Master'!$C$4384,0))} -> 0
A17: =VLOOKUP(Staff!$A15,Staff!$A$1:A$73,1,FALSE) -> Jim Taggart | B17: {=INDEX(Master!$I$2:'Master'!$I$4384,MATCH($A17&B$2,Master!$A$2:'Master'!$A$4384&Master!$C$2:'Master'!$C$4384,0))} -> 2 | C17: {=INDEX(Master!$I$2:'Master'!$I$4384,MATCH($A17&C$2,Master!$A$2:'Master'!$A$4384&Master!$C$2:'Master'!$C$4384,0))} -> 4 | D17: {=INDEX(Master!$I$2:'Master'!$I$4384,MATCH($A17&D$2,Master!$A$2:'Master'!$A$4384&Master!$C$2:'Master'!$C$4384,0))} -> 2 | E17: {=INDEX(Master!$I$2:'Master'!$I$4384,MATCH($A17&E$2,Master!$A$2:'Master'!$A$4384&Master!$C$2:'Master'!$C$4384,0))} -> 3 | F17: {=INDEX(Master!$I$2:'Master'!$I$4384,MATCH($A17&F$2,Master!$A$2:'Master'!$A$4384&Master!$C$2:'Master'!$C$4384,0))} -> 3 | G17: {=INDEX(Master!$I$2:'Master'!$I$4384,MATCH($A17&G$2,Master!$A$2:'Master'!$A$4384&Master!$C$2:'Master'!$C$4384,0))} -> 2 | H17: {=INDEX(Master!$I$2:'Master'!$I$4384,MATCH($A17&H$2,Master!$A$2:'Master'!$A$4384&Master!$C$2:'Master'!$C$4384,0))} -> 3 | I17: {=INDEX(Master!$I$2:'Master'!$I$4384,MATCH($A17&I$2,Master!$A$2:'Master'!$A$4384&Master!$C$2:'Master'!$C$4384,0))} -> 3 | ... CS17: {=INDEX(Master!$I$2:'Master'!$I$4384,MATCH($A17&CS$2,Master!$A$2:'Master'!$A$4384&Master!$C$2:'Master'!$C$4384,0))} -> 2
A18: =VLOOKUP(Staff!$A16,Staff!$A$1:A$73,1,FALSE) -> Tom Barnaby | B18: {=INDEX(Master!$I$2:'Master'!$I$4384,MATCH($A18&B$2,Master!$A$2:'Master'!$A$4384&Master!$C$2:'Master'!$C$4384,0))} -> 3 | C18: {=INDEX(Master!$I$2:'Master'!$I$4384,MATCH($A18&C$2,Master!$A$2:'Master'!$A$4384&Master!$C$2:'Master'!$C$4384,0))} -> 3 | D18: {=INDEX(Master!$I$2:'Master'!$I$4384,MATCH($A18&D$2,Master!$A$2:'Master'!$A$4384&Master!$C$2:'Master'!$C$4384,0))} -> 3 | E18: {=INDEX(Master!$I$2:'Master'!$I$4384,MATCH($A18&E$2,Master!$A$2:'Master'!$A$4384&Master!$C$2:'Master'!$C$4384,0))} -> 3 | F18: {=INDEX(Master!$I$2:'Master'!$I$4384,MATCH($A18&F$2,Master!$A$2:'Master'!$A$4384&Master!$C$2:'Master'!$C$4384,0))} -> 3 | G18: {=INDEX(Master!$I$2:'Master'!$I$4384,MATCH($A18&G$2,Master!$A$2:'Master'!$A$4384&Master!$C$2:'Master'!$C$4384,0))} -> 3 | H18: {=INDEX(Master!$I$2:'Master'!$I$4384,MATCH($A18&H$2,Master!$A$2:'Master'!$A$4384&Master!$C$2:'Master'!$C$4384,0))} -> 3 | I18: {=INDEX(Master!$I$2:'Master'!$I$4384,MATCH($A18&I$2,Master!$A$2:'Master'!$A$4384&Master!$C$2:'Master'!$C$4384,0))} -> 2 | ... CS18: {=INDEX(Master!$I$2:'Master'!$I$4384,MATCH($A18&CS$2,Master!$A$2:'Master'!$A$4384&Master!$C$2:'Master'!$C$4384,0))} -> 1
A19: =VLOOKUP(Staff!$A17,Staff!$A$1:A$73,1,FALSE) -> Endeavour Morse | B19: {=INDEX(Master!$I$2:'Master'!$I$4384,MATCH($A19&B$2,Master!$A$2:'Master'!$A$4384&Master!$C$2:'Master'!$C$4384,0))} -> 3 | C19: {=INDEX(Master!$I$2:'Master'!$I$4384,MATCH($A19&C$2,Master!$A$2:'Master'!$A$4384&Master!$C$2:'Master'!$C$4384,0))} -> 4 | D19: {=INDEX(Master!$I$2:'Master'!$I$4384,MATCH($A19&D$2,Master!$A$2:'Master'!$A$4384&Master!$C$2:'Master'!$C$4384,0))} -> 3 | E19: {=INDEX(Master!$I$2:'Master'!$I$4384,MATCH($A19&E$2,Master!$A$2:'Master'!$A$4384&Master!$C$2:'Master'!$C$4384,0))} -> 3 | F19: {=INDEX(Master!$I$2:'Master'!$I$4384,MATCH($A19&F$2,Master!$A$2:'Master'!$A$4384&Master!$C$2:'Master'!$C$4384,0))} -> 3 | G19: {=INDEX(Master!$I$2:'Master'!$I$4384,MATCH($A19&G$2,Master!$A$2:'Master'!$A$4384&Master!$C$2:'Master'!$C$4384,0))} -> 3 | H19: {=INDEX(Master!$I$2:'Master'!$I$4384,MATCH($A19&H$2,Master!$A$2:'Master'!$A$4384&Master!$C$2:'Master'!$C$4384,0))} -> 1 | I19: {=INDEX(Master!$I$2:'Master'!$I$4384,MATCH($A19&I$2,Master!$A$2:'Master'!$A$4384&Master!$C$2:'Master'!$C$4384,0))} -> 3 | ... CS19: {=INDEX(Master!$I$2:'Master'!$I$4384,MATCH($A19&CS$2,Master!$A$2:'Master'!$A$4384&Master!$C$2:'Master'!$C$4384,0))} -> 0
A20: =VLOOKUP(Staff!$A18,Staff!$A$1:A$73,1,FALSE) -> Catherine Cawood | B20: {=INDEX(Master!$I$2:'Master'!$I$4384,MATCH($A20&B$2,Master!$A$2:'Master'!$A$4384&Master!$C$2:'Master'!$C$4384,0))} -> 2 | C20: {=INDEX(Master!$I$2:'Master'!$I$4384,MATCH($A20&C$2,Master!$A$2:'Master'!$A$4384&Master!$C$2:'Master'!$C$4384,0))} -> 3 | D20: {=INDEX(Master!$I$2:'Master'!$I$4384,MATCH($A20&D$2,Master!$A$2:'Master'!$A$4384&Master!$C$2:'Master'!$C$4384,0))} -> 3 | E20: {=INDEX(Master!$I$2:'Master'!$I$4384,MATCH($A20&E$2,Master!$A$2:'Master'!$A$4384&Master!$C$2:'Master'!$C$4384,0))} -> 2 | F20: {=INDEX(Master!$I$2:'Master'!$I$4384,MATCH($A20&F$2,Master!$A$2:'Master'!$A$4384&Master!$C$2:'Master'!$C$4384,0))} -> 3 | G20: {=INDEX(Master!$I$2:'Master'!$I$4384,MATCH($A20&G$2,Master!$A$2:'Master'!$A$4384&Master!$C$2:'Master'!$C$4384,0))} -> 2 | H20: {=INDEX(Master!$I$2:'Master'!$I$4384,MATCH($A20&H$2,Master!$A$2:'Master'!$A$4384&Master!$C$2:'Master'!$C$4384,0))} -> 2 | I20: {=INDEX(Master!$I$2:'Master'!$I$4384,MATCH($A20&I$2,Master!$A$2:'Master'!$A$4384&Master!$C$2:'Master'!$C$4384,0))} -> 2 | ... CS20: {=INDEX(Master!$I$2:'Master'!$I$4384,MATCH($A20&CS$2,Master!$A$2:'Master'!$A$4384&Master!$C$2:'Master'!$C$4384,0))} -> 1
A21: =VLOOKUP(Staff!$A19,Staff!$A$1:A$73,1,FALSE) -> Cassie Stuart | B21: {=INDEX(Master!$I$2:'Master'!$I$4384,MATCH($A21&B$2,Master!$A$2:'Master'!$A$4384&Master!$C$2:'Master'!$C$4384,0))} -> 3 | C21: {=INDEX(Master!$I$2:'Master'!$I$4384,MATCH($A21&C$2,Master!$A$2:'Master'!$A$4384&Master!$C$2:'Master'!$C$4384,0))} -> 3 | D21: {=INDEX(Master!$I$2:'Master'!$I$4384,MATCH($A21&D$2,Master!$A$2:'Master'!$A$4384&Master!$C$2:'Master'!$C$4384,0))} -> 3 | E21: {=INDEX(Master!$I$2:'Master'!$I$4384,MATCH($A21&E$2,Master!$A$2:'Master'!$A$4384&Master!$C$2:'Master'!$C$4384,0))} -> 3 | F21: {=INDEX(Master!$I$2:'Master'!$I$4384,MATCH($A21&F$2,Master!$A$2:'Master'!$A$4384&Master!$C$2:'Master'!$C$4384,0))} -> 3 | G21: {=INDEX(Master!$I$2:'Master'!$I$4384,MATCH($A21&G$2,Master!$A$2:'Master'!$A$4384&Master!$C$2:'Master'!$C$4384,0))} -> 3 | H21: {=INDEX(Master!$I$2:'Master'!$I$4384,MATCH($A21&H$2,Master!$A$2:'Master'!$A$4384&Master!$C$2:'Master'!$C$4384,0))} -> 2 | I21: {=INDEX(Master!$I$2:'Master'!$I$4384,MATCH($A21&I$2,Master!$A$2:'Master'!$A$4384&Master!$C$2:'Master'!$C$4384,0))} -> 2 | ... CS21: {=INDEX(Master!$I$2:'Master'!$I$4384,MATCH($A21&CS$2,Master!$A$2:'Master'!$A$4384&Master!$C$2:'Master'!$C$4384,0))} -> 1
A22: =VLOOKUP(Staff!$A20,Staff!$A$1:A$73,1,FALSE) -> Jane Marple | B22: {=INDEX(Master!$I$2:'Master'!$I$4384,MATCH($A22&B$2,Master!$A$2:'Master'!$A$4384&Master!$C$2:'Master'!$C$4384,0))} -> 2 | C22: {=INDEX(Master!$I$2:'Master'!$I$4384,MATCH($A22&C$2,Master!$A$2:'Master'!$A$4384&Master!$C$2:'Master'!$C$4384,0))} -> 3 | D22: {=INDEX(Master!$I$2:'Master'!$I$4384,MATCH($A22&D$2,Master!$A$2:'Master'!$A$4384&Master!$C$2:'Master'!$C$4384,0))} -> 3 | E22: {=INDEX(Master!$I$2:'Master'!$I$4384,MATCH($A22&E$2,Master!$A$2:'Master'!$A$4384&Master!$C$2:'Master'!$C$4384,0))} -> 1 | F22: {=INDEX(Master!$I$2:'Master'!$I$4384,MATCH($A22&F$2,Master!$A$2:'Master'!$A$4384&Master!$C$2:'Master'!$C$4384,0))} -> 2 | G22: {=INDEX(Master!$I$2:'Master'!$I$4384,MATCH($A22&G$2,Master!$A$2:'Master'!$A$4384&Master!$C$2:'Master'!$C$4384,0))} -> 3 | H22: {=INDEX(Master!$I$2:'Master'!$I$4384,MATCH($A22&H$2,Master!$A$2:'Master'!$A$4384&Master!$C$2:'Master'!$C$4384,0))} -> 1 | I22: {=INDEX(Master!$I$2:'Master'!$I$4384,MATCH($A22&I$2,Master!$A$2:'Master'!$A$4384&Master!$C$2:'Master'!$C$4384,0))} -> 1 | ... CS22: {=INDEX(Master!$I$2:'Master'!$I$4384,MATCH($A22&CS$2,Master!$A$2:'Master'!$A$4384&Master!$C$2:'Master'!$C$4384,0))} -> 1
A23: =VLOOKUP(Staff!$A21,Staff!$A$1:A$73,1,FALSE) -> Vera Stanhope | B23: {=INDEX(Master!$I$2:'Master'!$I$4384,MATCH($A23&B$2,Master!$A$2:'Master'!$A$4384&Master!$C$2:'Master'!$C$4384,0))} -> 99 | C23: {=INDEX(Master!$I$2:'Master'!$I$4384,MATCH($A23&C$2,Master!$A$2:'Master'!$A$4384&Master!$C$2:'Master'!$C$4384,0))} -> 99 | D23: {=INDEX(Master!$I$2:'Master'!$I$4384,MATCH($A23&D$2,Master!$A$2:'Master'!$A$4384&Master!$C$2:'Master'!$C$4384,0))} -> 99 | E23: {=INDEX(Master!$I$2:'Master'!$I$4384,MATCH($A23&E$2,Master!$A$2:'Master'!$A$4384&Master!$C$2:'Master'!$C$4384,0))} -> 99 | F23: {=INDEX(Master!$I$2:'Master'!$I$4384,MATCH($A23&F$2,Master!$A$2:'Master'!$A$4384&Master!$C$2:'Master'!$C$4384,0))} -> 99 | G23: {=INDEX(Master!$I$2:'Master'!$I$4384,MATCH($A23&G$2,Master!$A$2:'Master'!$A$4384&Master!$C$2:'Master'!$C$4384,0))} -> 99 | H23: {=INDEX(Master!$I$2:'Master'!$I$4384,MATCH($A23&H$2,Master!$A$2:'Master'!$A$4384&Master!$C$2:'Master'!$C$4384,0))} -> 99 | I23: {=INDEX(Master!$I$2:'Master'!$I$4384,MATCH($A23&I$2,Master!$A$2:'Master'!$A$4384&Master!$C$2:'Master'!$C$4384,0))} -> 99 | ... CS23: {=INDEX(Master!$I$2:'Master'!$I$4384,MATCH($A23&CS$2,Master!$A$2:'Master'!$A$4384&Master!$C$2:'Master'!$C$4384,0))} -> 99
A24: =VLOOKUP(Staff!$A22,Staff!$A$1:A$73,1,FALSE) -> Frank Hathaway | B24: {=INDEX(Master!$I$2:'Master'!$I$4384,MATCH($A24&B$2,Master!$A$2:'Master'!$A$4384&Master!$C$2:'Master'!$C$4384,0))} -> 1 | C24: {=INDEX(Master!$I$2:'Master'!$I$4384,MATCH($A24&C$2,Master!$A$2:'Master'!$A$4384&Master!$C$2:'Master'!$C$4384,0))} -> 3 | D24: {=INDEX(Master!$I$2:'Master'!$I$4384,MATCH($A24&D$2,Master!$A$2:'Master'!$A$4384&Master!$C$2:'Master'!$C$4384,0))} -> 2 | E24: {=INDEX(Master!$I$2:'Master'!$I$4384,MATCH($A24&E$2,Master!$A$2:'Master'!$A$4384&Master!$C$2:'Master'!$C$4384,0))} -> 3 | F24: {=INDEX(Master!$I$2:'Master'!$I$4384,MATCH($A24&F$2,Master!$A$2:'Master'!$A$4384&Master!$C$2:'Master'!$C$4384,0))} -> 2 | G24: {=INDEX(Master!$I$2:'Master'!$I$4384,MATCH($A24&G$2,Master!$A$2:'Master'!$A$4384&Master!$C$2:'Master'!$C$4384,0))} -> 2 | H24: {=INDEX(Master!$I$2:'Master'!$I$4384,MATCH($A24&H$2,Master!$A$2:'Master'!$A$4384&Master!$C$2:'Master'!$C$4384,0))} -> 3 | I24: {=INDEX(Master!$I$2:'Master'!$I$4384,MATCH($A24&I$2,Master!$A$2:'Master'!$A$4384&Master!$C$2:'Master'!$C$4384,0))} -> 3 | ... CS24: {=INDEX(Master!$I$2:'Master'!$I$4384,MATCH($A24&CS$2,Master!$A$2:'Master'!$A$4384&Master!$C$2:'Master'!$C$4384,0))} -> 3
... A36: =VLOOKUP(Staff!$A34,Staff!$A$1:A$73,1,FALSE) -> Adam Dalgliesh | B36: {=INDEX(Master!$I$2:'Master'!$I$4384,MATCH($A36&B$2,Master!$A$2:'Master'!$A$4384&Master!$C$2:'Master'!$C$4384,0))} -> 1 | C36: {=INDEX(Master!$I$2:'Master'!$I$4384,MATCH($A36&C$2,Master!$A$2:'Master'!$A$4384&Master!$C$2:'Master'!$C$4384,0))} -> 2 | D36: {=INDEX(Master!$I$2:'Master'!$I$4384,MATCH($A36&D$2,Master!$A$2:'Master'!$A$4384&Master!$C$2:'Master'!$C$4384,0))} -> 1 | E36: {=INDEX(Master!$I$2:'Master'!$I$4384,MATCH($A36&E$2,Master!$A$2:'Master'!$A$4384&Master!$C$2:'Master'!$C$4384,0))} -> 2 | F36: {=INDEX(Master!$I$2:'Master'!$I$4384,MATCH($A36&F$2,Master!$A$2:'Master'!$A$4384&Master!$C$2:'Master'!$C$4384,0))} -> 4 | G36: {=INDEX(Master!$I$2:'Master'!$I$4384,MATCH($A36&G$2,Master!$A$2:'Master'!$A$4384&Master!$C$2:'Master'!$C$4384,0))} -> 1 | H36: {=INDEX(Master!$I$2:'Master'!$I$4384,MATCH($A36&H$2,Master!$A$2:'Master'!$A$4384&Master!$C$2:'Master'!$C$4384,0))} -> 4 | I36: {=INDEX(Master!$I$2:'Master'!$I$4384,MATCH($A36&I$2,Master!$A$2:'Master'!$A$4384&Master!$C$2:'Master'!$C$4384,0))} -> 3 | ... CS36: {=INDEX(Master!$I$2:'Master'!$I$4384,MATCH($A36&CS$2,Master!$A$2:'Master'!$A$4384&Master!$C$2:'Master'!$C$4384,0))} -> 0
A38: Count of SFIA Level 4 | B38: =COUNTIF('Competence Heatmap'!B$4:B$36,4) -> 2 | C38: =COUNTIF('Competence Heatmap'!C$4:C$36,4) -> 8 | D38: =COUNTIF('Competence Heatmap'!D$4:D$36,4) -> 7 | E38: =COUNTIF('Competence Heatmap'!E$4:E$36,4) -> 3 | F38: =COUNTIF('Competence Heatmap'!F$4:F$36,4) -> 2 | G38: =COUNTIF('Competence Heatmap'!G$4:G$36,4) -> 3 | H38: =COUNTIF('Competence Heatmap'!H$4:H$36,4) -> 2 | I38: =COUNTIF('Competence Heatmap'!I$4:I$36,4) -> 0 | ... CS38: =COUNTIF('Competence Heatmap'!CS$4:CS$36,4) -> 0
A39: Count of SFIA Level 3 | B39: =COUNTIF('Competence Heatmap'!B$4:B$36,3) -> 11 | C39: =COUNTIF('Competence Heatmap'!C$4:C$36,3) -> 11 | D39: =COUNTIF('Competence Heatmap'!D$4:D$36,3) -> 11 | E39: =COUNTIF('Competence Heatmap'!E$4:E$36,3) -> 12 | F39: =COUNTIF('Competence Heatmap'!F$4:F$36,3) -> 17 | G39: =COUNTIF('Competence Heatmap'!G$4:G$36,3) -> 12 | H39: =COUNTIF('Competence Heatmap'!H$4:H$36,3) -> 13 | I39: =COUNTIF('Competence Heatmap'!I$4:I$36,3) -> 11 | ... CS39: =COUNTIF('Competence Heatmap'!CS$4:CS$36,3) -> 4
A40: Count of SFIA Level 2 | B40: =COUNTIF('Competence Heatmap'!B$4:B$36,2) -> 8 | C40: =COUNTIF('Competence Heatmap'!C$4:C$36,2) -> 4 | D40: =COUNTIF('Competence Heatmap'!D$4:D$36,2) -> 4 | E40: =COUNTIF('Competence Heatmap'!E$4:E$36,2) -> 7 | F40: =COUNTIF('Competence Heatmap'!F$4:F$36,2) -> 5 | G40: =COUNTIF('Competence Heatmap'!G$4:G$36,2) -> 6 | H40: =COUNTIF('Competence Heatmap'!H$4:H$36,2) -> 7 | I40: =COUNTIF('Competence Heatmap'!I$4:I$36,2) -> 12 | ... CS40: =COUNTIF('Competence Heatmap'!CS$4:CS$36,2) -> 6
A41: Count of SFIA Level 1 | B41: =COUNTIF('Competence Heatmap'!B$4:B$36,4) -> 2 | C41: =COUNTIF('Competence Heatmap'!C$4:C$36,4) -> 8 | D41: =COUNTIF('Competence Heatmap'!D$4:D$36,4) -> 7 | E41: =COUNTIF('Competence Heatmap'!E$4:E$36,4) -> 3 | F41: =COUNTIF('Competence Heatmap'!F$4:F$36,4) -> 2 | G41: =COUNTIF('Competence Heatmap'!G$4:G$36,4) -> 3 | H41: =COUNTIF('Competence Heatmap'!H$4:H$36,4) -> 2 | I41: =COUNTIF('Competence Heatmap'!I$4:I$36,4) -> 0 | ... CS41: =COUNTIF('Competence Heatmap'!CS$4:CS$36,4) -> 0
A42: Count of SFIA Level 0 | B42: =COUNTIF('Competence Heatmap'!B$4:B$36,1) -> 2 | C42: =COUNTIF('Competence Heatmap'!C$4:C$36,1) -> 1 | D42: =COUNTIF('Competence Heatmap'!D$4:D$36,1) -> 1 | E42: =COUNTIF('Competence Heatmap'!E$4:E$36,1) -> 2 | F42: =COUNTIF('Competence Heatmap'!F$4:F$36,1) -> 0 | G42: =COUNTIF('Competence Heatmap'!G$4:G$36,1) -> 3 | H42: =COUNTIF('Competence Heatmap'!H$4:H$36,1) -> 2 | I42: =COUNTIF('Competence Heatmap'!I$4:I$36,1) -> 1 | ... CS42: =COUNTIF('Competence Heatmap'!CS$4:CS$36,1) -> 10
A43: Count of SFIA Level N/A | B43: =COUNTIF('Competence Heatmap'!B$4:B$36,#N/A) -> 0 | C43: =COUNTIF('Competence Heatmap'!C$4:C$36,#N/A) -> 0 | D43: =COUNTIF('Competence Heatmap'!D$4:D$36,#N/A) -> 0 | E43: =COUNTIF('Competence Heatmap'!E$4:E$36,#N/A) -> 0 | F43: =COUNTIF('Competence Heatmap'!F$4:F$36,#N/A) -> 0 | G43: =COUNTIF('Competence Heatmap'!G$4:G$36,#N/A) -> 0 | H43: =COUNTIF('Competence Heatmap'!H$4:H$36,#N/A) -> 0 | I43: =COUNTIF('Competence Heatmap'!I$4:I$36,#N/A) -> 0 | ... CS43: =COUNTIF('Competence Heatmap'!CS$4:CS$36,#N/A) -> 0

Sheet Skills Gap
A1: Competence Family | B1: Competence | C1: 4 points deficit | D1: 3 points deficit | E1: 2 points deficit | F1: 1 points deficit | G1: Required level | H1: 1 points surplus | I1: 2 points surplus | J1: 3 points surplus | K1: 4 points surplus | L1: N/A
A2: Core | B2: Asset Management | C2: =COUNTIF('Skills Gap Heatmap'!B$4:B$37,"-4") -> 0 | D2: =COUNTIF('Skills Gap Heatmap'!B$4:B$37,"-3") -> 2 | E2: =COUNTIF('Skills Gap Heatmap'!B$4:B$37,"-2") -> 2 | F2: =COUNTIF('Skills Gap Heatmap'!B$4:B$37,"-1") -> 5 | G2: =COUNTIF('Skills Gap Heatmap'!B$4:B$37,"0") -> 9 | H2: =COUNTIF('Skills Gap Heatmap'!B$4:B$37,"1") -> 4 | I2: =COUNTIF('Skills Gap Heatmap'!B$4:B$37,"2") -> 1 | J2: =COUNTIF('Skills Gap Heatmap'!B$4:B$37,"3") -> 2 | K2: =COUNTIF('Skills Gap Heatmap'!B$4:B$37,"4") -> 0 | L2: =COUNTIF('Skills Gap Heatmap'!B$4:B$37,"#N/A") -> 0
A3: Core | B3: Incident management | C3: =COUNTIF('Skills Gap Heatmap'!C$4:C$37,"-4") -> 0 | D3: =COUNTIF('Skills Gap Heatmap'!C$4:C$37,"-3") -> 0 | E3: =COUNTIF('Skills Gap Heatmap'!C$4:C$37,"-2") -> 1 | F3: =COUNTIF('Skills Gap Heatmap'!C$4:C$37,"-1") -> 4 | G3: =COUNTIF('Skills Gap Heatmap'!C$4:C$37,"0") -> 7 | H3: =COUNTIF('Skills Gap Heatmap'!C$4:C$37,"1") -> 7 | I3: =COUNTIF('Skills Gap Heatmap'!C$4:C$37,"2") -> 3 | J3: =COUNTIF('Skills Gap Heatmap'!C$4:C$37,"3") -> 2 | K3: =COUNTIF('Skills Gap Heatmap'!C$4:C$37,"4") -> 1 | L3: =COUNTIF('Skills Gap Heatmap'!C$4:C$37,"#N/A") -> 0
A4: Core | B4: Customer Service Support | C4: =COUNTIF('Skills Gap Heatmap'!D$4:D$37,"-4") -> 0 | D4: =COUNTIF('Skills Gap Heatmap'!D$4:D$37,"-3") -> 1 | E4: =COUNTIF('Skills Gap Heatmap'!D$4:D$37,"-2") -> 2 | F4: =COUNTIF('Skills Gap Heatmap'!D$4:D$37,"-1") -> 2 | G4: =COUNTIF('Skills Gap Heatmap'!D$4:D$37,"0") -> 10 | H4: =COUNTIF('Skills Gap Heatmap'!D$4:D$37,"1") -> 5 | I4: =COUNTIF('Skills Gap Heatmap'!D$4:D$37,"2") -> 2 | J4: =COUNTIF('Skills Gap Heatmap'!D$4:D$37,"3") -> 2 | K4: =COUNTIF('Skills Gap Heatmap'!D$4:D$37,"4") -> 1 | L4: =COUNTIF('Skills Gap Heatmap'!D$4:D$37,"#N/A") -> 0
A5: Core | B5: Problem management | C5: =COUNTIF('Skills Gap Heatmap'!E$4:E$37,"-4") -> 0 | D5: =COUNTIF('Skills Gap Heatmap'!E$4:E$37,"-3") -> 0 | E5: =COUNTIF('Skills Gap Heatmap'!E$4:E$37,"-2") -> 1 | F5: =COUNTIF('Skills Gap Heatmap'!E$4:E$37,"-1") -> 4 | G5: =COUNTIF('Skills Gap Heatmap'!E$4:E$37,"0") -> 11 | H5: =COUNTIF('Skills Gap Heatmap'!E$4:E$37,"1") -> 9 | I5: =COUNTIF('Skills Gap Heatmap'!E$4:E$37,"2") -> 0 | J5: =COUNTIF('Skills Gap Heatmap'!E$4:E$37,"3") -> 0 | K5: =COUNTIF('Skills Gap Heatmap'!E$4:E$37,"4") -> 0 | L5: =COUNTIF('Skills Gap Heatmap'!E$4:E$37,"#N/A") -> 0
A6: Core | B6: Personal data protection | C6: =COUNTIF('Skills Gap Heatmap'!F$4:F$37,"-4") -> 0 | D6: =COUNTIF('Skills Gap Heatmap'!F$4:F$37,"-3") -> 0 | E6: =COUNTIF('Skills Gap Heatmap'!F$4:F$37,"-2") -> 0 | F6: =COUNTIF('Skills Gap Heatmap'!F$4:F$37,"-1") -> 4 | G6: =COUNTIF('Skills Gap Heatmap'!F$4:F$37,"0") -> 12 | H6: =COUNTIF('Skills Gap Heatmap'!F$4:F$37,"1") -> 6 | I6: =COUNTIF('Skills Gap Heatmap'!F$4:F$37,"2") -> 0 | J6: =COUNTIF('Skills Gap Heatmap'!F$4:F$37,"3") -> 3 | K6: =COUNTIF('Skills Gap Heatmap'!F$4:F$37,"4") -> 0 | L6: =COUNTIF('Skills Gap Heatmap'!F$4:F$37,"#N/A") -> 0
A7: Core | B7: Service catalogue management | C7: =COUNTIF('Skills Gap Heatmap'!G$4:G$37,"-4") -> 0 | D7: =COUNTIF('Skills Gap Heatmap'!G$4:G$37,"-3") -> 0 | E7: =COUNTIF('Skills Gap Heatmap'!G$4:G$37,"-2") -> 0 | F7: =COUNTIF('Skills Gap Heatmap'!G$4:G$37,"-1") -> 6 | G7: =COUNTIF('Skills Gap Heatmap'!G$4:G$37,"0") -> 6 | H7: =COUNTIF('Skills Gap Heatmap'!G$4:G$37,"1") -> 12 | I7: =COUNTIF('Skills Gap Heatmap'!G$4:G$37,"2") -> 0 | J7: =COUNTIF('Skills Gap Heatmap'!G$4:G$37,"3") -> 1 | K7: =COUNTIF('Skills Gap Heatmap'!G$4:G$37,"4") -> 0 | L7: =COUNTIF('Skills Gap Heatmap'!G$4:G$37,"#N/A") -> 0
A8: Core | B8: Change Control | C8: =COUNTIF('Skills Gap Heatmap'!H$4:H$37,"-4") -> 0 | D8: =COUNTIF('Skills Gap Heatmap'!H$4:H$37,"-3") -> 0 | E8: =COUNTIF('Skills Gap Heatmap'!H$4:H$37,"-2") -> 2 | F8: =COUNTIF('Skills Gap Heatmap'!H$4:H$37,"-1") -> 6 | G8: =COUNTIF('Skills Gap Heatmap'!H$4:H$37,"0") -> 9 | H8: =COUNTIF('Skills Gap Heatmap'!H$4:H$37,"1") -> 6 | I8: =COUNTIF('Skills Gap Heatmap'!H$4:H$37,"2") -> 1 | J8: =COUNTIF('Skills Gap Heatmap'!H$4:H$37,"3") -> 1 | K8: =COUNTIF('Skills Gap Heatmap'!H$4:H$37,"4") -> 0 | L8: =COUNTIF('Skills Gap Heatmap'!H$4:H$37,"#N/A") -> 0
A9: Core | B9: Information security | C9: =COUNTIF('Skills Gap Heatmap'!I$4:I$37,"-4") -> 0 | D9: =COUNTIF('Skills Gap Heatmap'!I$4:I$37,"-3") -> 0 | E9: =COUNTIF('Skills Gap Heatmap'!I$4:I$37,"-2") -> 0 | F9: =COUNTIF('Skills Gap Heatmap'!I$4:I$37,"-1") -> 10 | G9: =COUNTIF('Skills Gap Heatmap'!I$4:I$37,"0") -> 10 | H9: =COUNTIF('Skills Gap Heatmap'!I$4:I$37,"1") -> 2 | I9: =COUNTIF('Skills Gap Heatmap'!I$4:I$37,"2") -> 2 | J9: =COUNTIF('Skills Gap Heatmap'!I$4:I$37,"3") -> 1 | K9: =COUNTIF('Skills Gap Heatmap'!I$4:I$37,"4") -> 0 | L9: =COUNTIF('Skills Gap Heatmap'!I$4:I$37,"#N/A") -> 0
A10: Core | B10: Service level management | C10: =COUNTIF('Skills Gap Heatmap'!J$4:J$37,"-4") -> 0 | D10: =COUNTIF('Skills Gap Heatmap'!J$4:J$37,"-3") -> 0 | E10: =COUNTIF('Skills Gap Heatmap'!J$4:J$37,"-2") -> 4 | F10: =COUNTIF('Skills Gap Heatmap'!J$4:J$37,"-1") -> 7 | G10: =COUNTIF('Skills Gap Heatmap'!J$4:J$37,"0") -> 10 | H10: =COUNTIF('Skills Gap Heatmap'!J$4:J$37,"1") -> 3 | I10: =COUNTIF('Skills Gap Heatmap'!J$4:J$37,"2") -> 0 | J10: =COUNTIF('Skills Gap Heatmap'!J$4:J$37,"3") -> 1 | K10: =COUNTIF('Skills Gap Heatmap'!J$4:J$37,"4") -> 0 | L10: =COUNTIF('Skills Gap Heatmap'!J$4:J$37,"#N/A") -> 0
A11: Service | B11: Availability Management | C11: =COUNTIF('Skills Gap Heatmap'!K$4:K$37,"-4") -> 0 | D11: =COUNTIF('Skills Gap Heatmap'!K$4:K$37,"-3") -> 1 | E11: =COUNTIF('Skills Gap Heatmap'!K$4:K$37,"-2") -> 2 | F11: =COUNTIF('Skills Gap Heatmap'!K$4:K$37,"-1") -> 9 | G11: =COUNTIF('Skills Gap Heatmap'!K$4:K$37,"0") -> 9 | H11: =COUNTIF('Skills Gap Heatmap'!K$4:K$37,"1") -> 1 | I11: =COUNTIF('Skills Gap Heatmap'!K$4:K$37,"2") -> 3 | J11: =COUNTIF('Skills Gap Heatmap'!K$4:K$37,"3") -> 0 | K11: =COUNTIF('Skills Gap Heatmap'!K$4:K$37,"4") -> 0 | L11: =COUNTIF('Skills Gap Heatmap'!K$4:K$37,"#N/A") -> 0
A12: Service | B12: Capacity management | C12: =COUNTIF('Skills Gap Heatmap'!L$4:L$37,"-4") -> 0 | D12: =COUNTIF('Skills Gap Heatmap'!L$4:L$37,"-3") -> 1 | E12: =COUNTIF('Skills Gap Heatmap'!L$4:L$37,"-2") -> 8 | F12: =COUNTIF('Skills Gap Heatmap'!L$4:L$37,"-1") -> 2 | G12: =COUNTIF('Skills Gap Heatmap'!L$4:L$37,"0") -> 7 | H12: =COUNTIF('Skills Gap Heatmap'!L$4:L$37,"1") -> 2 | I12: =COUNTIF('Skills Gap Heatmap'!L$4:L$37,"2") -> 3 | J12: =COUNTIF('Skills Gap Heatmap'!L$4:L$37,"3") -> 2 | K12: =COUNTIF('Skills Gap Heatmap'!L$4:L$37,"4") -> 0 | L12: =COUNTIF('Skills Gap Heatmap'!L$4:L$37,"#N/A") -> 0
A13: Service | B13: Configuration Management | C13: =COUNTIF('Skills Gap Heatmap'!M$4:M$37,"-4") -> 0 | D13: =COUNTIF('Skills Gap Heatmap'!M$4:M$37,"-3") -> 0 | E13: =COUNTIF('Skills Gap Heatmap'!M$4:M$37,"-2") -> 6 | F13: =COUNTIF('Skills Gap Heatmap'!M$4:M$37,"-1") -> 4 | G13: =COUNTIF('Skills Gap Heatmap'!M$4:M$37,"0") -> 8 | H13: =COUNTIF('Skills Gap Heatmap'!M$4:M$37,"1") -> 5 | I13: =COUNTIF('Skills Gap Heatmap'!M$4:M$37,"2") -> 2 | J13: =COUNTIF('Skills Gap Heatmap'!M$4:M$37,"3") -> 0 | K13: =COUNTIF('Skills Gap Heatmap'!M$4:M$37,"4") -> 0 | L13: =COUNTIF('Skills Gap Heatmap'!M$4:M$37,"#N/A") -> 0
A14: Service | B14: Continuity Management | C14: =COUNTIF('Skills Gap Heatmap'!N$4:N$37,"-4") -> 0 | D14: =COUNTIF('Skills Gap Heatmap'!N$4:N$37,"-3") -> 0 | E14: =COUNTIF('Skills Gap Heatmap'!N$4:N$37,"-2") -> 6 | F14: =COUNTIF('Skills Gap Heatmap'!N$4:N$37,"-1") -> 10 | G14: =COUNTIF('Skills Gap Heatmap'!N$4:N$37,"0") -> 6 | H14: =COUNTIF('Skills Gap Heatmap'!N$4:N$37,"1") -> 2 | I14: =COUNTIF('Skills Gap Heatmap'!N$4:N$37,"2") -> 1 | J14: =COUNTIF('Skills Gap Heatmap'!N$4:N$37,"3") -> 0 | K14: =COUNTIF('Skills Gap Heatmap'!N$4:N$37,"4") -> 0 | L14: =COUNTIF('Skills Gap Heatmap'!N$4:N$37,"#N/A") -> 0
A15: Service | B15: Demand Management | C15: =COUNTIF('Skills Gap Heatmap'!O$4:O$37,"-4") -> 0 | D15: =COUNTIF('Skills Gap Heatmap'!O$4:O$37,"-3") -> 1 | E15: =COUNTIF('Skills Gap Heatmap'!O$4:O$37,"-2") -> 5 | F15: =COUNTIF('Skills Gap Heatmap'!O$4:O$37,"-1") -> 10 | G15: =COUNTIF('Skills Gap Heatmap'!O$4:O$37,"0") -> 3 | H15: =COUNTIF('Skills Gap Heatmap'!O$4:O$37,"1") -> 5 | I15: =COUNTIF('Skills Gap Heatmap'!O$4:O$37,"2") -> 1 | J15: =COUNTIF('Skills Gap Heatmap'!O$4:O$37,"3") -> 0 | K15: =COUNTIF('Skills Gap Heatmap'!O$4:O$37,"4") -> 0 | L15: =COUNTIF('Skills Gap Heatmap'!O$4:O$37,"#N/A") -> 0
A16: Technical | B16: Knowledge management | C16: =COUNTIF('Skills Gap Heatmap'!P$4:P$37,"-4") -> 0 | D16: =COUNTIF('Skills Gap Heatmap'!P$4:P$37,"-3") -> 0 | E16: =COUNTIF('Skills Gap Heatmap'!P$4:P$37,"-2") -> 0 | F16: =COUNTIF('Skills Gap Heatmap'!P$4:P$37,"-1") -> 7 | G16: =COUNTIF('Skills Gap Heatmap'!P$4:P$37,"0") -> 10 | H16: =COUNTIF('Skills Gap Heatmap'!P$4:P$37,"1") -> 6 | I16: =COUNTIF('Skills Gap Heatmap'!P$4:P$37,"2") -> 0 | J16: =COUNTIF('Skills Gap Heatmap'!P$4:P$37,"3") -> 2 | K16: =COUNTIF('Skills Gap Heatmap'!P$4:P$37,"4") -> 0 | L16: =COUNTIF('Skills Gap Heatmap'!P$4:P$37,"#N/A") -> 0
A17: Technical | B17: Methods and tools | C17: =COUNTIF('Skills Gap Heatmap'!Q$4:Q$37,"-4") -> 0 | D17: =COUNTIF('Skills Gap Heatmap'!Q$4:Q$37,"-3") -> 0 | E17: =COUNTIF('Skills Gap Heatmap'!Q$4:Q$37,"-2") -> 1 | F17: =COUNTIF('Skills Gap Heatmap'!Q$4:Q$37,"-1") -> 5 | G17: =COUNTIF('Skills Gap Heatmap'!Q$4:Q$37,"0") -> 13 | H17: =COUNTIF('Skills Gap Heatmap'!Q$4:Q$37,"1") -> 4 | I17: =COUNTIF('Skills Gap Heatmap'!Q$4:Q$37,"2") -> 1 | J17: =COUNTIF('Skills Gap Heatmap'!Q$4:Q$37,"3") -> 0 | K17: =COUNTIF('Skills Gap Heatmap'!Q$4:Q$37,"4") -> 1 | L17: =COUNTIF('Skills Gap Heatmap'!Q$4:Q$37,"#N/A") -> 0
A18: Technical | B18: Release and deployment | C18: =COUNTIF('Skills Gap Heatmap'!R$4:R$37,"-4") -> 0 | D18: =COUNTIF('Skills Gap Heatmap'!R$4:R$37,"-3") -> 0 | E18: =COUNTIF('Skills Gap Heatmap'!R$4:R$37,"-2") -> 3 | F18: =COUNTIF('Skills Gap Heatmap'!R$4:R$37,"-1") -> 4 | G18: =COUNTIF('Skills Gap Heatmap'!R$4:R$37,"0") -> 11 | H18: =COUNTIF('Skills Gap Heatmap'!R$4:R$37,"1") -> 4 | I18: =COUNTIF('Skills Gap Heatmap'!R$4:R$37,"2") -> 1 | J18: =COUNTIF('Skills Gap Heatmap'!R$4:R$37,"3") -> 1 | K18: =COUNTIF('Skills Gap Heatmap'!R$4:R$37,"4") -> 1 | L18: =COUNTIF('Skills Gap Heatmap'!R$4:R$37,"#N/A") -> 0
A19: Technical | B19: Service acceptance | C19: =COUNTIF('Skills Gap Heatmap'!S$4:S$37,"-4") -> 0 | D19: =COUNTIF('Skills Gap Heatmap'!S$4:S$37,"-3") -> 1 | E19: =COUNTIF('Skills Gap Heatmap'!S$4:S$37,"-2") -> 2 | F19: =COUNTIF('Skills Gap Heatmap'!S$4:S$37,"-1") -> 7 | G19: =COUNTIF('Skills Gap Heatmap'!S$4:S$37,"0") -> 9 | H19: =COUNTIF('Skills Gap Heatmap'!S$4:S$37,"1") -> 3 | I19: =COUNTIF('Skills Gap Heatmap'!S$4:S$37,"2") -> 2 | J19: =COUNTIF('Skills Gap Heatmap'!S$4:S$37,"3") -> 0 | K19: =COUNTIF('Skills Gap Heatmap'!S$4:S$37,"4") -> 1 | L19: =COUNTIF('Skills Gap Heatmap'!S$4:S$37,"#N/A") -> 0
A20: Technical | B20: Stakeholder relationship management | C20: =COUNTIF('Skills Gap Heatmap'!T$4:T$37,"-4") -> 0 | D20: =COUNTIF('Skills Gap Heatmap'!T$4:T$37,"-3") -> 1 | E20: =COUNTIF('Skills Gap Heatmap'!T$4:T$37,"-2") -> 3 | F20: =COUNTIF('Skills Gap Heatmap'!T$4:T$37,"-1") -> 1 | G20: =COUNTIF('Skills Gap Heatmap'!T$4:T$37,"0") -> 14 | H20: =COUNTIF('Skills Gap Heatmap'!T$4:T$37,"1") -> 2 | I20: =COUNTIF('Skills Gap Heatmap'!T$4:T$37,"2") -> 1 | J20: =COUNTIF('Skills Gap Heatmap'!T$4:T$37,"3") -> 2 | K20: =COUNTIF('Skills Gap Heatmap'!T$4:T$37,"4") -> 1 | L20: =COUNTIF('Skills Gap Heatmap'!T$4:T$37,"#N/A") -> 0
A21: Technical | B21: Storage management | C21: =COUNTIF('Skills Gap Heatmap'!U$4:U$37,"-4") -> 0 | D21: =COUNTIF('Skills Gap Heatmap'!U$4:U$37,"-3") -> 0 | E21: =COUNTIF('Skills Gap Heatmap'!U$4:U$37,"-2") -> 2 | F21: =COUNTIF('Skills Gap Heatmap'!U$4:U$37,"-1") -> 8 | G21: =COUNTIF('Skills Gap Heatmap'!U$4:U$37,"0") -> 4 | H21: =COUNTIF('Skills Gap Heatmap'!U$4:U$37,"1") -> 5 | I21: =COUNTIF('Skills Gap Heatmap'!U$4:U$37,"2") -> 3 | J21: =COUNTIF('Skills Gap Heatmap'!U$4:U$37,"3") -> 3 | K21: =COUNTIF('Skills Gap Heatmap'!U$4:U$37,"4") -> 0 | L21: =COUNTIF('Skills Gap Heatmap'!U$4:U$37,"#N/A") -> 0
A22: Technical | B22: Acceptance testing | C22: =COUNTIF('Skills Gap Heatmap'!V$4:V$37,"-4") -> 0 | D22: =COUNTIF('Skills Gap Heatmap'!V$4:V$37,"-3") -> 0 | E22: =COUNTIF('Skills Gap Heatmap'!V$4:V$37,"-2") -> 3 | F22: =COUNTIF('Skills Gap Heatmap'!V$4:V$37,"-1") -> 5 | G22: =COUNTIF('Skills Gap Heatmap'!V$4:V$37,"0") -> 7 | H22: =COUNTIF('Skills Gap Heatmap'!V$4:V$37,"1") -> 8 | I22: =COUNTIF('Skills Gap Heatmap'!V$4:V$37,"2") -> 1 | J22: =COUNTIF('Skills Gap Heatmap'!V$4:V$37,"3") -> 1 | K22: =COUNTIF('Skills Gap Heatmap'!V$4:V$37,"4") -> 0 | L22: =COUNTIF('Skills Gap Heatmap'!V$4:V$37,"#N/A") -> 0
A23: Technical | B23: Application support | C23: =COUNTIF('Skills Gap Heatmap'!W$4:W$37,"-4") -> 0 | D23: =COUNTIF('Skills Gap Heatmap'!W$4:W$37,"-3") -> 0 | E23: =COUNTIF('Skills Gap Heatmap'!W$4:W$37,"-2") -> 0 | F23: =COUNTIF('Skills Gap Heatmap'!W$4:W$37,"-1") -> 4 | G23: =COUNTIF('Skills Gap Heatmap'!W$4:W$37,"0") -> 4 | H23: =COUNTIF('Skills Gap Heatmap'!W$4:W$37,"1") -> 5 | I23: =COUNTIF('Skills Gap Heatmap'!W$4:W$37,"2") -> 11 | J23: =COUNTIF('Skills Gap Heatmap'!W$4:W$37,"3") -> 0 | K23: =COUNTIF('Skills Gap Heatmap'!W$4:W$37,"4") -> 1 | L23: =COUNTIF('Skills Gap Heatmap'!W$4:W$37,"#N/A") -> 0
A24: Technical | B24: Data Engineering | C24: =COUNTIF('Skills Gap Heatmap'!X$4:X$37,"-4") -> 0 | D24: =COUNTIF('Skills Gap Heatmap'!X$4:X$37,"-3") -> 1 | E24: =COUNTIF('Skills Gap Heatmap'!X$4:X$37,"-2") -> 3 | F24: =COUNTIF('Skills Gap Heatmap'!X$4:X$37,"-1") -> 2 | G24: =COUNTIF('Skills Gap Heatmap'!X$4:X$37,"0") -> 6 | H24: =COUNTIF('Skills Gap Heatmap'!X$4:X$37,"1") -> 6 | I24: =COUNTIF('Skills Gap Heatmap'!X$4:X$37,"2") -> 3 | J24: =COUNTIF('Skills Gap Heatmap'!X$4:X$37,"3") -> 3 | K24: =COUNTIF('Skills Gap Heatmap'!X$4:X$37,"4") -> 1 | L24: =COUNTIF('Skills Gap Heatmap'!X$4:X$37,"#N/A") -> 0
A25: Technical | B25: Data Management | C25: =COUNTIF('Skills Gap Heatmap'!Y$4:Y$37,"-4") -> 0 | D25: =COUNTIF('Skills Gap Heatmap'!Y$4:Y$37,"-3") -> 0 | E25: =COUNTIF('Skills Gap Heatmap'!Y$4:Y$37,"-2") -> 1 | F25: =COUNTIF('Skills Gap Heatmap'!Y$4:Y$37,"-1") -> 2 | G25: =COUNTIF('Skills Gap Heatmap'!Y$4:Y$37,"0") -> 5 | H25: =COUNTIF('Skills Gap Heatmap'!Y$4:Y$37,"1") -> 7 | I25: =COUNTIF('Skills Gap Heatmap'!Y$4:Y$37,"2") -> 5 | J25: =COUNTIF('Skills Gap Heatmap'!Y$4:Y$37,"3") -> 4 | K25: =COUNTIF('Skills Gap Heatmap'!Y$4:Y$37,"4") -> 1 | L25: =COUNTIF('Skills Gap Heatmap'!Y$4:Y$37,"#N/A") -> 0
A26: Technical | B26: Data Modelling and Design | C26: =COUNTIF('Skills Gap Heatmap'!Z$4:Z$37,"-4") -> 0 | D26: =COUNTIF('Skills Gap Heatmap'!Z$4:Z$37,"-3") -> 0 | E26: =COUNTIF('Skills Gap Heatmap'!Z$4:Z$37,"-2") -> 1 | F26: =COUNTIF('Skills Gap Heatmap'!Z$4:Z$37,"-1") -> 3 | G26: =COUNTIF('Skills Gap Heatmap'!Z$4:Z$37,"0") -> 9 | H26: =COUNTIF('Skills Gap Heatmap'!Z$4:Z$37,"1") -> 6 | I26: =COUNTIF('Skills Gap Heatmap'!Z$4:Z$37,"2") -> 2 | J26: =COUNTIF('Skills Gap Heatmap'!Z$4:Z$37,"3") -> 3 | K26: =COUNTIF('Skills Gap Heatmap'!Z$4:Z$37,"4") -> 1 | L26: =COUNTIF('Skills Gap Heatmap'!Z$4:Z$37,"#N/A") -> 0
A27: Technical | B27: Data science | C27: =COUNTIF('Skills Gap Heatmap'!AA$4:AA$37,"-4") -> 0 | D27: =COUNTIF('Skills Gap Heatmap'!AA$4:AA$37,"-3") -> 1 | E27: =COUNTIF('Skills Gap Heatmap'!AA$4:AA$37,"-2") -> 2 | F27: =COUNTIF('Skills Gap Heatmap'!AA$4:AA$37,"-1") -> 7 | G27: =COUNTIF('Skills Gap Heatmap'!AA$4:AA$37,"0") -> 6 | H27: =COUNTIF('Skills Gap Heatmap'!AA$4:AA$37,"1") -> 2 | I27: =COUNTIF('Skills Gap Heatmap'!AA$4:AA$37,"2") -> 6 | J27: =COUNTIF('Skills Gap Heatmap'!AA$4:AA$37,"3") -> 0 | K27: =COUNTIF('Skills Gap Heatmap'!AA$4:AA$37,"4") -> 1 | L27: =COUNTIF('Skills Gap Heatmap'!AA$4:AA$37,"#N/A") -> 0
A28: Technical | B28: Data visualisation | C28: =COUNTIF('Skills Gap Heatmap'!AB$4:AB$37,"-4") -> 0 | D28: =COUNTIF('Skills Gap Heatmap'!AB$4:AB$37,"-3") -> 0 | E28: =COUNTIF('Skills Gap Heatmap'!AB$4:AB$37,"-2") -> 1 | F28: =COUNTIF('Skills Gap Heatmap'!AB$4:AB$37,"-1") -> 3 | G28: =COUNTIF('Skills Gap Heatmap'!AB$4:AB$37,"0") -> 7 | H28: =COUNTIF('Skills Gap Heatmap'!AB$4:AB$37,"1") -> 7 | I28: =COUNTIF('Skills Gap Heatmap'!AB$4:AB$37,"2") -> 3 | J28: =COUNTIF('Skills Gap Heatmap'!AB$4:AB$37,"3") -> 3 | K28: =COUNTIF('Skills Gap Heatmap'!AB$4:AB$37,"4") -> 1 | L28: =COUNTIF('Skills Gap Heatmap'!AB$4:AB$37,"#N/A") -> 0
A29: Technical | B29: Database Administration | C29: =COUNTIF('Skills Gap Heatmap'!AC$4:AC$37,"-4") -> 0 | D29: =COUNTIF('Skills Gap Heatmap'!AC$4:AC$37,"-3") -> 0 | E29: =COUNTIF('Skills Gap Heatmap'!AC$4:AC$37,"-2") -> 0 | F29: =COUNTIF('Skills Gap Heatmap'!AC$4:AC$37,"-1") -> 6 | G29: =COUNTIF('Skills Gap Heatmap'!AC$4:AC$37,"0") -> 7 | H29: =COUNTIF('Skills Gap Heatmap'!AC$4:AC$37,"1") -> 5 | I29: =COUNTIF('Skills Gap Heatmap'!AC$4:AC$37,"2") -> 4 | J29: =COUNTIF('Skills Gap Heatmap'!AC$4:AC$37,"3") -> 3 | K29: =COUNTIF('Skills Gap Heatmap'!AC$4:AC$37,"4") -> 0 | L29: =COUNTIF('Skills Gap Heatmap'!AC$4:AC$37,"#N/A") -> 0
A30: Technical | B30: Database Design | C30: =COUNTIF('Skills Gap Heatmap'!AD$4:AD$37,"-4") -> 0 | D30: =COUNTIF('Skills Gap Heatmap'!AD$4:AD$37,"-3") -> 0 | E30: =COUNTIF('Skills Gap Heatmap'!AD$4:AD$37,"-2") -> 2 | F30: =COUNTIF('Skills Gap Heatmap'!AD$4:AD$37,"-1") -> 4 | G30: =COUNTIF('Skills Gap Heatmap'!AD$4:AD$37,"0") -> 6 | H30: =COUNTIF('Skills Gap Heatmap'!AD$4:AD$37,"1") -> 5 | I30: =COUNTIF('Skills Gap Heatmap'!AD$4:AD$37,"2") -> 4 | J30: =COUNTIF('Skills Gap Heatmap'!AD$4:AD$37,"3") -> 4 | K30: =COUNTIF('Skills Gap Heatmap'!AD$4:AD$37,"4") -> 0 | L30: =COUNTIF('Skills Gap Heatmap'!AD$4:AD$37,"#N/A") -> 0
A31: Technical | B31: Hardware design | C31: =COUNTIF('Skills Gap Heatmap'!AE$4:AE$37,"-4") -> 0 | D31: =COUNTIF('Skills Gap Heatmap'!AE$4:AE$37,"-3") -> 0 | E31: =COUNTIF('Skills Gap Heatmap'!AE$4:AE$37,"-2") -> 2 | F31: =COUNTIF('Skills Gap Heatmap'!AE$4:AE$37,"-1") -> 2 | G31: =COUNTIF('Skills Gap Heatmap'!AE$4:AE$37,"0") -> 7 | H31: =COUNTIF('Skills Gap Heatmap'!AE$4:AE$37,"1") -> 11 | I31: =COUNTIF('Skills Gap Heatmap'!AE$4:AE$37,"2") -> 1 | J31: =COUNTIF('Skills Gap Heatmap'!AE$4:AE$37,"3") -> 2 | K31: =COUNTIF('Skills Gap Heatmap'!AE$4:AE$37,"4") -> 0 | L31: =COUNTIF('Skills Gap Heatmap'!AE$4:AE$37,"#N/A") -> 0
A32: Technical | B32: High Performance Computing | C32: =COUNTIF('Skills Gap Heatmap'!AF$4:AF$37,"-4") -> 0 | D32: =COUNTIF('Skills Gap Heatmap'!AF$4:AF$37,"-3") -> 0 | E32: =COUNTIF('Skills Gap Heatmap'!AF$4:AF$37,"-2") -> 0 | F32: =COUNTIF('Skills Gap Heatmap'!AF$4:AF$37,"-1") -> 4 | G32: =COUNTIF('Skills Gap Heatmap'!AF$4:AF$37,"0") -> 6 | H32: =COUNTIF('Skills Gap Heatmap'!AF$4:AF$37,"1") -> 13 | I32: =COUNTIF('Skills Gap Heatmap'!AF$4:AF$37,"2") -> 2 | J32: =COUNTIF('Skills Gap Heatmap'!AF$4:AF$37,"3") -> 0 | K32: =COUNTIF('Skills Gap Heatmap'!AF$4:AF$37,"4") -> 0 | L32: =COUNTIF('Skills Gap Heatmap'!AF$4:AF$37,"#N/A") -> 0
A33: Technical | B33: Research Computing | C33: =COUNTIF('Skills Gap Heatmap'!AG$4:AG$37,"-4") -> 0 | D33: =COUNTIF('Skills Gap Heatmap'!AG$4:AG$37,"-3") -> 0 | E33: =COUNTIF('Skills Gap Heatmap'!AG$4:AG$37,"-2") -> 1 | F33: =COUNTIF('Skills Gap Heatmap'!AG$4:AG$37,"-1") -> 5 | G33: =COUNTIF('Skills Gap Heatmap'!AG$4:AG$37,"0") -> 9 | H33: =COUNTIF('Skills Gap Heatmap'!AG$4:AG$37,"1") -> 7 | I33: =COUNTIF('Skills Gap Heatmap'!AG$4:AG$37,"2") -> 2 | J33: =COUNTIF('Skills Gap Heatmap'!AG$4:AG$37,"3") -> 1 | K33: =COUNTIF('Skills Gap Heatmap'!AG$4:AG$37,"4") -> 0 | L33: =COUNTIF('Skills Gap Heatmap'!AG$4:AG$37,"#N/A") -> 0
A34: Technical | B34: Information assurance | C34: =COUNTIF('Skills Gap Heatmap'!AH$4:AH$37,"-4") -> 0 | D34: =COUNTIF('Skills Gap Heatmap'!AH$4:AH$37,"-3") -> 0 | E34: =COUNTIF('Skills Gap Heatmap'!AH$4:AH$37,"-2") -> 2 | F34: =COUNTIF('Skills Gap Heatmap'!AH$4:AH$37,"-1") -> 2 | G34: =COUNTIF('Skills Gap Heatmap'!AH$4:AH$37,"0") -> 3 | H34: =COUNTIF('Skills Gap Heatmap'!AH$4:AH$37,"1") -> 7 | I34: =COUNTIF('Skills Gap Heatmap'!AH$4:AH$37,"2") -> 7 | J34: =COUNTIF('Skills Gap Heatmap'!AH$4:AH$37,"3") -> 4 | K34: =COUNTIF('Skills Gap Heatmap'!AH$4:AH$37,"4") -> 0 | L34: =COUNTIF('Skills Gap Heatmap'!AH$4:AH$37,"#N/A") -> 0
A35: Technical | B35: Information management | C35: =COUNTIF('Skills Gap Heatmap'!AI$4:AI$37,"-4") -> 0 | D35: =COUNTIF('Skills Gap Heatmap'!AI$4:AI$37,"-3") -> 0 | E35: =COUNTIF('Skills Gap Heatmap'!AI$4:AI$37,"-2") -> 0 | F35: =COUNTIF('Skills Gap Heatmap'!AI$4:AI$37,"-1") -> 4 | G35: =COUNTIF('Skills Gap Heatmap'!AI$4:AI$37,"0") -> 6 | H35: =COUNTIF('Skills Gap Heatmap'!AI$4:AI$37,"1") -> 9 | I35: =COUNTIF('Skills Gap Heatmap'!AI$4:AI$37,"2") -> 4 | J35: =COUNTIF('Skills Gap Heatmap'!AI$4:AI$37,"3") -> 2 | K35: =COUNTIF('Skills Gap Heatmap'!AI$4:AI$37,"4") -> 0 | L35: =COUNTIF('Skills Gap Heatmap'!AI$4:AI$37,"#N/A") -> 0
A36: Technical | B36: Infrastructure | C36: =COUNTIF('Skills Gap Heatmap'!AJ$4:AJ$37,"-4") -> 0 | D36: =COUNTIF('Skills Gap Heatmap'!AJ$4:AJ$37,"-3") -> 0 | E36: =COUNTIF('Skills Gap Heatmap'!AJ$4:AJ$37,"-2") -> 1 | F36: =COUNTIF('Skills Gap Heatmap'!AJ$4:AJ$37,"-1") -> 1 | G36: =COUNTIF('Skills Gap Heatmap'!AJ$4:AJ$37,"0") -> 3 | H36: =COUNTIF('Skills Gap Heatmap'!AJ$4:AJ$37,"1") -> 8 | I36: =COUNTIF('Skills Gap Heatmap'!AJ$4:AJ$37,"2") -> 6 | J36: =COUNTIF('Skills Gap Heatmap'!AJ$4:AJ$37,"3") -> 4 | K36: =COUNTIF('Skills Gap Heatmap'!AJ$4:AJ$37,"4") -> 2 | L36: =COUNTIF('Skills Gap Heatmap'!AJ$4:AJ$37,"#N/A") -> 0
A37: Technical | B37: Network design | C37: =COUNTIF('Skills Gap Heatmap'!AK$4:AK$37,"-4") -> 0 | D37: =COUNTIF('Skills Gap Heatmap'!AK$4:AK$37,"-3") -> 0 | E37: =COUNTIF('Skills Gap Heatmap'!AK$4:AK$37,"-2") -> 3 | F37: =COUNTIF('Skills Gap Heatmap'!AK$4:AK$37,"-1") -> 3 | G37: =COUNTIF('Skills Gap Heatmap'!AK$4:AK$37,"0") -> 6 | H37: =COUNTIF('Skills Gap Heatmap'!AK$4:AK$37,"1") -> 8 | I37: =COUNTIF('Skills Gap Heatmap'!AK$4:AK$37,"2") -> 3 | J37: =COUNTIF('Skills Gap Heatmap'!AK$4:AK$37,"3") -> 2 | K37: =COUNTIF('Skills Gap Heatmap'!AK$4:AK$37,"4") -> 0 | L37: =COUNTIF('Skills Gap Heatmap'!AK$4:AK$37,"#N/A") -> 0
A38: Technical | B38: Network Analytics | C38: =COUNTIF('Skills Gap Heatmap'!AL$4:AL$37,"-4") -> 0 | D38: =COUNTIF('Skills Gap Heatmap'!AL$4:AL$37,"-3") -> 0 | E38: =COUNTIF('Skills Gap Heatmap'!AL$4:AL$37,"-2") -> 1 | F38: =COUNTIF('Skills Gap Heatmap'!AL$4:AL$37,"-1") -> 2 | G38: =COUNTIF('Skills Gap Heatmap'!AL$4:AL$37,"0") -> 6 | H38: =COUNTIF('Skills Gap Heatmap'!AL$4:AL$37,"1") -> 7 | I38: =COUNTIF('Skills Gap Heatmap'!AL$4:AL$37,"2") -> 6 | J38: =COUNTIF('Skills Gap Heatmap'!AL$4:AL$37,"3") -> 3 | K38: =COUNTIF('Skills Gap Heatmap'!AL$4:AL$37,"4") -> 0 | L38: =COUNTIF('Skills Gap Heatmap'!AL$4:AL$37,"#N/A") -> 0
A39: Technical | B39: Network support | C39: =COUNTIF('Skills Gap Heatmap'!AM$4:AM$37,"-4") -> 0 | D39: =COUNTIF('Skills Gap Heatmap'!AM$4:AM$37,"-3") -> 0 | E39: =COUNTIF('Skills Gap Heatmap'!AM$4:AM$37,"-2") -> 0 | F39: =COUNTIF('Skills Gap Heatmap'!AM$4:AM$37,"-1") -> 3 | G39: =COUNTIF('Skills Gap Heatmap'!AM$4:AM$37,"0") -> 7 | H39: =COUNTIF('Skills Gap Heatmap'!AM$4:AM$37,"1") -> 2 | I39: =COUNTIF('Skills Gap Heatmap'!AM$4:AM$37,"2") -> 7 | J39: =COUNTIF('Skills Gap Heatmap'!AM$4:AM$37,"3") -> 6 | K39: =COUNTIF('Skills Gap Heatmap'!AM$4:AM$37,"4") -> 0 | L39: =COUNTIF('Skills Gap Heatmap'!AM$4:AM$37,"#N/A") -> 0
A40: Technical | B40: Programming/software development | C40: =COUNTIF('Skills Gap Heatmap'!AN$4:AN$37,"-4") -> 0 | D40: =COUNTIF('Skills Gap Heatmap'!AN$4:AN$37,"-3") -> 0 | E40: =COUNTIF('Skills Gap Heatmap'!AN$4:AN$37,"-2") -> 3 | F40: =COUNTIF('Skills Gap Heatmap'!AN$4:AN$37,"-1") -> 1 | G40: =COUNTIF('Skills Gap Heatmap'!AN$4:AN$37,"0") -> 7 | H40: =COUNTIF('Skills Gap Heatmap'!AN$4:AN$37,"1") -> 7 | I40: =COUNTIF('Skills Gap Heatmap'!AN$4:AN$37,"2") -> 3 | J40: =COUNTIF('Skills Gap Heatmap'!AN$4:AN$37,"3") -> 4 | K40: =COUNTIF('Skills Gap Heatmap'!AN$4:AN$37,"4") -> 0 | L40: =COUNTIF('Skills Gap Heatmap'!AN$4:AN$37,"#N/A") -> 0
A41: Technical | B41: Real-time/embedded systems development | C41: =COUNTIF('Skills Gap Heatmap'!AO$4:AO$37,"-4") -> 0 | D41: =COUNTIF('Skills Gap Heatmap'!AO$4:AO$37,"-3") -> 1 | E41: =COUNTIF('Skills Gap Heatmap'!AO$4:AO$37,"-2") -> 2 | F41: =COUNTIF('Skills Gap Heatmap'!AO$4:AO$37,"-1") -> 2 | G41: =COUNTIF('Skills Gap Heatmap'!AO$4:AO$37,"0") -> 10 | H41: =COUNTIF('Skills Gap Heatmap'!AO$4:AO$37,"1") -> 7 | I41: =COUNTIF('Skills Gap Heatmap'!AO$4:AO$37,"2") -> 3 | J41: =COUNTIF('Skills Gap Heatmap'!AO$4:AO$37,"3") -> 0 | K41: =COUNTIF('Skills Gap Heatmap'!AO$4:AO$37,"4") -> 0 | L41: =COUNTIF('Skills Gap Heatmap'!AO$4:AO$37,"#N/A") -> 0
A42: Technical | B42: Requirements definition and management | C42: =COUNTIF('Skills Gap Heatmap'!AP$4:AP$37,"-4") -> 0 | D42: =COUNTIF('Skills Gap Heatmap'!AP$4:AP$37,"-3") -> 0 | E42: =COUNTIF('Skills Gap Heatmap'!AP$4:AP$37,"-2") -> 2 | F42: =COUNTIF('Skills Gap Heatmap'!AP$4:AP$37,"-1") -> 4 | G42: =COUNTIF('Skills Gap Heatmap'!AP$4:AP$37,"0") -> 7 | H42: =COUNTIF('Skills Gap Heatmap'!AP$4:AP$37,"1") -> 6 | I42: =COUNTIF('Skills Gap Heatmap'!AP$4:AP$37,"2") -> 3 | J42: =COUNTIF('Skills Gap Heatmap'!AP$4:AP$37,"3") -> 3 | K42: =COUNTIF('Skills Gap Heatmap'!AP$4:AP$37,"4") -> 0 | L42: =COUNTIF('Skills Gap Heatmap'!AP$4:AP$37,"#N/A") -> 0
A43: Technical | B43: Software configuration | C43: =COUNTIF('Skills Gap Heatmap'!AQ$4:AQ$37,"-4") -> 0 | D43: =COUNTIF('Skills Gap Heatmap'!AQ$4:AQ$37,"-3") -> 0 | E43: =COUNTIF('Skills Gap Heatmap'!AQ$4:AQ$37,"-2") -> 0 | F43: =COUNTIF('Skills Gap Heatmap'!AQ$4:AQ$37,"-1") -> 3 | G43: =COUNTIF('Skills Gap Heatmap'!AQ$4:AQ$37,"0") -> 8 | H43: =COUNTIF('Skills Gap Heatmap'!AQ$4:AQ$37,"1") -> 5 | I43: =COUNTIF('Skills Gap Heatmap'!AQ$4:AQ$37,"2") -> 6 | J43: =COUNTIF('Skills Gap Heatmap'!AQ$4:AQ$37,"3") -> 3 | K43: =COUNTIF('Skills Gap Heatmap'!AQ$4:AQ$37,"4") -> 0 | L43: =COUNTIF('Skills Gap Heatmap'!AQ$4:AQ$37,"#N/A") -> 0
A44: Technical | B44: Software design | C44: =COUNTIF('Skills Gap Heatmap'!AR$4:AR$37,"-4") -> 0 | D44: =COUNTIF('Skills Gap Heatmap'!AR$4:AR$37,"-3") -> 0 | E44: =COUNTIF('Skills Gap Heatmap'!AR$4:AR$37,"-2") -> 0 | F44: =COUNTIF('Skills Gap Heatmap'!AR$4:AR$37,"-1") -> 5 | G44: =COUNTIF('Skills Gap Heatmap'!AR$4:AR$37,"0") -> 5 | H44: =COUNTIF('Skills Gap Heatmap'!AR$4:AR$37,"1") -> 9 | I44: =COUNTIF('Skills Gap Heatmap'!AR$4:AR$37,"2") -> 2 | J44: =COUNTIF('Skills Gap Heatmap'!AR$4:AR$37,"3") -> 3 | K44: =COUNTIF('Skills Gap Heatmap'!AR$4:AR$37,"4") -> 1 | L44: =COUNTIF('Skills Gap Heatmap'!AR$4:AR$37,"#N/A") -> 0
A45: Technical | B45: Solution architecture | C45: =COUNTIF('Skills Gap Heatmap'!AS$4:AS$37,"-4") -> 0 | D45: =COUNTIF('Skills Gap Heatmap'!AS$4:AS$37,"-3") -> 0 | E45: =COUNTIF('Skills Gap Heatmap'!AS$4:AS$37,"-2") -> 4 | F45: =COUNTIF('Skills Gap Heatmap'!AS$4:AS$37,"-1") -> 1 | G45: =COUNTIF('Skills Gap Heatmap'!AS$4:AS$37,"0") -> 10 | H45: =COUNTIF('Skills Gap Heatmap'!AS$4:AS$37,"1") -> 7 | I45: =COUNTIF('Skills Gap Heatmap'!AS$4:AS$37,"2") -> 0 | J45: =COUNTIF('Skills Gap Heatmap'!AS$4:AS$37,"3") -> 2 | K45: =COUNTIF('Skills Gap Heatmap'!AS$4:AS$37,"4") -> 1 | L45: =COUNTIF('Skills Gap Heatmap'!AS$4:AS$37,"#N/A") -> 0
A46: Technical | B46: System software | C46: =COUNTIF('Skills Gap Heatmap'!AT$4:AT$37,"-4") -> 0 | D46: =COUNTIF('Skills Gap Heatmap'!AT$4:AT$37,"-3") -> 0 | E46: =COUNTIF('Skills Gap Heatmap'!AT$4:AT$37,"-2") -> 3 | F46: =COUNTIF('Skills Gap Heatmap'!AT$4:AT$37,"-1") -> 4 | G46: =COUNTIF('Skills Gap Heatmap'!AT$4:AT$37,"0") -> 2 | H46: =COUNTIF('Skills Gap Heatmap'!AT$4:AT$37,"1") -> 6 | I46: =COUNTIF('Skills Gap Heatmap'!AT$4:AT$37,"2") -> 4 | J46: =COUNTIF('Skills Gap Heatmap'!AT$4:AT$37,"3") -> 3 | K46: =COUNTIF('Skills Gap Heatmap'!AT$4:AT$37,"4") -> 3 | L46: =COUNTIF('Skills Gap Heatmap'!AT$4:AT$37,"#N/A") -> 0
A47: Technical | B47: Systems and software life cycle engineering | C47: =COUNTIF('Skills Gap Heatmap'!AU$4:AU$37,"-4") -> 0 | D47: =COUNTIF('Skills Gap Heatmap'!AU$4:AU$37,"-3") -> 1 | E47: =COUNTIF('Skills Gap Heatmap'!AU$4:AU$37,"-2") -> 3 | F47: =COUNTIF('Skills Gap Heatmap'!AU$4:AU$37,"-1") -> 2 | G47: =COUNTIF('Skills Gap Heatmap'!AU$4:AU$37,"0") -> 6 | H47: =COUNTIF('Skills Gap Heatmap'!AU$4:AU$37,"1") -> 5 | I47: =COUNTIF('Skills Gap Heatmap'!AU$4:AU$37,"2") -> 6 | J47: =COUNTIF('Skills Gap Heatmap'!AU$4:AU$37,"3") -> 2 | K47: =COUNTIF('Skills Gap Heatmap'!AU$4:AU$37,"4") -> 0 | L47: =COUNTIF('Skills Gap Heatmap'!AU$4:AU$37,"#N/A") -> 0
A48: Technical | B48: Systems design | C48: =COUNTIF('Skills Gap Heatmap'!AV$4:AV$37,"-4") -> 0 | D48: =COUNTIF('Skills Gap Heatmap'!AV$4:AV$37,"-3") -> 0 | E48: =COUNTIF('Skills Gap Heatmap'!AV$4:AV$37,"-2") -> 1 | F48: =COUNTIF('Skills Gap Heatmap'!AV$4:AV$37,"-1") -> 5 | G48: =COUNTIF('Skills Gap Heatmap'!AV$4:AV$37,"0") -> 4 | H48: =COUNTIF('Skills Gap Heatmap'!AV$4:AV$37,"1") -> 8 | I48: =COUNTIF('Skills Gap Heatmap'!AV$4:AV$37,"2") -> 4 | J48: =COUNTIF('Skills Gap Heatmap'!AV$4:AV$37,"3") -> 3 | K48: =COUNTIF('Skills Gap Heatmap'!AV$4:AV$37,"4") -> 0 | L48: =COUNTIF('Skills Gap Heatmap'!AV$4:AV$37,"#N/A") -> 0
A49: Technical | B49: Systems development management | C49: =COUNTIF('Skills Gap Heatmap'!AW$4:AW$37,"-4") -> 0 | D49: =COUNTIF('Skills Gap Heatmap'!AW$4:AW$37,"-3") -> 0 | E49: =COUNTIF('Skills Gap Heatmap'!AW$4:AW$37,"-2") -> 0 | F49: =COUNTIF('Skills Gap Heatmap'!AW$4:AW$37,"-1") -> 3 | G49: =COUNTIF('Skills Gap Heatmap'!AW$4:AW$37,"0") -> 11 | H49: =COUNTIF('Skills Gap Heatmap'!AW$4:AW$37,"1") -> 5 | I49: =COUNTIF('Skills Gap Heatmap'!AW$4:AW$37,"2") -> 6 | J49: =COUNTIF('Skills Gap Heatmap'!AW$4:AW$37,"3") -> 0 | K49: =COUNTIF('Skills Gap Heatmap'!AW$4:AW$37,"4") -> 0 | L49: =COUNTIF('Skills Gap Heatmap'!AW$4:AW$37,"#N/A") -> 0
A50: Technical | B50: Systems installation and removal | C50: =COUNTIF('Skills Gap Heatmap'!AX$4:AX$37,"-4") -> 0 | D50: =COUNTIF('Skills Gap Heatmap'!AX$4:AX$37,"-3") -> 0 | E50: =COUNTIF('Skills Gap Heatmap'!AX$4:AX$37,"-2") -> 1 | F50: =COUNTIF('Skills Gap Heatmap'!AX$4:AX$37,"-1") -> 2 | G50: =COUNTIF('Skills Gap Heatmap'!AX$4:AX$37,"0") -> 2 | H50: =COUNTIF('Skills Gap Heatmap'!AX$4:AX$37,"1") -> 4 | I50: =COUNTIF('Skills Gap Heatmap'!AX$4:AX$37,"2") -> 5 | J50: =COUNTIF('Skills Gap Heatmap'!AX$4:AX$37,"3") -> 7 | K50: =COUNTIF('Skills Gap Heatmap'!AX$4:AX$37,"4") -> 4 | L50: =COUNTIF('Skills Gap Heatmap'!AX$4:AX$37,"#N/A") -> 0
A51: Technical | B51: Testing | C51: =COUNTIF('Skills Gap Heatmap'!AY$4:AY$37,"-4") -> 0 | D51: =COUNTIF('Skills Gap Heatmap'!AY$4:AY$37,"-3") -> 0 | E51: =COUNTIF('Skills Gap Heatmap'!AY$4:AY$37,"-2") -> 0 | F51: =COUNTIF('Skills Gap Heatmap'!AY$4:AY$37,"-1") -> 1 | G51: =COUNTIF('Skills Gap Heatmap'!AY$4:AY$37,"0") -> 4 | H51: =COUNTIF('Skills Gap Heatmap'!AY$4:AY$37,"1") -> 9 | I51: =COUNTIF('Skills Gap Heatmap'!AY$4:AY$37,"2") -> 4 | J51: =COUNTIF('Skills Gap Heatmap'!AY$4:AY$37,"3") -> 6 | K51: =COUNTIF('Skills Gap Heatmap'!AY$4:AY$37,"4") -> 1 | L51: =COUNTIF('Skills Gap Heatmap'!AY$4:AY$37,"#N/A") -> 0
A52: Technical | B52: Innovation | C52: =COUNTIF('Skills Gap Heatmap'!AZ$4:AZ$37,"-4") -> 0 | D52: =COUNTIF('Skills Gap Heatmap'!AZ$4:AZ$37,"-3") -> 0 | E52: =COUNTIF('Skills Gap Heatmap'!AZ$4:AZ$37,"-2") -> 2 | F52: =COUNTIF('Skills Gap Heatmap'!AZ$4:AZ$37,"-1") -> 3 | G52: =COUNTIF('Skills Gap Heatmap'!AZ$4:AZ$37,"0") -> 8 | H52: =COUNTIF('Skills Gap Heatmap'!AZ$4:AZ$37,"1") -> 3 | I52: =COUNTIF('Skills Gap Heatmap'!AZ$4:AZ$37,"2") -> 6 | J52: =COUNTIF('Skills Gap Heatmap'!AZ$4:AZ$37,"3") -> 3 | K52: =COUNTIF('Skills Gap Heatmap'!AZ$4:AZ$37,"4") -> 0 | L52: =COUNTIF('Skills Gap Heatmap'!AZ$4:AZ$37,"#N/A") -> 0
A53: Technical | B53: Specialist Advice | C53: =COUNTIF('Skills Gap Heatmap'!BA$4:BA$37,"-4") -> 0 | D53: =COUNTIF('Skills Gap Heatmap'!BA$4:BA$37,"-3") -> 0 | E53: =COUNTIF('Skills Gap Heatmap'!BA$4:BA$37,"-2") -> 1 | F53: =COUNTIF('Skills Gap Heatmap'!BA$4:BA$37,"-1") -> 2 | G53: =COUNTIF('Skills Gap Heatmap'!BA$4:BA$37,"0") -> 5 | H53: =COUNTIF('Skills Gap Heatmap'!BA$4:BA$37,"1") -> 3 | I53: =COUNTIF('Skills Gap Heatmap'!BA$4:BA$37,"2") -> 6 | J53: =COUNTIF('Skills Gap Heatmap'!BA$4:BA$37,"3") -> 6 | K53: =COUNTIF('Skills Gap Heatmap'!BA$4:BA$37,"4") -> 2 | L53: =COUNTIF('Skills Gap Heatmap'!BA$4:BA$37,"#N/A") -> 0
A54: Technical | B54: Emerging technology monitoring | C54: =COUNTIF('Skills Gap Heatmap'!BB$4:BB$37,"-4") -> 0 | D54: =COUNTIF('Skills Gap Heatmap'!BB$4:BB$37,"-3") -> 0 | E54: =COUNTIF('Skills Gap Heatmap'!BB$4:BB$37,"-2") -> 0 | F54: =COUNTIF('Skills Gap Heatmap'!BB$4:BB$37,"-1") -> 2 | G54: =COUNTIF('Skills Gap Heatmap'!BB$4:BB$37,"0") -> 6 | H54: =COUNTIF('Skills Gap Heatmap'!BB$4:BB$37,"1") -> 7 | I54: =COUNTIF('Skills Gap Heatmap'!BB$4:BB$37,"2") -> 6 | J54: =COUNTIF('Skills Gap Heatmap'!BB$4:BB$37,"3") -> 4 | K54: =COUNTIF('Skills Gap Heatmap'!BB$4:BB$37,"4") -> 0 | L54: =COUNTIF('Skills Gap Heatmap'!BB$4:BB$37,"#N/A") -> 0
A55: Technical | B55: Systems integration and build | C55: =COUNTIF('Skills Gap Heatmap'!BC$4:BC$37,"-4") -> 0 | D55: =COUNTIF('Skills Gap Heatmap'!BC$4:BC$37,"-3") -> 0 | E55: =COUNTIF('Skills Gap Heatmap'!BC$4:BC$37,"-2") -> 0 | F55: =COUNTIF('Skills Gap Heatmap'!BC$4:BC$37,"-1") -> 4 | G55: =COUNTIF('Skills Gap Heatmap'!BC$4:BC$37,"0") -> 6 | H55: =COUNTIF('Skills Gap Heatmap'!BC$4:BC$37,"1") -> 7 | I55: =COUNTIF('Skills Gap Heatmap'!BC$4:BC$37,"2") -> 5 | J55: =COUNTIF('Skills Gap Heatmap'!BC$4:BC$37,"3") -> 3 | K55: =COUNTIF('Skills Gap Heatmap'!BC$4:BC$37,"4") -> 0 | L55: =COUNTIF('Skills Gap Heatmap'!BC$4:BC$37,"#N/A") -> 0
A56: Technical | B56: Audio Visual | C56: =COUNTIF('Skills Gap Heatmap'!BD$4:BD$37,"-4") -> 0 | D56: =COUNTIF('Skills Gap Heatmap'!BD$4:BD$37,"-3") -> 0 | E56: =COUNTIF('Skills Gap Heatmap'!BD$4:BD$37,"-2") -> 0 | F56: =COUNTIF('Skills Gap Heatmap'!BD$4:BD$37,"-1") -> 2 | G56: =COUNTIF('Skills Gap Heatmap'!BD$4:BD$37,"0") -> 2 | H56: =COUNTIF('Skills Gap Heatmap'!BD$4:BD$37,"1") -> 6 | I56: =COUNTIF('Skills Gap Heatmap'!BD$4:BD$37,"2") -> 6 | J56: =COUNTIF('Skills Gap Heatmap'!BD$4:BD$37,"3") -> 8 | K56: =COUNTIF('Skills Gap Heatmap'!BD$4:BD$37,"4") -> 1 | L56: =COUNTIF('Skills Gap Heatmap'!BD$4:BD$37,"#N/A") -> 0
A57: Technical | B57: Augmented Reality | C57: =COUNTIF('Skills Gap Heatmap'!BE$4:BE$37,"-4") -> 0 | D57: =COUNTIF('Skills Gap Heatmap'!BE$4:BE$37,"-3") -> 0 | E57: =COUNTIF('Skills Gap Heatmap'!BE$4:BE$37,"-2") -> 1 | F57: =COUNTIF('Skills Gap Heatmap'!BE$4:BE$37,"-1") -> 0 | G57: =COUNTIF('Skills Gap Heatmap'!BE$4:BE$37,"0") -> 11 | H57: =COUNTIF('Skills Gap Heatmap'!BE$4:BE$37,"1") -> 10 | I57: =COUNTIF('Skills Gap Heatmap'!BE$4:BE$37,"2") -> 2 | J57: =COUNTIF('Skills Gap Heatmap'!BE$4:BE$37,"3") -> 1 | K57: =COUNTIF('Skills Gap Heatmap'!BE$4:BE$37,"4") -> 0 | L57: =COUNTIF('Skills Gap Heatmap'!BE$4:BE$37,"#N/A") -> 0
A58: Governance | B58: Audit | C58: =COUNTIF('Skills Gap Heatmap'!BF$4:BF$37,"-4") -> 0 | D58: =COUNTIF('Skills Gap Heatmap'!BF$4:BF$37,"-3") -> 0 | E58: =COUNTIF('Skills Gap Heatmap'!BF$4:BF$37,"-2") -> 8 | F58: =COUNTIF('Skills Gap Heatmap'!BF$4:BF$37,"-1") -> 4 | G58: =COUNTIF('Skills Gap Heatmap'!BF$4:BF$37,"0") -> 7 | H58: =COUNTIF('Skills Gap Heatmap'!BF$4:BF$37,"1") -> 6 | I58: =COUNTIF('Skills Gap Heatmap'!BF$4:BF$37,"2") -> 0 | J58: =COUNTIF('Skills Gap Heatmap'!BF$4:BF$37,"3") -> 0 | K58: =COUNTIF('Skills Gap Heatmap'!BF$4:BF$37,"4") -> 0 | L58: =COUNTIF('Skills Gap Heatmap'!BF$4:BF$37,"#N/A") -> 0
A59: Governance | B59: Contract management | C59: =COUNTIF('Skills Gap Heatmap'!BG$4:BG$37,"-4") -> 0 | D59: =COUNTIF('Skills Gap Heatmap'!BG$4:BG$37,"-3") -> 2 | E59: =COUNTIF('Skills Gap Heatmap'!BG$4:BG$37,"-2") -> 8 | F59: =COUNTIF('Skills Gap Heatmap'!BG$4:BG$37,"-1") -> 4 | G59: =COUNTIF('Skills Gap Heatmap'!BG$4:BG$37,"0") -> 5 | H59: =COUNTIF('Skills Gap Heatmap'!BG$4:BG$37,"1") -> 5 | I59: =COUNTIF('Skills Gap Heatmap'!BG$4:BG$37,"2") -> 1 | J59: =COUNTIF('Skills Gap Heatmap'!BG$4:BG$37,"3") -> 0 | K59: =COUNTIF('Skills Gap Heatmap'!BG$4:BG$37,"4") -> 0 | L59: =COUNTIF('Skills Gap Heatmap'!BG$4:BG$37,"#N/A") -> 0
A60: Governance | B60: Feasibility assessment | C60: =COUNTIF('Skills Gap Heatmap'!BH$4:BH$37,"-4") -> 0 | D60: =COUNTIF('Skills Gap Heatmap'!BH$4:BH$37,"-3") -> 1 | E60: =COUNTIF('Skills Gap Heatmap'!BH$4:BH$37,"-2") -> 6 | F60: =COUNTIF('Skills Gap Heatmap'!BH$4:BH$37,"-1") -> 5 | G60: =COUNTIF('Skills Gap Heatmap'!BH$4:BH$37,"0") -> 7 | H60: =COUNTIF('Skills Gap Heatmap'!BH$4:BH$37,"1") -> 4 | I60: =COUNTIF('Skills Gap Heatmap'!BH$4:BH$37,"2") -> 1 | J60: =COUNTIF('Skills Gap Heatmap'!BH$4:BH$37,"3") -> 0 | K60: =COUNTIF('Skills Gap Heatmap'!BH$4:BH$37,"4") -> 1 | L60: =COUNTIF('Skills Gap Heatmap'!BH$4:BH$37,"#N/A") -> 0
A61: Governance | B61: Governance | C61: =COUNTIF('Skills Gap Heatmap'!BI$4:BI$37,"-4") -> 0 | D61: =COUNTIF('Skills Gap Heatmap'!BI$4:BI$37,"-3") -> 0 | E61: =COUNTIF('Skills Gap Heatmap'!BI$4:BI$37,"-2") -> 4 | F61: =COUNTIF('Skills Gap Heatmap'!BI$4:BI$37,"-1") -> 6 | G61: =COUNTIF('Skills Gap Heatmap'!BI$4:BI$37,"0") -> 12 | H61: =COUNTIF('Skills Gap Heatmap'!BI$4:BI$37,"1") -> 1 | I61: =COUNTIF('Skills Gap Heatmap'!BI$4:BI$37,"2") -> 2 | J61: =COUNTIF('Skills Gap Heatmap'!BI$4:BI$37,"3") -> 0 | K61: =COUNTIF('Skills Gap Heatmap'!BI$4:BI$37,"4") -> 0 | L61: =COUNTIF('Skills Gap Heatmap'!BI$4:BI$37,"#N/A") -> 0
